Workbook
Name Applicable: [1]Fields!$A$2:$A$3
Name Applicable: 'Fields & Revisions'!$A$2:$A$3
Name Assessor: 'Fields & Revisions'!#REF!
Name Five: 'Fields & Revisions'!#REF!
Name Ten: 'Fields & Revisions'!#REF!
Name Yes: [1]Fields!$B$2:$B$6
Name Yes: 'Fields & Revisions'!$B$2:$B$6

Sheet Intro
B2: Assessed Entity Name
B3: HITRUST CSF Validated Assessment
B4: Fieldwork: xx/xx/xxxx - xx/xx/xxxx
B6: Role | C6: Name
B7: Certified Assessor:
B8: Engagement Manager:
B9: Engagement QA: | C9: Angie Jones/James Whitfield
B10: Engagement Executive: | C10: Shreesh Bhattarai/James Whitfield
B12: Sample Sizes Guidance
B13: Manual Control | C13: 10% with a minimum of 3 and a maximum of 25
B14: Automatic Control | C14: Configuration and one example
B15: Periodic Rates | C15: Annual – Most recent report
C16: Quarterly – Sample of two quarters
C17: Monthly – Sample of two months
C18: Weekly – Sample of 5 weeks
C19: Daily – Sample of 25 days
B20: Sampling Methodology | C20: Random

Sheet Assessment
A1: IQA Review Notes | B1: IQA Review Responses | C1: Control Prisma Score | D1: CAP (Yes/No) | E1: In Scope | F1: Domain Name | G1: CVID | H1: Unique ID | I1: Level | J1: Control Reference | K1: Requirement Statement | L1: Implemented Guidance | M1: Implemented Guidance: Notes | N1: Sample Suggested | O1: Shared Responsibility Matrix (SRM) v9.x | P1: Inherited Weight | Q1: Score After Inheritance Applied: Policy | R1: Score After Inheritance Applied: Process | S1: Score After Inheritance Applied: Implementation | T1: Score After Inheritance Applied: Measured | U1: Score After Inheritance Applied: Managed | V1: Control Applicable | W1: N/A Reason | X1: Maturity - Policy | Y1: Maturity - Process | Z1: Maturity - Implemented | AA1: Maturity - Measured | AB1: Maturity - Managed | AC1: Policy File Name | AD1: Policy Mapping (policy name - page/section reference) | AE1: Policy exception notes (gap or defect)Two condition rules applied | AF1: Policy Reviewed By | AG1: Process File Name | AH1: Process Mapping (policy name - page/section reference) | AI1: Process exception notes (gap or defect)Two condition rules applied | AJ1: Process Reviewed By | AK1: Implemented inquiry contact (Name - Title) | AL1: Implemented inquiry notes | AM1: Implemented Observation notes | AN1: Implemented Evidence reviewed | AO1: Implemented Notes - what's in the file and how does it address the requirement? | AP1: Implemented exception notes (gap or defect) | AQ1: Inheritance Notes - explain weight rational | AR1: Date Control Was Scored/Tested | AS1: Implemented Reviewed By | AT1: Measure/Metrix evidence reviewed | AU1: Measure/Metrix evidence explanation and notes | AV1: Measure/Metrix Management evidence reviewed | AW1: Measure/Metrix Management evidence explanation and notes | AX1: Date Write-up Helper | AY1: Inheritance Write-up Helper (if needed) | AZ1: Policy Write-up Helper | BA1: Process Write-up Helper | BB1: Inquiry Write-up Helper(if needed) | BC1: Observation Write-up Helper(if needed) | BD1: Implemented (evidence) Write-up Helper | BE1: Measured Write-up Helper | BF1: Managed Write-up Helper | BG1: Sample Write-up Helper | BH1: Completed Full Comments
C2: =IF(V2="No","Not Applicable",(IF(X2="1. Non Compliant (0%)","0",IF(X2="2. Somewhat Compliant (25%)","25",IF(X2="3. Partially Compliant (50%)","50",IF(X2="4. Mostly Compliant (75%)","75",IF(X2="5. Fully Compliant (100%)","100")))))*0.15)+((IF(Y2="1. Non Compliant (0%)","0",IF(Y2="2. Somewhat Compliant (25%)","25",IF(Y2="3. Partially Compliant (50%)","50",IF(Y2="4. Mostly Compliant (75%)","75",IF(Y2="5. Fully Compliant (100%)","100"))))))*0.2)+(IF(Z2="1. Non Compliant (0%)","0",IF(Z2="2. Somewhat Compliant (25%)","25",IF(Z2="3. Partially Compliant (50%)","50",IF(Z2="4. Mostly Compliant (75%)","75",IF(Z2="5. Fully Compliant (100%)","100")))))*0.4)+(IF(AA2="1. Non Compliant (0%)","0",IF(AA2="2. Somewhat Compliant (25%)","25",IF(AA2="3. Partially Compliant (50%)","50",IF(AA2="4. Mostly Compliant (75%)","75",IF(AA2="5. Fully Compliant (100%)","100")))))*0.1)+(IF(AB2="1. Non Compliant (0%)","0",IF(AB2="2. Somewhat Compliant (25%)","25",IF(AB2="3. Partially Compliant (50%)","50",IF(AB2="4. Mostly Compliant (75%)","75",IF(AB2="5. Fully Compliant (100%)","100")))))*0.15)) -> 0 | D2: =IF(AND((_xlfn.XLOOKUP(J2,'Fields & Revisions'!$H:$H,'Fields & Revisions'!$I:$I))<70.99,(OR(Z2="4. Mostly Compliant (75%)",Z2="3. Partially Compliant (50%)",Z2="2. Somewhat Compliant (25%)",Z2="1. Non Compliant (0%)"))),"Yes","No") -> Yes | E2: =IF(ISERROR(VLOOKUP(H2,Scope!A:A,1,FALSE)),"No","Yes") -> Yes | F2: 01 Information Protection Program | G2: 3038.0 | H2: 01.00aAISecOrganizational.1 | I2: HITRUST Security for AI System | J2: 00.a Information Security Management Program | K2: As appropriate to the organization’s AI deployment context, the stated scope and contents of the organization’s written policies, in areas including but not limited to |security administration, |data governance, |software development, |risk management, |incident management, |business continuity, and |disaster recovery,|| explicitly includes the organization’s AI systems and their AI specificities.|| | L2: Examine evidence that all evaluative elements within the requirement statement have been implemented as defined in the HITRUST scoring rubric, using a sample based test where possible for each evaluative element. Example test(s): For example, review the organizations written policies for AI systems to confirm their completeness. Further, confirm that the AI system policies contain security administration, data governance, software development, risk management, incident management, business continuity, and disaster recovery, explicitly to AI systems and their AI specificities. | M2: Documentation: Artificial Intelligence Program - defines: security administration - defines: data governance - defines: software development - defines: risk management - defines: incident management - defines: business continuity - defines: disaster recovery | N2: No | O2: =_xlfn.XLOOKUP(G2,SRMs!$A:$A,SRMs!$D:$D) -> NO INHERITANCE | P2: =IFERROR(VLOOKUP(H2,Inherited!A:B,2,FALSE),"") | Q2: =IF(MATCH(H2,Inherited!A:A),IF((((_xlfn.XLOOKUP(Assessment!#REF!,Inherited!A:A,Inherited!B:B))/100)*(_xlfn.XLOOKUP(Assessment!#REF!,Inherited!A:A,Inherited!C:C)))+(((100-(_xlfn.XLOOKUP(Assessment!#REF!,Inherited!A:A,Inherited!B:B)))/100)*IF(X2="1. Non Compliant (0%)","0",IF(X2="2. Somewhat Compliant (25%)","25",IF(X2="3. Partially Compliant (50%)","50",IF(X2="4. Mostly Compliant (75%)","75",IF(X2="5. Fully Compliant (100%)","100"))))))<=10,"0", IF(AND((((_xlfn.XLOOKUP(Assessment!#REF!,Inherited!A:A,Inherited!B:B))/100)*(_xlfn.XLOOKUP(Assessment!#REF!,Inherited!A:A,Inherited!C:C)))+(((100-(_xlfn.XLOOKUP(Assessment!#REF!,Inherited!A:A,Inherited!B:B)))/100)*IF(X2="1. Non Compliant (0%)","0",IF(X2="2. Somewhat Compliant (25%)","25",IF(X2="3. Partially Compliant (50%)","50",IF(X2="4. Mostly Compliant (75%)","75",IF(X2="5. Fully Compliant (100%)","100"))))))>=11,(((_xlfn.XLOOKUP(Assessment!#REF!,Inherited!A:A,Inherited!B:B))/100)*(_xlfn.XLOOKUP(Assessment!#REF!,Inherited!A:A,Inherited!C:C)))+(((100-(_xlfn.XLOOKUP(Assessment!#REF!,Inherited!A:A,Inherited!B:B)))/100)*IF(X2="1. Non Compliant (0%)","0",IF(X2="2. Somewhat Compliant (25%)","25",IF(X2="3. Partially Compliant (50%)","50",IF(X2="4. Mostly Compliant (75%)","75",IF(X2="5. Fully Compliant (100%)","100"))))))<=32),"25",IF(AND((((_xlfn.XLOOKUP(Assessment!#REF!,Inherited!A:A,Inherited!B:B))/100)*(_xlfn.XLOOKUP(Assessment!#REF!,Inherited!A:A,Inherited!C:C)))+(((100-(_xlfn.XLOOKUP(Assessment!#REF!,Inherited!A:A,Inherited!B:B)))/100)*IF(X2="1. Non Compliant (0%)","0",IF(X2="2. Somewhat Compliant (25%)","25",IF(X2="3. Partially Compliant (50%)","50",IF(X2="4. Mostly Compliant (75%)","75",IF(X2="5. Fully Compliant (100%)","100"))))))>=33,(((_xlfn.XLOOKUP(Assessment!#REF!,Inherited!A:A,Inherited!B:B))/100)*(_xlfn.XLOOKUP(Assessment!#REF!,Inherited!A:A,Inherited!C:C)))+(((100-(_xlfn.XLOOKUP(Assessment!#REF!,Inherited!A:A,Inherited!B:B)))/100)*IF(X2="1. Non Compliant (0%)","0",IF(X2="2. Somewhat Compliant (25%)","25",IF(X2="3. Partially Compliant (50%)","50",IF(X2="4. Mostly Compliant (75%)","75",IF(X2="5. Fully Compliant (100%)","100"))))))<=65),"50",IF(AND((((_xlfn.XLOOKUP(Assessment!#REF!,Inherited!A:A,Inherited!B:B))/100)*(_xlfn.XLOOKUP(Assessment!#REF!,Inherited!A:A,Inherited!C:C)))+(((100-(_xlfn.XLOOKUP(Assessment!#REF!,Inherited!A:A,Inherited!B:B)))/100)*IF(X2="1. Non Compliant (0%)","0",IF(X2="2. Somewhat Compliant (25%)","25",IF(X2="3. Partially Compliant (50%)","50",IF(X2="4. Mostly Compliant (75%)","75",IF(X2="5. Fully Compliant (100%)","100"))))))>=66,(((_xlfn.XLOOKUP(Assessment!#REF!,Inherited!A:A,Inherited!B:B))/100)*(_xlfn.XLOOKUP(Assessment!#REF!,Inherited!A:A,Inherited!C:C)))+(((100-(_xlfn.XLOOKUP(Assessment!#REF!,Inherited!A:A,Inherited!B:B)))/100)*IF(X2="1. Non Compliant (0%)","0",IF(X2="2. Somewhat Compliant (25%)","25",IF(X2="3. Partially Compliant (50%)","50",IF(X2="4. Mostly Compliant (75%)","75",IF(X2="5. Fully Compliant (100%)","100"))))))<=89),"75",IF((((_xlfn.XLOOKUP(Assessment!#REF!,Inherited!A:A,Inherited!B:B))/100)*(_xlfn.XLOOKUP(Assessment!#REF!,Inherited!A:A,Inherited!C:C)))+(((100-(_xlfn.XLOOKUP(Assessment!#REF!,Inherited!A:A,Inherited!B:B)))/100)*IF(X2="1. Non Compliant (0%)","0",IF(X2="2. Somewhat Compliant (25%)","25",IF(X2="3. Partially Compliant (50%)","50",IF(X2="4. Mostly Compliant (75%)","75",IF(X2="5. Fully Compliant (100%)","100"))))))>=90,"100")))))) -> #N/A | R2: =IF(MATCH(H2,Inherited!A:A),IF((((_xlfn.XLOOKUP(Assessment!#REF!,Inherited!A:A,Inherited!B:B))/100)*(_xlfn.XLOOKUP(Assessment!#REF!,Inherited!A:A,Inherited!D:D)))+(((100-(_xlfn.XLOOKUP(Assessment!#REF!,Inherited!A:A,Inherited!B:B)))/100)*IF(Y2="1. Non Compliant (0%)","0",IF(Y2="2. Somewhat Compliant (25%)","25",IF(Y2="3. Partially Compliant (50%)","50",IF(Y2="4. Mostly Compliant (75%)","75",IF(Y2="5. Fully Compliant (100%)","100"))))))<=10,"0", IF(AND((((_xlfn.XLOOKUP(Assessment!#REF!,Inherited!A:A,Inherited!B:B))/100)*(_xlfn.XLOOKUP(Assessment!#REF!,Inherited!A:A,Inherited!D:D)))+(((100-(_xlfn.XLOOKUP(Assessment!#REF!,Inherited!A:A,Inherited!B:B)))/100)*IF(Y2="1. Non Compliant (0%)","0",IF(Y2="2. Somewhat Compliant (25%)","25",IF(Y2="3. Partially Compliant (50%)","50",IF(Y2="4. Mostly Compliant (75%)","75",IF(Y2="5. Fully Compliant (100%)","100"))))))>=11,(((_xlfn.XLOOKUP(Assessment!#REF!,Inherited!A:A,Inherited!B:B))/100)*(_xlfn.XLOOKUP(Assessment!#REF!,Inherited!A:A,Inherited!D:D)))+(((100-(_xlfn.XLOOKUP(Assessment!#REF!,Inherited!A:A,Inherited!B:B)))/100)*IF(Y2="1. Non Compliant (0%)","0",IF(Y2="2. Somewhat Compliant (25%)","25",IF(Y2="3. Partially Compliant (50%)","50",IF(Y2="4. Mostly Compliant (75%)","75",IF(Y2="5. Fully Compliant (100%)","100"))))))<=32),"25",IF(AND((((_xlfn.XLOOKUP(Assessment!#REF!,Inherited!A:A,Inherited!B:B))/100)*(_xlfn.XLOOKUP(Assessment!#REF!,Inherited!A:A,Inherited!D:D)))+(((100-(_xlfn.XLOOKUP(Assessment!#REF!,Inherited!A:A,Inherited!B:B)))/100)*IF(Y2="1. Non Compliant (0%)","0",IF(Y2="2. Somewhat Compliant (25%)","25",IF(Y2="3. Partially Compliant (50%)","50",IF(Y2="4. Mostly Compliant (75%)","75",IF(Y2="5. Fully Compliant (100%)","100"))))))>=33,(((_xlfn.XLOOKUP(Assessment!#REF!,Inherited!A:A,Inherited!B:B))/100)*(_xlfn.XLOOKUP(Assessment!#REF!,Inherited!A:A,Inherited!D:D)))+(((100-(_xlfn.XLOOKUP(Assessment!#REF!,Inherited!A:A,Inherited!B:B)))/100)*IF(Y2="1. Non Compliant (0%)","0",IF(Y2="2. Somewhat Compliant (25%)","25",IF(Y2="3. Partially Compliant (50%)","50",IF(Y2="4. Mostly Compliant (75%)","75",IF(Y2="5. Fully Compliant (100%)","100"))))))<=65),"50",IF(AND((((_xlfn.XLOOKUP(Assessment!#REF!,Inherited!A:A,Inherited!B:B))/100)*(_xlfn.XLOOKUP(Assessment!#REF!,Inherited!A:A,Inherited!D:D)))+(((100-(_xlfn.XLOOKUP(Assessment!#REF!,Inherited!A:A,Inherited!B:B)))/100)*IF(Y2="1. Non Compliant (0%)","0",IF(Y2="2. Somewhat Compliant (25%)","25",IF(Y2="3. Partially Compliant (50%)","50",IF(Y2="4. Mostly Compliant (75%)","75",IF(Y2="5. Fully Compliant (100%)","100"))))))>=66,(((_xlfn.XLOOKUP(Assessment!#REF!,Inherited!A:A,Inherited!B:B))/100)*(_xlfn.XLOOKUP(Assessment!#REF!,Inherited!A:A,Inherited!D:D)))+(((100-(_xlfn.XLOOKUP(Assessment!#REF!,Inherited!A:A,Inherited!B:B)))/100)*IF(Y2="1. Non Compliant (0%)","0",IF(Y2="2. Somewhat Compliant (25%)","25",IF(Y2="3. Partially Compliant (50%)","50",IF(Y2="4. Mostly Compliant (75%)","75",IF(Y2="5. Fully Compliant (100%)","100"))))))<=89),"75",IF((((_xlfn.XLOOKUP(Assessment!#REF!,Inherited!A:A,Inherited!B:B))/100)*(_xlfn.XLOOKUP(Assessment!#REF!,Inherited!A:A,Inherited!D:D)))+(((100-(_xlfn.XLOOKUP(Assessment!#REF!,Inherited!A:A,Inherited!B:B)))/100)*IF(Y2="1. Non Compliant (0%)","0",IF(Y2="2. Somewhat Compliant (25%)","25",IF(Y2="3. Partially Compliant (50%)","50",IF(Y2="4. Mostly Compliant (75%)","75",IF(Y2="5. Fully Compliant (100%)","100"))))))>=90,"100")))))) -> #N/A | S2: =IF(MATCH(H2,Inherited!A:A),IF((((_xlfn.XLOOKUP(Assessment!#REF!,Inherited!A:A,Inherited!B:B))/100)*(_xlfn.XLOOKUP(Assessment!#REF!,Inherited!A:A,Inherited!E:E)))+(((100-(_xlfn.XLOOKUP(Assessment!#REF!,Inherited!A:A,Inherited!B:B)))/100)*IF(Z2="1. Non Compliant (0%)","0",IF(Z2="2. Somewhat Compliant (25%)","25",IF(Z2="3. Partially Compliant (50%)","50",IF(Z2="4. Mostly Compliant (75%)","75",IF(Z2="5. Fully Compliant (100%)","100"))))))<=10,"0", IF(AND((((_xlfn.XLOOKUP(Assessment!#REF!,Inherited!A:A,Inherited!B:B))/100)*(_xlfn.XLOOKUP(Assessment!#REF!,Inherited!A:A,Inherited!E:E)))+(((100-(_xlfn.XLOOKUP(Assessment!#REF!,Inherited!A:A,Inherited!B:B)))/100)*IF(Z2="1. Non Compliant (0%)","0",IF(Z2="2. Somewhat Compliant (25%)","25",IF(Z2="3. Partially Compliant (50%)","50",IF(Z2="4. Mostly Compliant (75%)","75",IF(Z2="5. Fully Compliant (100%)","100"))))))>=11,(((_xlfn.XLOOKUP(Assessment!#REF!,Inherited!A:A,Inherited!B:B))/100)*(_xlfn.XLOOKUP(Assessment!#REF!,Inherited!A:A,Inherited!E:E)))+(((100-(_xlfn.XLOOKUP(Assessment!#REF!,Inherited!A:A,Inherited!B:B)))/100)*IF(Z2="1. Non Compliant (0%)","0",IF(Z2="2. Somewhat Compliant (25%)","25",IF(Z2="3. Partially Compliant (50%)","50",IF(Z2="4. Mostly Compliant (75%)","75",IF(Z2="5. Fully Compliant (100%)","100"))))))<=32),"25",IF(AND((((_xlfn.XLOOKUP(Assessment!#REF!,Inherited!A:A,Inherited!B:B))/100)*(_xlfn.XLOOKUP(Assessment!#REF!,Inherited!A:A,Inherited!E:E)))+(((100-(_xlfn.XLOOKUP(Assessment!#REF!,Inherited!A:A,Inherited!B:B)))/100)*IF(Z2="1. Non Compliant (0%)","0",IF(Z2="2. Somewhat Compliant (25%)","25",IF(Z2="3. Partially Compliant (50%)","50",IF(Z2="4. Mostly Compliant (75%)","75",IF(Z2="5. Fully Compliant (100%)","100"))))))>=33,(((_xlfn.XLOOKUP(Assessment!#REF!,Inherited!A:A,Inherited!B:B))/100)*(_xlfn.XLOOKUP(Assessment!#REF!,Inherited!A:A,Inherited!E:E)))+(((100-(_xlfn.XLOOKUP(Assessment!#REF!,Inherited!A:A,Inherited!B:B)))/100)*IF(Z2="1. Non Compliant (0%)","0",IF(Z2="2. Somewhat Compliant (25%)","25",IF(Z2="3. Partially Compliant (50%)","50",IF(Z2="4. Mostly Compliant (75%)","75",IF(Z2="5. Fully Compliant (100%)","100"))))))<=65),"50",IF(AND((((_xlfn.XLOOKUP(Assessment!#REF!,Inherited!A:A,Inherited!B:B))/100)*(_xlfn.XLOOKUP(Assessment!#REF!,Inherited!A:A,Inherited!E:E)))+(((100-(_xlfn.XLOOKUP(Assessment!#REF!,Inherited!A:A,Inherited!B:B)))/100)*IF(Z2="1. Non Compliant (0%)","0",IF(Z2="2. Somewhat Compliant (25%)","25",IF(Z2="3. Partially Compliant (50%)","50",IF(Z2="4. Mostly Compliant (75%)","75",IF(Z2="5. Fully Compliant (100%)","100"))))))>=66,(((_xlfn.XLOOKUP(Assessment!#REF!,Inherited!A:A,Inherited!B:B))/100)*(_xlfn.XLOOKUP(Assessment!#REF!,Inherited!A:A,Inherited!E:E)))+(((100-(_xlfn.XLOOKUP(Assessment!#REF!,Inherited!A:A,Inherited!B:B)))/100)*IF(Z2="1. Non Compliant (0%)","0",IF(Z2="2. Somewhat Compliant (25%)","25",IF(Z2="3. Partially Compliant (50%)","50",IF(Z2="4. Mostly Compliant (75%)","75",IF(Z2="5. Fully Compliant (100%)","100"))))))<=89),"75",IF((((_xlfn.XLOOKUP(Assessment!#REF!,Inherited!A:A,Inherited!B:B))/100)*(_xlfn.XLOOKUP(Assessment!#REF!,Inherited!A:A,Inherited!E:E)))+(((100-(_xlfn.XLOOKUP(Assessment!#REF!,Inherited!A:A,Inherited!B:B)))/100)*IF(Z2="1. Non Compliant (0%)","0",IF(Z2="2. Somewhat Compliant (25%)","25",IF(Z2="3. Partially Compliant (50%)","50",IF(Z2="4. Mostly Compliant (75%)","75",IF(Z2="5. Fully Compliant (100%)","100"))))))>=90,"100")))))) -> #N/A | T2: =IF(MATCH(H2,Inherited!A:A),IF((((_xlfn.XLOOKUP(Assessment!#REF!,Inherited!A:A,Inherited!B:B))/100)*(_xlfn.XLOOKUP(Assessment!#REF!,Inherited!A:A,Inherited!F:F)))+(((100-(_xlfn.XLOOKUP(Assessment!#REF!,Inherited!A:A,Inherited!B:B)))/100)*IF(AA2="1. Non Compliant (0%)","0",IF(AA2="2. Somewhat Compliant (25%)","25",IF(AA2="3. Partially Compliant (50%)","50",IF(AA2="4. Mostly Compliant (75%)","75",IF(AA2="5. Fully Compliant (100%)","100"))))))<=10,"0", IF(AND((((_xlfn.XLOOKUP(Assessment!#REF!,Inherited!A:A,Inherited!B:B))/100)*(_xlfn.XLOOKUP(Assessment!#REF!,Inherited!A:A,Inherited!F:F)))+(((100-(_xlfn.XLOOKUP(Assessment!#REF!,Inherited!A:A,Inherited!B:B)))/100)*IF(AA2="1. Non Compliant (0%)","0",IF(AA2="2. Somewhat Compliant (25%)","25",IF(AA2="3. Partially Compliant (50%)","50",IF(AA2="4. Mostly Compliant (75%)","75",IF(AA2="5. Fully Compliant (100%)","100"))))))>=11,(((_xlfn.XLOOKUP(Assessment!#REF!,Inherited!A:A,Inherited!B:B))/100)*(_xlfn.XLOOKUP(Assessment!#REF!,Inherited!A:A,Inherited!F:F)))+(((100-(_xlfn.XLOOKUP(Assessment!#REF!,Inherited!A:A,Inherited!B:B)))/100)*IF(AA2="1. Non Compliant (0%)","0",IF(AA2="2. Somewhat Compliant (25%)","25",IF(AA2="3. Partially Compliant (50%)","50",IF(AA2="4. Mostly Compliant (75%)","75",IF(AA2="5. Fully Compliant (100%)","100"))))))<=32),"25",IF(AND((((_xlfn.XLOOKUP(Assessment!#REF!,Inherited!A:A,Inherited!B:B))/100)*(_xlfn.XLOOKUP(Assessment!#REF!,Inherited!A:A,Inherited!F:F)))+(((100-(_xlfn.XLOOKUP(Assessment!#REF!,Inherited!A:A,Inherited!B:B)))/100)*IF(AA2="1. Non Compliant (0%)","0",IF(AA2="2. Somewhat Compliant (25%)","25",IF(AA2="3. Partially Compliant (50%)","50",IF(AA2="4. Mostly Compliant (75%)","75",IF(AA2="5. Fully Compliant (100%)","100"))))))>=33,(((_xlfn.XLOOKUP(Assessment!#REF!,Inherited!A:A,Inherited!B:B))/100)*(_xlfn.XLOOKUP(Assessment!#REF!,Inherited!A:A,Inherited!F:F)))+(((100-(_xlfn.XLOOKUP(Assessment!#REF!,Inherited!A:A,Inherited!B:B)))/100)*IF(AA2="1. Non Compliant (0%)","0",IF(AA2="2. Somewhat Compliant (25%)","25",IF(AA2="3. Partially Compliant (50%)","50",IF(AA2="4. Mostly Compliant (75%)","75",IF(AA2="5. Fully Compliant (100%)","100"))))))<=65),"50",IF(AND((((_xlfn.XLOOKUP(Assessment!#REF!,Inherited!A:A,Inherited!B:B))/100)*(_xlfn.XLOOKUP(Assessment!#REF!,Inherited!A:A,Inherited!F:F)))+(((100-(_xlfn.XLOOKUP(Assessment!#REF!,Inherited!A:A,Inherited!B:B)))/100)*IF(AA2="1. Non Compliant (0%)","0",IF(AA2="2. Somewhat Compliant (25%)","25",IF(AA2="3. Partially Compliant (50%)","50",IF(AA2="4. Mostly Compliant (75%)","75",IF(AA2="5. Fully Compliant (100%)","100"))))))>=66,(((_xlfn.XLOOKUP(Assessment!#REF!,Inherited!A:A,Inherited!B:B))/100)*(_xlfn.XLOOKUP(Assessment!#REF!,Inherited!A:A,Inherited!F:F)))+(((100-(_xlfn.XLOOKUP(Assessment!#REF!,Inherited!A:A,Inherited!B:B)))/100)*IF(AA2="1. Non Compliant (0%)","0",IF(AA2="2. Somewhat Compliant (25%)","25",IF(AA2="3. Partially Compliant (50%)","50",IF(AA2="4. Mostly Compliant (75%)","75",IF(AA2="5. Fully Compliant (100%)","100"))))))<=89),"75",IF((((_xlfn.XLOOKUP(Assessment!#REF!,Inherited!A:A,Inherited!B:B))/100)*(_xlfn.XLOOKUP(Assessment!#REF!,Inherited!A:A,Inherited!F:F)))+(((100-(_xlfn.XLOOKUP(Assessment!#REF!,Inherited!A:A,Inherited!B:B)))/100)*IF(AA2="1. Non Compliant (0%)","0",IF(AA2="2. Somewhat Compliant (25%)","25",IF(AA2="3. Partially Compliant (50%)","50",IF(AA2="4. Mostly Compliant (75%)","75",IF(AA2="5. Fully Compliant (100%)","100"))))))>=90,"100")))))) -> #N/A | U2: =IF(MATCH(H2,Inherited!A:A),IF((((_xlfn.XLOOKUP(Assessment!#REF!,Inherited!A:A,Inherited!B:B))/100)*(_xlfn.XLOOKUP(Assessment!#REF!,Inherited!A:A,Inherited!G:G)))+(((100-(_xlfn.XLOOKUP(Assessment!#REF!,Inherited!A:A,Inherited!B:B)))/100)*IF(AB2="1. Non Compliant (0%)","0",IF(AB2="2. Somewhat Compliant (25%)","25",IF(AB2="3. Partially Compliant (50%)","50",IF(AB2="4. Mostly Compliant (75%)","75",IF(AB2="5. Fully Compliant (100%)","100"))))))<=10,"0", IF(AND((((_xlfn.XLOOKUP(Assessment!#REF!,Inherited!A:A,Inherited!B:B))/100)*(_xlfn.XLOOKUP(Assessment!#REF!,Inherited!A:A,Inherited!G:G)))+(((100-(_xlfn.XLOOKUP(Assessment!#REF!,Inherited!A:A,Inherited!B:B)))/100)*IF(AB2="1. Non Compliant (0%)","0",IF(AB2="2. Somewhat Compliant (25%)","25",IF(AB2="3. Partially Compliant (50%)","50",IF(AB2="4. Mostly Compliant (75%)","75",IF(AB2="5. Fully Compliant (100%)","100"))))))>=11,(((_xlfn.XLOOKUP(Assessment!#REF!,Inherited!A:A,Inherited!B:B))/100)*(_xlfn.XLOOKUP(Assessment!#REF!,Inherited!A:A,Inherited!G:G)))+(((100-(_xlfn.XLOOKUP(Assessment!#REF!,Inherited!A:A,Inherited!B:B)))/100)*IF(AB2="1. Non Compliant (0%)","0",IF(AB2="2. Somewhat Compliant (25%)","25",IF(AB2="3. Partially Compliant (50%)","50",IF(AB2="4. Mostly Compliant (75%)","75",IF(AB2="5. Fully Compliant (100%)","100"))))))<=32),"25",IF(AND((((_xlfn.XLOOKUP(Assessment!#REF!,Inherited!A:A,Inherited!B:B))/100)*(_xlfn.XLOOKUP(Assessment!#REF!,Inherited!A:A,Inherited!G:G)))+(((100-(_xlfn.XLOOKUP(Assessment!#REF!,Inherited!A:A,Inherited!B:B)))/100)*IF(AB2="1. Non Compliant (0%)","0",IF(AB2="2. Somewhat Compliant (25%)","25",IF(AB2="3. Partially Compliant (50%)","50",IF(AB2="4. Mostly Compliant (75%)","75",IF(AB2="5. Fully Compliant (100%)","100"))))))>=33,(((_xlfn.XLOOKUP(Assessment!#REF!,Inherited!A:A,Inherited!B:B))/100)*(_xlfn.XLOOKUP(Assessment!#REF!,Inherited!A:A,Inherited!G:G)))+(((100-(_xlfn.XLOOKUP(Assessment!#REF!,Inherited!A:A,Inherited!B:B)))/100)*IF(AB2="1. Non Compliant (0%)","0",IF(AB2="2. Somewhat Compliant (25%)","25",IF(AB2="3. Partially Compliant (50%)","50",IF(AB2="4. Mostly Compliant (75%)","75",IF(AB2="5. Fully Compliant (100%)","100"))))))<=65),"50",IF(AND((((_xlfn.XLOOKUP(Assessment!#REF!,Inherited!A:A,Inherited!B:B))/100)*(_xlfn.XLOOKUP(Assessment!#REF!,Inherited!A:A,Inherited!G:G)))+(((100-(_xlfn.XLOOKUP(Assessment!#REF!,Inherited!A:A,Inherited!B:B)))/100)*IF(AB2="1. Non Compliant (0%)","0",IF(AB2="2. Somewhat Compliant (25%)","25",IF(AB2="3. Partially Compliant (50%)","50",IF(AB2="4. Mostly Compliant (75%)","75",IF(AB2="5. Fully Compliant (100%)","100"))))))>=66,(((_xlfn.XLOOKUP(Assessment!#REF!,Inherited!A:A,Inherited!B:B))/100)*(_xlfn.XLOOKUP(Assessment!#REF!,Inherited!A:A,Inherited!G:G)))+(((100-(_xlfn.XLOOKUP(Assessment!#REF!,Inherited!A:A,Inherited!B:B)))/100)*IF(AB2="1. Non Compliant (0%)","0",IF(AB2="2. Somewhat Compliant (25%)","25",IF(AB2="3. Partially Compliant (50%)","50",IF(AB2="4. Mostly Compliant (75%)","75",IF(AB2="5. Fully Compliant (100%)","100"))))))<=89),"75",IF((((_xlfn.XLOOKUP(Assessment!#REF!,Inherited!A:A,Inherited!B:B))/100)*(_xlfn.XLOOKUP(Assessment!#REF!,Inherited!A:A,Inherited!G:G)))+(((100-(_xlfn.XLOOKUP(Assessment!#REF!,Inherited!A:A,Inherited!B:B)))/100)*IF(AB2="1. Non Compliant (0%)","0",IF(AB2="2. Somewhat Compliant (25%)","25",IF(AB2="3. Partially Compliant (50%)","50",IF(AB2="4. Mostly Compliant (75%)","75",IF(AB2="5. Fully Compliant (100%)","100"))))))>=90,"100")))))) -> #N/A | V2: Yes | Z2: 1. Non Compliant (0%) | AK2: Michael Wood - VP of AI Engineering Kyle Smith - IT Operations and AI Expert | AL2: AI policies and procedures are not formally maintained at this time. Documentation will be developed and integrated to existing Merge policies and procedures | AP2: Gap: AI policies and procedures considering the details of the requirement statement are not formally maintained at this time. Recommendation: Management should ensure that AI policies and procedures are developed considering the following: - defines: security administration - defines: data governance - defines: software development - defines: risk management - defines: incident management - defines: business continuity - defines: disaster recovery | AX2: =_xlfn.CONCAT("A-LIGN finished its review of this control on ",AR2, " during the scheduled fieldwork window (",Intro!$B$4,")."& CHAR(10)& CHAR(10)) -> A-LIGN finished its review of this control on during the scheduled fieldwork window (Fieldwork: xx/xx/xxxx - xx/xx/xxxx). | AY2: =IF(AQ2<>"",(_xlfn.CONCAT("Inheritance note: "& CHAR(10),AQ2& CHAR(10)& CHAR(10))),"") | AZ2: =IFERROR(IF(AD2<>"",_xlfn.CONCAT("Examined the following policy during fieldwork:"& CHAR(10),AD2& CHAR(10)& CHAR(10),IF(AND(X2<>"5. Fully Compliant (100%)",AE2<>""),"Reviewed policy exception note:"& CHAR(10) & AE2 & CHAR(10) & CHAR(10),"")),""),"") | BA2: =IFERROR(IF(AH2<>"",_xlfn.CONCAT("Examined the following process during fieldwork:"& CHAR(10),AH2& CHAR(10)& CHAR(10),IF(AND(Y2<>"5. Fully Compliant (100%)",AI2<>""),"Reviewed process exception note:"& CHAR(10) & AI2 & CHAR(10) & CHAR(10),"")),""),"") | BB2: =IF(AK2<>"",(_xlfn.CONCAT("Inquired of the following workforce member: "& CHAR(10),AK2& CHAR(10)& CHAR(10),"Inquiry lead to the following conclusions: "& CHAR(10),AL2& CHAR(10) & CHAR(10))),"") -> Inquired of the following workforce member: Michael Wood - VP of AI Engineering Kyle Smith - IT Operations and AI Expert Inquiry lead to the following conclusions: AI policies and procedures are not formally maintained at this time. Documentation will be developed and integrated to existing Merge policies and procedures | BC2: =IF(AM2<>"",(_xlfn.CONCAT("Observed the following live during fieldwork: "& CHAR(10),AM2& CHAR(10) & CHAR(10))),"") | BD2: =_xlfn.CONCAT("Examined the following evidence during fieldwork:"& CHAR(10),AN2& CHAR(10)& CHAR(10),IF(AO2<>"","Reviewed evidence note:"& CHAR(10)&AO2& CHAR(10) & CHAR(10),"Reviewed evidence addressed the requirement statement."& CHAR(10) & CHAR(10)),IF(AND(AP2<>"5. Fully Compliant (100%)",AP2<>""),"Reviewed evidence exception note: "& CHAR(10) & AP2 & CHAR(10) & CHAR(10),"")) -> Examined the following evidence during fieldwork: Reviewed evidence addressed the requirement statement. Reviewed evidence exception note: Gap: AI policies and procedures considering the details of the requirement statement are not formally maintained at this time. Recommendation: Management should ensure that AI policies and procedures are developed considering the following: - defines: security administration - defines: data governance - defines: software development - defines: risk management - defines: incident management - defines: business continuity - defines: disaster recovery | BE2: =IF(AT2<>"",(_xlfn.CONCAT("Examined the following measure/metric during fieldwork:"& CHAR(10),AT2& CHAR(10)& CHAR(10),"Reviewed measure/metric note:"& CHAR(10),AU2 & CHAR(10) & CHAR(10))),"") | BF2: =IF(AV2<>"",(_xlfn.CONCAT("Examined the following measure/metric management during fieldwork:"& CHAR(10),AV2& CHAR(10)& CHAR(10),"Reviewed measure/metric management note:"& CHAR(10),AW2 & CHAR(10) & CHAR(10))),"") | BG2: =_xlfn.CONCAT((IF((COUNTIF('Sample Tables'!B:B,"")>0)=TRUE,_xlfn.CONCAT("",""),IF((COUNTIF('Sample Tables'!B:B,"")>0)=FALSE,""))),) | BH2: =IF(V2="No","Not Applicable: "&W2,(_xlfn.CONCAT(AX2,AY2,AZ2,BA2,BB2,BC2,BD2,BE2,BF2,BG2))) -> A-LIGN finished its review of this control on during the scheduled fieldwork window (Fieldwork: xx/xx/xxxx - xx/xx/xxxx). Inquired of the following workforce member: Michael Wood - VP of AI Engineering Kyle Smith - IT Operations and AI Expert Inquiry lead to the following conclusions: AI policies and procedures are not formally maintained at this time. Documentation will be developed and integrated to existing Merge policies and procedures Examined the following evidence during fieldwork: Reviewed evidence addressed the requirement statement. Reviewed evidence exception note: Gap: AI policies and procedures considering the details of the requirement statement are not formally maintained at this time. Recommendation: Management should ensure that AI policies and procedures are developed considering the following: - defines: security administration - defines: data governance - defines: software development - defines: risk management - defines: incident management - defines: business continuity - defines: disaster recovery
C3: =IF(V3="No","Not Applicable",(IF(X3="1. Non Compliant (0%)","0",IF(X3="2. Somewhat Compliant (25%)","25",IF(X3="3. Partially Compliant (50%)","50",IF(X3="4. Mostly Compliant (75%)","75",IF(X3="5. Fully Compliant (100%)","100")))))*0.15)+((IF(Y3="1. Non Compliant (0%)","0",IF(Y3="2. Somewhat Compliant (25%)","25",IF(Y3="3. Partially Compliant (50%)","50",IF(Y3="4. Mostly Compliant (75%)","75",IF(Y3="5. Fully Compliant (100%)","100"))))))*0.2)+(IF(Z3="1. Non Compliant (0%)","0",IF(Z3="2. Somewhat Compliant (25%)","25",IF(Z3="3. Partially Compliant (50%)","50",IF(Z3="4. Mostly Compliant (75%)","75",IF(Z3="5. Fully Compliant (100%)","100")))))*0.4)+(IF(AA3="1. Non Compliant (0%)","0",IF(AA3="2. Somewhat Compliant (25%)","25",IF(AA3="3. Partially Compliant (50%)","50",IF(AA3="4. Mostly Compliant (75%)","75",IF(AA3="5. Fully Compliant (100%)","100")))))*0.1)+(IF(AB3="1. Non Compliant (0%)","0",IF(AB3="2. Somewhat Compliant (25%)","25",IF(AB3="3. Partially Compliant (50%)","50",IF(AB3="4. Mostly Compliant (75%)","75",IF(AB3="5. Fully Compliant (100%)","100")))))*0.15)) -> 0 | D3: =IF(AND((_xlfn.XLOOKUP(J3,'Fields & Revisions'!$H:$H,'Fields & Revisions'!$I:$I))<70.99,(OR(Z3="4. Mostly Compliant (75%)",Z3="3. Partially Compliant (50%)",Z3="2. Somewhat Compliant (25%)",Z3="1. Non Compliant (0%)"))),"Yes","No") -> Yes | E3: =IF(ISERROR(VLOOKUP(H3,Scope!A:A,1,FALSE)),"No","Yes") -> Yes | F3: 01 Information Protection Program | G3: 3037.0 | H3: 01.02aAISecOrganizational.1 | I3: HITRUST Security for AI System | J3: 02.a Roles and Responsibilities | K3: The organization formally defines the roles and responsibilities for the |governance, |security, and |risk management|| of the organization's deployed AI systems within the organization (e.g., by extending a pre-existing RACI chart or creating a new one specific to AI).|| The organization formally |assigns human accountability for the actions performed by, outputs produced by, and decisions made by the organization’s deployed AI systems.|| | L3: Examine evidence that all evaluative elements within the requirement statement have been implemented as defined in the HITRUST scoring rubric, using a sample based test where possible for each evaluative element. Example test(s): For example, review AI systems policy and procedure documentation to determine if roles and responsibilities for the governance, security, and risk management of the organization’s deployed AI systems is in place. Further, confirm that the organization assigns human accountability for the actions performed by, outputs produced by, and decisions made by the organization’s deployed AI systems. | M3: Documentation: Artificial Intelligence Program - defines: roles and responsibilities for governance - defines: roles and responsibilities for security - defines: roles and responsibilities for risk management Evidence Test: Artificial Intelligence - human accountability assigned for actions performed by the Artificial Intelligence System - human accountability assigned for outputs produced by the Artificial Intelligence System - human accountability assigned for decisions made by the Artificial Intelligence System | N3: No | O3: =_xlfn.XLOOKUP(G3,SRMs!$A:$A,SRMs!$D:$D) -> NO INHERITANCE | P3: =IFERROR(VLOOKUP(H3,Inherited!A:B,2,FALSE),"") | Q3: =IF(MATCH(H3,Inherited!A:A),IF((((_xlfn.XLOOKUP(Assessment!#REF!,Inherited!A:A,Inherited!B:B))/100)*(_xlfn.XLOOKUP(Assessment!#REF!,Inherited!A:A,Inherited!C:C)))+(((100-(_xlfn.XLOOKUP(Assessment!#REF!,Inherited!A:A,Inherited!B:B)))/100)*IF(X3="1. Non Compliant (0%)","0",IF(X3="2. Somewhat Compliant (25%)","25",IF(X3="3. Partially Compliant (50%)","50",IF(X3="4. Mostly Compliant (75%)","75",IF(X3="5. Fully Compliant (100%)","100"))))))<=10,"0", IF(AND((((_xlfn.XLOOKUP(Assessment!#REF!,Inherited!A:A,Inherited!B:B))/100)*(_xlfn.XLOOKUP(Assessment!#REF!,Inherited!A:A,Inherited!C:C)))+(((100-(_xlfn.XLOOKUP(Assessment!#REF!,Inherited!A:A,Inherited!B:B)))/100)*IF(X3="1. Non Compliant (0%)","0",IF(X3="2. Somewhat Compliant (25%)","25",IF(X3="3. Partially Compliant (50%)","50",IF(X3="4. Mostly Compliant (75%)","75",IF(X3="5. Fully Compliant (100%)","100"))))))>=11,(((_xlfn.XLOOKUP(Assessment!#REF!,Inherited!A:A,Inherited!B:B))/100)*(_xlfn.XLOOKUP(Assessment!#REF!,Inherited!A:A,Inherited!C:C)))+(((100-(_xlfn.XLOOKUP(Assessment!#REF!,Inherited!A:A,Inherited!B:B)))/100)*IF(X3="1. Non Compliant (0%)","0",IF(X3="2. Somewhat Compliant (25%)","25",IF(X3="3. Partially Compliant (50%)","50",IF(X3="4. Mostly Compliant (75%)","75",IF(X3="5. Fully Compliant (100%)","100"))))))<=32),"25",IF(AND((((_xlfn.XLOOKUP(Assessment!#REF!,Inherited!A:A,Inherited!B:B))/100)*(_xlfn.XLOOKUP(Assessment!#REF!,Inherited!A:A,Inherited!C:C)))+(((100-(_xlfn.XLOOKUP(Assessment!#REF!,Inherited!A:A,Inherited!B:B)))/100)*IF(X3="1. Non Compliant (0%)","0",IF(X3="2. Somewhat Compliant (25%)","25",IF(X3="3. Partially Compliant (50%)","50",IF(X3="4. Mostly Compliant (75%)","75",IF(X3="5. Fully Compliant (100%)","100"))))))>=33,(((_xlfn.XLOOKUP(Assessment!#REF!,Inherited!A:A,Inherited!B:B))/100)*(_xlfn.XLOOKUP(Assessment!#REF!,Inherited!A:A,Inherited!C:C)))+(((100-(_xlfn.XLOOKUP(Assessment!#REF!,Inherited!A:A,Inherited!B:B)))/100)*IF(X3="1. Non Compliant (0%)","0",IF(X3="2. Somewhat Compliant (25%)","25",IF(X3="3. Partially Compliant (50%)","50",IF(X3="4. Mostly Compliant (75%)","75",IF(X3="5. Fully Compliant (100%)","100"))))))<=65),"50",IF(AND((((_xlfn.XLOOKUP(Assessment!#REF!,Inherited!A:A,Inherited!B:B))/100)*(_xlfn.XLOOKUP(Assessment!#REF!,Inherited!A:A,Inherited!C:C)))+(((100-(_xlfn.XLOOKUP(Assessment!#REF!,Inherited!A:A,Inherited!B:B)))/100)*IF(X3="1. Non Compliant (0%)","0",IF(X3="2. Somewhat Compliant (25%)","25",IF(X3="3. Partially Compliant (50%)","50",IF(X3="4. Mostly Compliant (75%)","75",IF(X3="5. Fully Compliant (100%)","100"))))))>=66,(((_xlfn.XLOOKUP(Assessment!#REF!,Inherited!A:A,Inherited!B:B))/100)*(_xlfn.XLOOKUP(Assessment!#REF!,Inherited!A:A,Inherited!C:C)))+(((100-(_xlfn.XLOOKUP(Assessment!#REF!,Inherited!A:A,Inherited!B:B)))/100)*IF(X3="1. Non Compliant (0%)","0",IF(X3="2. Somewhat Compliant (25%)","25",IF(X3="3. Partially Compliant (50%)","50",IF(X3="4. Mostly Compliant (75%)","75",IF(X3="5. Fully Compliant (100%)","100"))))))<=89),"75",IF((((_xlfn.XLOOKUP(Assessment!#REF!,Inherited!A:A,Inherited!B:B))/100)*(_xlfn.XLOOKUP(Assessment!#REF!,Inherited!A:A,Inherited!C:C)))+(((100-(_xlfn.XLOOKUP(Assessment!#REF!,Inherited!A:A,Inherited!B:B)))/100)*IF(X3="1. Non Compliant (0%)","0",IF(X3="2. Somewhat Compliant (25%)","25",IF(X3="3. Partially Compliant (50%)","50",IF(X3="4. Mostly Compliant (75%)","75",IF(X3="5. Fully Compliant (100%)","100"))))))>=90,"100")))))) -> #N/A | R3: =IF(MATCH(H3,Inherited!A:A),IF((((_xlfn.XLOOKUP(Assessment!#REF!,Inherited!A:A,Inherited!B:B))/100)*(_xlfn.XLOOKUP(Assessment!#REF!,Inherited!A:A,Inherited!D:D)))+(((100-(_xlfn.XLOOKUP(Assessment!#REF!,Inherited!A:A,Inherited!B:B)))/100)*IF(Y3="1. Non Compliant (0%)","0",IF(Y3="2. Somewhat Compliant (25%)","25",IF(Y3="3. Partially Compliant (50%)","50",IF(Y3="4. Mostly Compliant (75%)","75",IF(Y3="5. Fully Compliant (100%)","100"))))))<=10,"0", IF(AND((((_xlfn.XLOOKUP(Assessment!#REF!,Inherited!A:A,Inherited!B:B))/100)*(_xlfn.XLOOKUP(Assessment!#REF!,Inherited!A:A,Inherited!D:D)))+(((100-(_xlfn.XLOOKUP(Assessment!#REF!,Inherited!A:A,Inherited!B:B)))/100)*IF(Y3="1. Non Compliant (0%)","0",IF(Y3="2. Somewhat Compliant (25%)","25",IF(Y3="3. Partially Compliant (50%)","50",IF(Y3="4. Mostly Compliant (75%)","75",IF(Y3="5. Fully Compliant (100%)","100"))))))>=11,(((_xlfn.XLOOKUP(Assessment!#REF!,Inherited!A:A,Inherited!B:B))/100)*(_xlfn.XLOOKUP(Assessment!#REF!,Inherited!A:A,Inherited!D:D)))+(((100-(_xlfn.XLOOKUP(Assessment!#REF!,Inherited!A:A,Inherited!B:B)))/100)*IF(Y3="1. Non Compliant (0%)","0",IF(Y3="2. Somewhat Compliant (25%)","25",IF(Y3="3. Partially Compliant (50%)","50",IF(Y3="4. Mostly Compliant (75%)","75",IF(Y3="5. Fully Compliant (100%)","100"))))))<=32),"25",IF(AND((((_xlfn.XLOOKUP(Assessment!#REF!,Inherited!A:A,Inherited!B:B))/100)*(_xlfn.XLOOKUP(Assessment!#REF!,Inherited!A:A,Inherited!D:D)))+(((100-(_xlfn.XLOOKUP(Assessment!#REF!,Inherited!A:A,Inherited!B:B)))/100)*IF(Y3="1. Non Compliant (0%)","0",IF(Y3="2. Somewhat Compliant (25%)","25",IF(Y3="3. Partially Compliant (50%)","50",IF(Y3="4. Mostly Compliant (75%)","75",IF(Y3="5. Fully Compliant (100%)","100"))))))>=33,(((_xlfn.XLOOKUP(Assessment!#REF!,Inherited!A:A,Inherited!B:B))/100)*(_xlfn.XLOOKUP(Assessment!#REF!,Inherited!A:A,Inherited!D:D)))+(((100-(_xlfn.XLOOKUP(Assessment!#REF!,Inherited!A:A,Inherited!B:B)))/100)*IF(Y3="1. Non Compliant (0%)","0",IF(Y3="2. Somewhat Compliant (25%)","25",IF(Y3="3. Partially Compliant (50%)","50",IF(Y3="4. Mostly Compliant (75%)","75",IF(Y3="5. Fully Compliant (100%)","100"))))))<=65),"50",IF(AND((((_xlfn.XLOOKUP(Assessment!#REF!,Inherited!A:A,Inherited!B:B))/100)*(_xlfn.XLOOKUP(Assessment!#REF!,Inherited!A:A,Inherited!D:D)))+(((100-(_xlfn.XLOOKUP(Assessment!#REF!,Inherited!A:A,Inherited!B:B)))/100)*IF(Y3="1. Non Compliant (0%)","0",IF(Y3="2. Somewhat Compliant (25%)","25",IF(Y3="3. Partially Compliant (50%)","50",IF(Y3="4. Mostly Compliant (75%)","75",IF(Y3="5. Fully Compliant (100%)","100"))))))>=66,(((_xlfn.XLOOKUP(Assessment!#REF!,Inherited!A:A,Inherited!B:B))/100)*(_xlfn.XLOOKUP(Assessment!#REF!,Inherited!A:A,Inherited!D:D)))+(((100-(_xlfn.XLOOKUP(Assessment!#REF!,Inherited!A:A,Inherited!B:B)))/100)*IF(Y3="1. Non Compliant (0%)","0",IF(Y3="2. Somewhat Compliant (25%)","25",IF(Y3="3. Partially Compliant (50%)","50",IF(Y3="4. Mostly Compliant (75%)","75",IF(Y3="5. Fully Compliant (100%)","100"))))))<=89),"75",IF((((_xlfn.XLOOKUP(Assessment!#REF!,Inherited!A:A,Inherited!B:B))/100)*(_xlfn.XLOOKUP(Assessment!#REF!,Inherited!A:A,Inherited!D:D)))+(((100-(_xlfn.XLOOKUP(Assessment!#REF!,Inherited!A:A,Inherited!B:B)))/100)*IF(Y3="1. Non Compliant (0%)","0",IF(Y3="2. Somewhat Compliant (25%)","25",IF(Y3="3. Partially Compliant (50%)","50",IF(Y3="4. Mostly Compliant (75%)","75",IF(Y3="5. Fully Compliant (100%)","100"))))))>=90,"100")))))) -> #N/A | S3: =IF(MATCH(H3,Inherited!A:A),IF((((_xlfn.XLOOKUP(Assessment!#REF!,Inherited!A:A,Inherited!B:B))/100)*(_xlfn.XLOOKUP(Assessment!#REF!,Inherited!A:A,Inherited!E:E)))+(((100-(_xlfn.XLOOKUP(Assessment!#REF!,Inherited!A:A,Inherited!B:B)))/100)*IF(Z3="1. Non Compliant (0%)","0",IF(Z3="2. Somewhat Compliant (25%)","25",IF(Z3="3. Partially Compliant (50%)","50",IF(Z3="4. Mostly Compliant (75%)","75",IF(Z3="5. Fully Compliant (100%)","100"))))))<=10,"0", IF(AND((((_xlfn.XLOOKUP(Assessment!#REF!,Inherited!A:A,Inherited!B:B))/100)*(_xlfn.XLOOKUP(Assessment!#REF!,Inherited!A:A,Inherited!E:E)))+(((100-(_xlfn.XLOOKUP(Assessment!#REF!,Inherited!A:A,Inherited!B:B)))/100)*IF(Z3="1. Non Compliant (0%)","0",IF(Z3="2. Somewhat Compliant (25%)","25",IF(Z3="3. Partially Compliant (50%)","50",IF(Z3="4. Mostly Compliant (75%)","75",IF(Z3="5. Fully Compliant (100%)","100"))))))>=11,(((_xlfn.XLOOKUP(Assessment!#REF!,Inherited!A:A,Inherited!B:B))/100)*(_xlfn.XLOOKUP(Assessment!#REF!,Inherited!A:A,Inherited!E:E)))+(((100-(_xlfn.XLOOKUP(Assessment!#REF!,Inherited!A:A,Inherited!B:B)))/100)*IF(Z3="1. Non Compliant (0%)","0",IF(Z3="2. Somewhat Compliant (25%)","25",IF(Z3="3. Partially Compliant (50%)","50",IF(Z3="4. Mostly Compliant (75%)","75",IF(Z3="5. Fully Compliant (100%)","100"))))))<=32),"25",IF(AND((((_xlfn.XLOOKUP(Assessment!#REF!,Inherited!A:A,Inherited!B:B))/100)*(_xlfn.XLOOKUP(Assessment!#REF!,Inherited!A:A,Inherited!E:E)))+(((100-(_xlfn.XLOOKUP(Assessment!#REF!,Inherited!A:A,Inherited!B:B)))/100)*IF(Z3="1. Non Compliant (0%)","0",IF(Z3="2. Somewhat Compliant (25%)","25",IF(Z3="3. Partially Compliant (50%)","50",IF(Z3="4. Mostly Compliant (75%)","75",IF(Z3="5. Fully Compliant (100%)","100"))))))>=33,(((_xlfn.XLOOKUP(Assessment!#REF!,Inherited!A:A,Inherited!B:B))/100)*(_xlfn.XLOOKUP(Assessment!#REF!,Inherited!A:A,Inherited!E:E)))+(((100-(_xlfn.XLOOKUP(Assessment!#REF!,Inherited!A:A,Inherited!B:B)))/100)*IF(Z3="1. Non Compliant (0%)","0",IF(Z3="2. Somewhat Compliant (25%)","25",IF(Z3="3. Partially Compliant (50%)","50",IF(Z3="4. Mostly Compliant (75%)","75",IF(Z3="5. Fully Compliant (100%)","100"))))))<=65),"50",IF(AND((((_xlfn.XLOOKUP(Assessment!#REF!,Inherited!A:A,Inherited!B:B))/100)*(_xlfn.XLOOKUP(Assessment!#REF!,Inherited!A:A,Inherited!E:E)))+(((100-(_xlfn.XLOOKUP(Assessment!#REF!,Inherited!A:A,Inherited!B:B)))/100)*IF(Z3="1. Non Compliant (0%)","0",IF(Z3="2. Somewhat Compliant (25%)","25",IF(Z3="3. Partially Compliant (50%)","50",IF(Z3="4. Mostly Compliant (75%)","75",IF(Z3="5. Fully Compliant (100%)","100"))))))>=66,(((_xlfn.XLOOKUP(Assessment!#REF!,Inherited!A:A,Inherited!B:B))/100)*(_xlfn.XLOOKUP(Assessment!#REF!,Inherited!A:A,Inherited!E:E)))+(((100-(_xlfn.XLOOKUP(Assessment!#REF!,Inherited!A:A,Inherited!B:B)))/100)*IF(Z3="1. Non Compliant (0%)","0",IF(Z3="2. Somewhat Compliant (25%)","25",IF(Z3="3. Partially Compliant (50%)","50",IF(Z3="4. Mostly Compliant (75%)","75",IF(Z3="5. Fully Compliant (100%)","100"))))))<=89),"75",IF((((_xlfn.XLOOKUP(Assessment!#REF!,Inherited!A:A,Inherited!B:B))/100)*(_xlfn.XLOOKUP(Assessment!#REF!,Inherited!A:A,Inherited!E:E)))+(((100-(_xlfn.XLOOKUP(Assessment!#REF!,Inherited!A:A,Inherited!B:B)))/100)*IF(Z3="1. Non Compliant (0%)","0",IF(Z3="2. Somewhat Compliant (25%)","25",IF(Z3="3. Partially Compliant (50%)","50",IF(Z3="4. Mostly Compliant (75%)","75",IF(Z3="5. Fully Compliant (100%)","100"))))))>=90,"100")))))) -> #N/A | T3: =IF(MATCH(H3,Inherited!A:A),IF((((_xlfn.XLOOKUP(Assessment!#REF!,Inherited!A:A,Inherited!B:B))/100)*(_xlfn.XLOOKUP(Assessment!#REF!,Inherited!A:A,Inherited!F:F)))+(((100-(_xlfn.XLOOKUP(Assessment!#REF!,Inherited!A:A,Inherited!B:B)))/100)*IF(AA3="1. Non Compliant (0%)","0",IF(AA3="2. Somewhat Compliant (25%)","25",IF(AA3="3. Partially Compliant (50%)","50",IF(AA3="4. Mostly Compliant (75%)","75",IF(AA3="5. Fully Compliant (100%)","100"))))))<=10,"0", IF(AND((((_xlfn.XLOOKUP(Assessment!#REF!,Inherited!A:A,Inherited!B:B))/100)*(_xlfn.XLOOKUP(Assessment!#REF!,Inherited!A:A,Inherited!F:F)))+(((100-(_xlfn.XLOOKUP(Assessment!#REF!,Inherited!A:A,Inherited!B:B)))/100)*IF(AA3="1. Non Compliant (0%)","0",IF(AA3="2. Somewhat Compliant (25%)","25",IF(AA3="3. Partially Compliant (50%)","50",IF(AA3="4. Mostly Compliant (75%)","75",IF(AA3="5. Fully Compliant (100%)","100"))))))>=11,(((_xlfn.XLOOKUP(Assessment!#REF!,Inherited!A:A,Inherited!B:B))/100)*(_xlfn.XLOOKUP(Assessment!#REF!,Inherited!A:A,Inherited!F:F)))+(((100-(_xlfn.XLOOKUP(Assessment!#REF!,Inherited!A:A,Inherited!B:B)))/100)*IF(AA3="1. Non Compliant (0%)","0",IF(AA3="2. Somewhat Compliant (25%)","25",IF(AA3="3. Partially Compliant (50%)","50",IF(AA3="4. Mostly Compliant (75%)","75",IF(AA3="5. Fully Compliant (100%)","100"))))))<=32),"25",IF(AND((((_xlfn.XLOOKUP(Assessment!#REF!,Inherited!A:A,Inherited!B:B))/100)*(_xlfn.XLOOKUP(Assessment!#REF!,Inherited!A:A,Inherited!F:F)))+(((100-(_xlfn.XLOOKUP(Assessment!#REF!,Inherited!A:A,Inherited!B:B)))/100)*IF(AA3="1. Non Compliant (0%)","0",IF(AA3="2. Somewhat Compliant (25%)","25",IF(AA3="3. Partially Compliant (50%)","50",IF(AA3="4. Mostly Compliant (75%)","75",IF(AA3="5. Fully Compliant (100%)","100"))))))>=33,(((_xlfn.XLOOKUP(Assessment!#REF!,Inherited!A:A,Inherited!B:B))/100)*(_xlfn.XLOOKUP(Assessment!#REF!,Inherited!A:A,Inherited!F:F)))+(((100-(_xlfn.XLOOKUP(Assessment!#REF!,Inherited!A:A,Inherited!B:B)))/100)*IF(AA3="1. Non Compliant (0%)","0",IF(AA3="2. Somewhat Compliant (25%)","25",IF(AA3="3. Partially Compliant (50%)","50",IF(AA3="4. Mostly Compliant (75%)","75",IF(AA3="5. Fully Compliant (100%)","100"))))))<=65),"50",IF(AND((((_xlfn.XLOOKUP(Assessment!#REF!,Inherited!A:A,Inherited!B:B))/100)*(_xlfn.XLOOKUP(Assessment!#REF!,Inherited!A:A,Inherited!F:F)))+(((100-(_xlfn.XLOOKUP(Assessment!#REF!,Inherited!A:A,Inherited!B:B)))/100)*IF(AA3="1. Non Compliant (0%)","0",IF(AA3="2. Somewhat Compliant (25%)","25",IF(AA3="3. Partially Compliant (50%)","50",IF(AA3="4. Mostly Compliant (75%)","75",IF(AA3="5. Fully Compliant (100%)","100"))))))>=66,(((_xlfn.XLOOKUP(Assessment!#REF!,Inherited!A:A,Inherited!B:B))/100)*(_xlfn.XLOOKUP(Assessment!#REF!,Inherited!A:A,Inherited!F:F)))+(((100-(_xlfn.XLOOKUP(Assessment!#REF!,Inherited!A:A,Inherited!B:B)))/100)*IF(AA3="1. Non Compliant (0%)","0",IF(AA3="2. Somewhat Compliant (25%)","25",IF(AA3="3. Partially Compliant (50%)","50",IF(AA3="4. Mostly Compliant (75%)","75",IF(AA3="5. Fully Compliant (100%)","100"))))))<=89),"75",IF((((_xlfn.XLOOKUP(Assessment!#REF!,Inherited!A:A,Inherited!B:B))/100)*(_xlfn.XLOOKUP(Assessment!#REF!,Inherited!A:A,Inherited!F:F)))+(((100-(_xlfn.XLOOKUP(Assessment!#REF!,Inherited!A:A,Inherited!B:B)))/100)*IF(AA3="1. Non Compliant (0%)","0",IF(AA3="2. Somewhat Compliant (25%)","25",IF(AA3="3. Partially Compliant (50%)","50",IF(AA3="4. Mostly Compliant (75%)","75",IF(AA3="5. Fully Compliant (100%)","100"))))))>=90,"100")))))) -> #N/A | U3: =IF(MATCH(H3,Inherited!A:A),IF((((_xlfn.XLOOKUP(Assessment!#REF!,Inherited!A:A,Inherited!B:B))/100)*(_xlfn.XLOOKUP(Assessment!#REF!,Inherited!A:A,Inherited!G:G)))+(((100-(_xlfn.XLOOKUP(Assessment!#REF!,Inherited!A:A,Inherited!B:B)))/100)*IF(AB3="1. Non Compliant (0%)","0",IF(AB3="2. Somewhat Compliant (25%)","25",IF(AB3="3. Partially Compliant (50%)","50",IF(AB3="4. Mostly Compliant (75%)","75",IF(AB3="5. Fully Compliant (100%)","100"))))))<=10,"0", IF(AND((((_xlfn.XLOOKUP(Assessment!#REF!,Inherited!A:A,Inherited!B:B))/100)*(_xlfn.XLOOKUP(Assessment!#REF!,Inherited!A:A,Inherited!G:G)))+(((100-(_xlfn.XLOOKUP(Assessment!#REF!,Inherited!A:A,Inherited!B:B)))/100)*IF(AB3="1. Non Compliant (0%)","0",IF(AB3="2. Somewhat Compliant (25%)","25",IF(AB3="3. Partially Compliant (50%)","50",IF(AB3="4. Mostly Compliant (75%)","75",IF(AB3="5. Fully Compliant (100%)","100"))))))>=11,(((_xlfn.XLOOKUP(Assessment!#REF!,Inherited!A:A,Inherited!B:B))/100)*(_xlfn.XLOOKUP(Assessment!#REF!,Inherited!A:A,Inherited!G:G)))+(((100-(_xlfn.XLOOKUP(Assessment!#REF!,Inherited!A:A,Inherited!B:B)))/100)*IF(AB3="1. Non Compliant (0%)","0",IF(AB3="2. Somewhat Compliant (25%)","25",IF(AB3="3. Partially Compliant (50%)","50",IF(AB3="4. Mostly Compliant (75%)","75",IF(AB3="5. Fully Compliant (100%)","100"))))))<=32),"25",IF(AND((((_xlfn.XLOOKUP(Assessment!#REF!,Inherited!A:A,Inherited!B:B))/100)*(_xlfn.XLOOKUP(Assessment!#REF!,Inherited!A:A,Inherited!G:G)))+(((100-(_xlfn.XLOOKUP(Assessment!#REF!,Inherited!A:A,Inherited!B:B)))/100)*IF(AB3="1. Non Compliant (0%)","0",IF(AB3="2. Somewhat Compliant (25%)","25",IF(AB3="3. Partially Compliant (50%)","50",IF(AB3="4. Mostly Compliant (75%)","75",IF(AB3="5. Fully Compliant (100%)","100"))))))>=33,(((_xlfn.XLOOKUP(Assessment!#REF!,Inherited!A:A,Inherited!B:B))/100)*(_xlfn.XLOOKUP(Assessment!#REF!,Inherited!A:A,Inherited!G:G)))+(((100-(_xlfn.XLOOKUP(Assessment!#REF!,Inherited!A:A,Inherited!B:B)))/100)*IF(AB3="1. Non Compliant (0%)","0",IF(AB3="2. Somewhat Compliant (25%)","25",IF(AB3="3. Partially Compliant (50%)","50",IF(AB3="4. Mostly Compliant (75%)","75",IF(AB3="5. Fully Compliant (100%)","100"))))))<=65),"50",IF(AND((((_xlfn.XLOOKUP(Assessment!#REF!,Inherited!A:A,Inherited!B:B))/100)*(_xlfn.XLOOKUP(Assessment!#REF!,Inherited!A:A,Inherited!G:G)))+(((100-(_xlfn.XLOOKUP(Assessment!#REF!,Inherited!A:A,Inherited!B:B)))/100)*IF(AB3="1. Non Compliant (0%)","0",IF(AB3="2. Somewhat Compliant (25%)","25",IF(AB3="3. Partially Compliant (50%)","50",IF(AB3="4. Mostly Compliant (75%)","75",IF(AB3="5. Fully Compliant (100%)","100"))))))>=66,(((_xlfn.XLOOKUP(Assessment!#REF!,Inherited!A:A,Inherited!B:B))/100)*(_xlfn.XLOOKUP(Assessment!#REF!,Inherited!A:A,Inherited!G:G)))+(((100-(_xlfn.XLOOKUP(Assessment!#REF!,Inherited!A:A,Inherited!B:B)))/100)*IF(AB3="1. Non Compliant (0%)","0",IF(AB3="2. Somewhat Compliant (25%)","25",IF(AB3="3. Partially Compliant (50%)","50",IF(AB3="4. Mostly Compliant (75%)","75",IF(AB3="5. Fully Compliant (100%)","100"))))))<=89),"75",IF((((_xlfn.XLOOKUP(Assessment!#REF!,Inherited!A:A,Inherited!B:B))/100)*(_xlfn.XLOOKUP(Assessment!#REF!,Inherited!A:A,Inherited!G:G)))+(((100-(_xlfn.XLOOKUP(Assessment!#REF!,Inherited!A:A,Inherited!B:B)))/100)*IF(AB3="1. Non Compliant (0%)","0",IF(AB3="2. Somewhat Compliant (25%)","25",IF(AB3="3. Partially Compliant (50%)","50",IF(AB3="4. Mostly Compliant (75%)","75",IF(AB3="5. Fully Compliant (100%)","100"))))))>=90,"100")))))) -> #N/A | V3: Yes | Z3: 1. Non Compliant (0%) | AK3: Michael Wood - VP of AI Engineering Kyle Smith - IT Operations and AI Expert | AL3: AI policies and procedures are not formally maintained at this time. Documentation will be developed and integrated to existing Merge policies and procedures | AP3: Gap: AI policies and procedures considering the details of the requirement statement are not formally maintained at this time. Recommendation: Management should ensure that AI policies and procedures are developed considering the following: - defines: roles and responsibilities for governance - defines: roles and responsibilities for security - defines: roles and responsibilities for risk management Further, management should ensure that the organization assigns human accountability for the actions performed by, outputs produced by, and decisions made by the organization’s deployed AI systems. | AX3: =_xlfn.CONCAT("A-LIGN finished its review of this control on ",AR3, " during the scheduled fieldwork window (",Intro!$B$4,")."& CHAR(10)& CHAR(10)) -> A-LIGN finished its review of this control on during the scheduled fieldwork window (Fieldwork: xx/xx/xxxx - xx/xx/xxxx). | AY3: =IF(AQ3<>"",(_xlfn.CONCAT("Inheritance note: "& CHAR(10),AQ3& CHAR(10)& CHAR(10))),"") | AZ3: =IFERROR(IF(AD3<>"",_xlfn.CONCAT("Examined the following policy during fieldwork:"& CHAR(10),AD3& CHAR(10)& CHAR(10),IF(AND(X3<>"5. Fully Compliant (100%)",AE3<>""),"Reviewed policy exception note:"& CHAR(10) & AE3 & CHAR(10) & CHAR(10),"")),""),"") | BA3: =IFERROR(IF(AH3<>"",_xlfn.CONCAT("Examined the following process during fieldwork:"& CHAR(10),AH3& CHAR(10)& CHAR(10),IF(AND(Y3<>"5. Fully Compliant (100%)",AI3<>""),"Reviewed process exception note:"& CHAR(10) & AI3 & CHAR(10) & CHAR(10),"")),""),"") | BB3: =IF(AK3<>"",(_xlfn.CONCAT("Inquired of the following workforce member: "& CHAR(10),AK3& CHAR(10)& CHAR(10),"Inquiry lead to the following conclusions: "& CHAR(10),AL3& CHAR(10) & CHAR(10))),"") -> Inquired of the following workforce member: Michael Wood - VP of AI Engineering Kyle Smith - IT Operations and AI Expert Inquiry lead to the following conclusions: AI policies and procedures are not formally maintained at this time. Documentation will be developed and integrated to existing Merge policies and procedures | BC3: =IF(AM3<>"",(_xlfn.CONCAT("Observed the following live during fieldwork: "& CHAR(10),AM3& CHAR(10) & CHAR(10))),"") | BD3: =_xlfn.CONCAT("Examined the following evidence during fieldwork:"& CHAR(10),AN3& CHAR(10)& CHAR(10),IF(AO3<>"","Reviewed evidence note:"& CHAR(10)&AO3& CHAR(10) & CHAR(10),"Reviewed evidence addressed the requirement statement."& CHAR(10) & CHAR(10)),IF(AND(AP3<>"5. Fully Compliant (100%)",AP3<>""),"Reviewed evidence exception note: "& CHAR(10) & AP3 & CHAR(10) & CHAR(10),"")) -> Examined the following evidence during fieldwork: Reviewed evidence addressed the requirement statement. Reviewed evidence exception note: Gap: AI policies and procedures considering the details of the requirement statement are not formally maintained at this time. Recommendation: Management should ensure that AI policies and procedures are developed considering the following: - defines: roles and responsibilities for governance - defines: roles and responsibilities for security - defines: roles and responsibilities for risk management Further, management should ensure that the organization assigns human accountability for the actions performed by, outputs produced by, and decisions made by the organization’s deployed AI systems. | BE3: =IF(AT3<>"",(_xlfn.CONCAT("Examined the following measure/metric during fieldwork:"& CHAR(10),AT3& CHAR(10)& CHAR(10),"Reviewed measure/metric note:"& CHAR(10),AU3 & CHAR(10) & CHAR(10))),"") | BF3: =IF(AV3<>"",(_xlfn.CONCAT("Examined the following measure/metric management during fieldwork:"& CHAR(10),AV3& CHAR(10)& CHAR(10),"Reviewed measure/metric management note:"& CHAR(10),AW3 & CHAR(10) & CHAR(10))),"") | BG3: =_xlfn.CONCAT((IF((COUNTIF('Sample Tables'!B:B,"")>0)=TRUE,_xlfn.CONCAT("",""),IF((COUNTIF('Sample Tables'!B:B,"")>0)=FALSE,""))),) | BH3: =IF(V3="No","Not Applicable: "&W3,(_xlfn.CONCAT(AX3,AY3,AZ3,BA3,BB3,BC3,BD3,BE3,BF3,BG3))) -> A-LIGN finished its review of this control on during the scheduled fieldwork window (Fieldwork: xx/xx/xxxx - xx/xx/xxxx). Inquired of the following workforce member: Michael Wood - VP of AI Engineering Kyle Smith - IT Operations and AI Expert Inquiry lead to the following conclusions: AI policies and procedures are not formally maintained at this time. Documentation will be developed and integrated to existing Merge policies and procedures Examined the following evidence during fieldwork: Reviewed evidence addressed the requirement statement. Reviewed evidence exception note: Gap: AI policies and procedures considering the details of the requirement statement are not formally maintained at this time. Recommendation: Management should ensure that AI policies and procedures are developed considering the following: - defines: roles and responsibilities for governance - defines: roles and responsibilities for security - defines: roles and responsibilities for risk management Further, management should ensure that the organization assigns human accountability for the actions performed by, outputs produced by, and decisions made by the organization’s deployed AI systems.
C4: =IF(V4="No","Not Applicable",(IF(X4="1. Non Compliant (0%)","0",IF(X4="2. Somewhat Compliant (25%)","25",IF(X4="3. Partially Compliant (50%)","50",IF(X4="4. Mostly Compliant (75%)","75",IF(X4="5. Fully Compliant (100%)","100")))))*0.15)+((IF(Y4="1. Non Compliant (0%)","0",IF(Y4="2. Somewhat Compliant (25%)","25",IF(Y4="3. Partially Compliant (50%)","50",IF(Y4="4. Mostly Compliant (75%)","75",IF(Y4="5. Fully Compliant (100%)","100"))))))*0.2)+(IF(Z4="1. Non Compliant (0%)","0",IF(Z4="2. Somewhat Compliant (25%)","25",IF(Z4="3. Partially Compliant (50%)","50",IF(Z4="4. Mostly Compliant (75%)","75",IF(Z4="5. Fully Compliant (100%)","100")))))*0.4)+(IF(AA4="1. Non Compliant (0%)","0",IF(AA4="2. Somewhat Compliant (25%)","25",IF(AA4="3. Partially Compliant (50%)","50",IF(AA4="4. Mostly Compliant (75%)","75",IF(AA4="5. Fully Compliant (100%)","100")))))*0.1)+(IF(AB4="1. Non Compliant (0%)","0",IF(AB4="2. Somewhat Compliant (25%)","25",IF(AB4="3. Partially Compliant (50%)","50",IF(AB4="4. Mostly Compliant (75%)","75",IF(AB4="5. Fully Compliant (100%)","100")))))*0.15)) -> 0 | D4: =IF(AND((_xlfn.XLOOKUP(J4,'Fields & Revisions'!$H:$H,'Fields & Revisions'!$I:$I))<70.99,(OR(Z4="4. Mostly Compliant (75%)",Z4="3. Partially Compliant (50%)",Z4="2. Somewhat Compliant (25%)",Z4="1. Non Compliant (0%)"))),"Yes","No") -> Yes | E4: =IF(ISERROR(VLOOKUP(H4,Scope!A:A,1,FALSE)),"No","Yes") -> Yes | F4: 01 Information Protection Program | G4: 2809.0 | H4: 01.03aISO23894Organizational.12 | I4: ISO/IEC 23894 | J4: 03.a Risk Management Program Development | K4: The organization maintains documentation of the following aspects of the external context of organization's development and/or use of AI: |relevant legal requirements, including those specifically relating to AI; |guidelines on ethical use and design of AI and automated systems issued by government-related groups, regulators, standardization bodies, civil society, academia and industry associations; |domain-specific guidelines and frameworks related to AI; |technology trends and advancements in the various areas of AI; |societal and political implications of the deployment of AI systems, including guidance from social sciences; |external stakeholder perceptions, needs, and expectations; |how the use of AI, especially AI systems using continuous learning, can affect the ability of the organization to meet contractual obligations and guarantees; |contractual relationships during the design and production of AI systems and services; |how the use of AI can increase the complexity of networks and dependencies; and |how an AI system can replace an existing system and, in such a case, an assessment of the risk benefits and risk transfers of an AI system versus the existing system can be undertaken, considering safety, environmental, social, technical and financial issues associated with the implementation of the AI system. || | L4: Examine evidence that all evaluative elements within the requirement statement have been implemented as defined in the HITRUST scoring rubric, using a sample based test where possible for each evaluative element._x000D_ _x000D_ _x000D_ Example test(s):_x000D_ For example, _x000D_ obtain and examine evidence to confirm the organization has documented its considerations of the external context of the organization per the elements stipulated in the requirement statement. | M4: Documentation: Artificial Intelligence Program - defines relative legal requirements related to AI - defines guidelines on ethical use and design of AI - defines domain-specific guidelines and frameworks related to AI - defines technology trends and advancements related to areas of AI - defines societal and political implications of the deployment of AI systems - defines external stakeholder perceptions, needs, and expectations - defines how the use of AI can affect the ability of the organization to meet contractual obligations and guarantees - defines contractual relationships during the design and production of AI systems and services - defines how the use of AI can increase the complexity of networks and dependencies - defines how an AI system can replace an existing system - defines the risk benefits and risk transfers of an AI system versus the existing system can be undertaken, considering safety, environmental, social, technical and financial issues | N4: No | O4: =_xlfn.XLOOKUP(G4,SRMs!$A:$A,SRMs!$D:$D) -> NO INHERITANCE | P4: =IFERROR(VLOOKUP(H4,Inherited!A:B,2,FALSE),"") | Q4: =IF(MATCH(H4,Inherited!A:A),IF((((_xlfn.XLOOKUP(Assessment!H5,Inherited!A:A,Inherited!B:B))/100)*(_xlfn.XLOOKUP(Assessment!H5,Inherited!A:A,Inherited!C:C)))+(((100-(_xlfn.XLOOKUP(Assessment!H5,Inherited!A:A,Inherited!B:B)))/100)*IF(X4="1. Non Compliant (0%)","0",IF(X4="2. Somewhat Compliant (25%)","25",IF(X4="3. Partially Compliant (50%)","50",IF(X4="4. Mostly Compliant (75%)","75",IF(X4="5. Fully Compliant (100%)","100"))))))<=10,"0", IF(AND((((_xlfn.XLOOKUP(Assessment!H5,Inherited!A:A,Inherited!B:B))/100)*(_xlfn.XLOOKUP(Assessment!H5,Inherited!A:A,Inherited!C:C)))+(((100-(_xlfn.XLOOKUP(Assessment!H5,Inherited!A:A,Inherited!B:B)))/100)*IF(X4="1. Non Compliant (0%)","0",IF(X4="2. Somewhat Compliant (25%)","25",IF(X4="3. Partially Compliant (50%)","50",IF(X4="4. Mostly Compliant (75%)","75",IF(X4="5. Fully Compliant (100%)","100"))))))>=11,(((_xlfn.XLOOKUP(Assessment!H5,Inherited!A:A,Inherited!B:B))/100)*(_xlfn.XLOOKUP(Assessment!H5,Inherited!A:A,Inherited!C:C)))+(((100-(_xlfn.XLOOKUP(Assessment!H5,Inherited!A:A,Inherited!B:B)))/100)*IF(X4="1. Non Compliant (0%)","0",IF(X4="2. Somewhat Compliant (25%)","25",IF(X4="3. Partially Compliant (50%)","50",IF(X4="4. Mostly Compliant (75%)","75",IF(X4="5. Fully Compliant (100%)","100"))))))<=32),"25",IF(AND((((_xlfn.XLOOKUP(Assessment!H5,Inherited!A:A,Inherited!B:B))/100)*(_xlfn.XLOOKUP(Assessment!H5,Inherited!A:A,Inherited!C:C)))+(((100-(_xlfn.XLOOKUP(Assessment!H5,Inherited!A:A,Inherited!B:B)))/100)*IF(X4="1. Non Compliant (0%)","0",IF(X4="2. Somewhat Compliant (25%)","25",IF(X4="3. Partially Compliant (50%)","50",IF(X4="4. Mostly Compliant (75%)","75",IF(X4="5. Fully Compliant (100%)","100"))))))>=33,(((_xlfn.XLOOKUP(Assessment!H5,Inherited!A:A,Inherited!B:B))/100)*(_xlfn.XLOOKUP(Assessment!H5,Inherited!A:A,Inherited!C:C)))+(((100-(_xlfn.XLOOKUP(Assessment!H5,Inherited!A:A,Inherited!B:B)))/100)*IF(X4="1. Non Compliant (0%)","0",IF(X4="2. Somewhat Compliant (25%)","25",IF(X4="3. Partially Compliant (50%)","50",IF(X4="4. Mostly Compliant (75%)","75",IF(X4="5. Fully Compliant (100%)","100"))))))<=65),"50",IF(AND((((_xlfn.XLOOKUP(Assessment!H5,Inherited!A:A,Inherited!B:B))/100)*(_xlfn.XLOOKUP(Assessment!H5,Inherited!A:A,Inherited!C:C)))+(((100-(_xlfn.XLOOKUP(Assessment!H5,Inherited!A:A,Inherited!B:B)))/100)*IF(X4="1. Non Compliant (0%)","0",IF(X4="2. Somewhat Compliant (25%)","25",IF(X4="3. Partially Compliant (50%)","50",IF(X4="4. Mostly Compliant (75%)","75",IF(X4="5. Fully Compliant (100%)","100"))))))>=66,(((_xlfn.XLOOKUP(Assessment!H5,Inherited!A:A,Inherited!B:B))/100)*(_xlfn.XLOOKUP(Assessment!H5,Inherited!A:A,Inherited!C:C)))+(((100-(_xlfn.XLOOKUP(Assessment!H5,Inherited!A:A,Inherited!B:B)))/100)*IF(X4="1. Non Compliant (0%)","0",IF(X4="2. Somewhat Compliant (25%)","25",IF(X4="3. Partially Compliant (50%)","50",IF(X4="4. Mostly Compliant (75%)","75",IF(X4="5. Fully Compliant (100%)","100"))))))<=89),"75",IF((((_xlfn.XLOOKUP(Assessment!H5,Inherited!A:A,Inherited!B:B))/100)*(_xlfn.XLOOKUP(Assessment!H5,Inherited!A:A,Inherited!C:C)))+(((100-(_xlfn.XLOOKUP(Assessment!H5,Inherited!A:A,Inherited!B:B)))/100)*IF(X4="1. Non Compliant (0%)","0",IF(X4="2. Somewhat Compliant (25%)","25",IF(X4="3. Partially Compliant (50%)","50",IF(X4="4. Mostly Compliant (75%)","75",IF(X4="5. Fully Compliant (100%)","100"))))))>=90,"100")))))) -> #N/A | R4: =IF(MATCH(H4,Inherited!A:A),IF((((_xlfn.XLOOKUP(Assessment!H5,Inherited!A:A,Inherited!B:B))/100)*(_xlfn.XLOOKUP(Assessment!H5,Inherited!A:A,Inherited!D:D)))+(((100-(_xlfn.XLOOKUP(Assessment!H5,Inherited!A:A,Inherited!B:B)))/100)*IF(Y4="1. Non Compliant (0%)","0",IF(Y4="2. Somewhat Compliant (25%)","25",IF(Y4="3. Partially Compliant (50%)","50",IF(Y4="4. Mostly Compliant (75%)","75",IF(Y4="5. Fully Compliant (100%)","100"))))))<=10,"0", IF(AND((((_xlfn.XLOOKUP(Assessment!H5,Inherited!A:A,Inherited!B:B))/100)*(_xlfn.XLOOKUP(Assessment!H5,Inherited!A:A,Inherited!D:D)))+(((100-(_xlfn.XLOOKUP(Assessment!H5,Inherited!A:A,Inherited!B:B)))/100)*IF(Y4="1. Non Compliant (0%)","0",IF(Y4="2. Somewhat Compliant (25%)","25",IF(Y4="3. Partially Compliant (50%)","50",IF(Y4="4. Mostly Compliant (75%)","75",IF(Y4="5. Fully Compliant (100%)","100"))))))>=11,(((_xlfn.XLOOKUP(Assessment!H5,Inherited!A:A,Inherited!B:B))/100)*(_xlfn.XLOOKUP(Assessment!H5,Inherited!A:A,Inherited!D:D)))+(((100-(_xlfn.XLOOKUP(Assessment!H5,Inherited!A:A,Inherited!B:B)))/100)*IF(Y4="1. Non Compliant (0%)","0",IF(Y4="2. Somewhat Compliant (25%)","25",IF(Y4="3. Partially Compliant (50%)","50",IF(Y4="4. Mostly Compliant (75%)","75",IF(Y4="5. Fully Compliant (100%)","100"))))))<=32),"25",IF(AND((((_xlfn.XLOOKUP(Assessment!H5,Inherited!A:A,Inherited!B:B))/100)*(_xlfn.XLOOKUP(Assessment!H5,Inherited!A:A,Inherited!D:D)))+(((100-(_xlfn.XLOOKUP(Assessment!H5,Inherited!A:A,Inherited!B:B)))/100)*IF(Y4="1. Non Compliant (0%)","0",IF(Y4="2. Somewhat Compliant (25%)","25",IF(Y4="3. Partially Compliant (50%)","50",IF(Y4="4. Mostly Compliant (75%)","75",IF(Y4="5. Fully Compliant (100%)","100"))))))>=33,(((_xlfn.XLOOKUP(Assessment!H5,Inherited!A:A,Inherited!B:B))/100)*(_xlfn.XLOOKUP(Assessment!H5,Inherited!A:A,Inherited!D:D)))+(((100-(_xlfn.XLOOKUP(Assessment!H5,Inherited!A:A,Inherited!B:B)))/100)*IF(Y4="1. Non Compliant (0%)","0",IF(Y4="2. Somewhat Compliant (25%)","25",IF(Y4="3. Partially Compliant (50%)","50",IF(Y4="4. Mostly Compliant (75%)","75",IF(Y4="5. Fully Compliant (100%)","100"))))))<=65),"50",IF(AND((((_xlfn.XLOOKUP(Assessment!H5,Inherited!A:A,Inherited!B:B))/100)*(_xlfn.XLOOKUP(Assessment!H5,Inherited!A:A,Inherited!D:D)))+(((100-(_xlfn.XLOOKUP(Assessment!H5,Inherited!A:A,Inherited!B:B)))/100)*IF(Y4="1. Non Compliant (0%)","0",IF(Y4="2. Somewhat Compliant (25%)","25",IF(Y4="3. Partially Compliant (50%)","50",IF(Y4="4. Mostly Compliant (75%)","75",IF(Y4="5. Fully Compliant (100%)","100"))))))>=66,(((_xlfn.XLOOKUP(Assessment!H5,Inherited!A:A,Inherited!B:B))/100)*(_xlfn.XLOOKUP(Assessment!H5,Inherited!A:A,Inherited!D:D)))+(((100-(_xlfn.XLOOKUP(Assessment!H5,Inherited!A:A,Inherited!B:B)))/100)*IF(Y4="1. Non Compliant (0%)","0",IF(Y4="2. Somewhat Compliant (25%)","25",IF(Y4="3. Partially Compliant (50%)","50",IF(Y4="4. Mostly Compliant (75%)","75",IF(Y4="5. Fully Compliant (100%)","100"))))))<=89),"75",IF((((_xlfn.XLOOKUP(Assessment!H5,Inherited!A:A,Inherited!B:B))/100)*(_xlfn.XLOOKUP(Assessment!H5,Inherited!A:A,Inherited!D:D)))+(((100-(_xlfn.XLOOKUP(Assessment!H5,Inherited!A:A,Inherited!B:B)))/100)*IF(Y4="1. Non Compliant (0%)","0",IF(Y4="2. Somewhat Compliant (25%)","25",IF(Y4="3. Partially Compliant (50%)","50",IF(Y4="4. Mostly Compliant (75%)","75",IF(Y4="5. Fully Compliant (100%)","100"))))))>=90,"100")))))) -> #N/A | S4: =IF(MATCH(H4,Inherited!A:A),IF((((_xlfn.XLOOKUP(Assessment!H5,Inherited!A:A,Inherited!B:B))/100)*(_xlfn.XLOOKUP(Assessment!H5,Inherited!A:A,Inherited!E:E)))+(((100-(_xlfn.XLOOKUP(Assessment!H5,Inherited!A:A,Inherited!B:B)))/100)*IF(Z4="1. Non Compliant (0%)","0",IF(Z4="2. Somewhat Compliant (25%)","25",IF(Z4="3. Partially Compliant (50%)","50",IF(Z4="4. Mostly Compliant (75%)","75",IF(Z4="5. Fully Compliant (100%)","100"))))))<=10,"0", IF(AND((((_xlfn.XLOOKUP(Assessment!H5,Inherited!A:A,Inherited!B:B))/100)*(_xlfn.XLOOKUP(Assessment!H5,Inherited!A:A,Inherited!E:E)))+(((100-(_xlfn.XLOOKUP(Assessment!H5,Inherited!A:A,Inherited!B:B)))/100)*IF(Z4="1. Non Compliant (0%)","0",IF(Z4="2. Somewhat Compliant (25%)","25",IF(Z4="3. Partially Compliant (50%)","50",IF(Z4="4. Mostly Compliant (75%)","75",IF(Z4="5. Fully Compliant (100%)","100"))))))>=11,(((_xlfn.XLOOKUP(Assessment!H5,Inherited!A:A,Inherited!B:B))/100)*(_xlfn.XLOOKUP(Assessment!H5,Inherited!A:A,Inherited!E:E)))+(((100-(_xlfn.XLOOKUP(Assessment!H5,Inherited!A:A,Inherited!B:B)))/100)*IF(Z4="1. Non Compliant (0%)","0",IF(Z4="2. Somewhat Compliant (25%)","25",IF(Z4="3. Partially Compliant (50%)","50",IF(Z4="4. Mostly Compliant (75%)","75",IF(Z4="5. Fully Compliant (100%)","100"))))))<=32),"25",IF(AND((((_xlfn.XLOOKUP(Assessment!H5,Inherited!A:A,Inherited!B:B))/100)*(_xlfn.XLOOKUP(Assessment!H5,Inherited!A:A,Inherited!E:E)))+(((100-(_xlfn.XLOOKUP(Assessment!H5,Inherited!A:A,Inherited!B:B)))/100)*IF(Z4="1. Non Compliant (0%)","0",IF(Z4="2. Somewhat Compliant (25%)","25",IF(Z4="3. Partially Compliant (50%)","50",IF(Z4="4. Mostly Compliant (75%)","75",IF(Z4="5. Fully Compliant (100%)","100"))))))>=33,(((_xlfn.XLOOKUP(Assessment!H5,Inherited!A:A,Inherited!B:B))/100)*(_xlfn.XLOOKUP(Assessment!H5,Inherited!A:A,Inherited!E:E)))+(((100-(_xlfn.XLOOKUP(Assessment!H5,Inherited!A:A,Inherited!B:B)))/100)*IF(Z4="1. Non Compliant (0%)","0",IF(Z4="2. Somewhat Compliant (25%)","25",IF(Z4="3. Partially Compliant (50%)","50",IF(Z4="4. Mostly Compliant (75%)","75",IF(Z4="5. Fully Compliant (100%)","100"))))))<=65),"50",IF(AND((((_xlfn.XLOOKUP(Assessment!H5,Inherited!A:A,Inherited!B:B))/100)*(_xlfn.XLOOKUP(Assessment!H5,Inherited!A:A,Inherited!E:E)))+(((100-(_xlfn.XLOOKUP(Assessment!H5,Inherited!A:A,Inherited!B:B)))/100)*IF(Z4="1. Non Compliant (0%)","0",IF(Z4="2. Somewhat Compliant (25%)","25",IF(Z4="3. Partially Compliant (50%)","50",IF(Z4="4. Mostly Compliant (75%)","75",IF(Z4="5. Fully Compliant (100%)","100"))))))>=66,(((_xlfn.XLOOKUP(Assessment!H5,Inherited!A:A,Inherited!B:B))/100)*(_xlfn.XLOOKUP(Assessment!H5,Inherited!A:A,Inherited!E:E)))+(((100-(_xlfn.XLOOKUP(Assessment!H5,Inherited!A:A,Inherited!B:B)))/100)*IF(Z4="1. Non Compliant (0%)","0",IF(Z4="2. Somewhat Compliant (25%)","25",IF(Z4="3. Partially Compliant (50%)","50",IF(Z4="4. Mostly Compliant (75%)","75",IF(Z4="5. Fully Compliant (100%)","100"))))))<=89),"75",IF((((_xlfn.XLOOKUP(Assessment!H5,Inherited!A:A,Inherited!B:B))/100)*(_xlfn.XLOOKUP(Assessment!H5,Inherited!A:A,Inherited!E:E)))+(((100-(_xlfn.XLOOKUP(Assessment!H5,Inherited!A:A,Inherited!B:B)))/100)*IF(Z4="1. Non Compliant (0%)","0",IF(Z4="2. Somewhat Compliant (25%)","25",IF(Z4="3. Partially Compliant (50%)","50",IF(Z4="4. Mostly Compliant (75%)","75",IF(Z4="5. Fully Compliant (100%)","100"))))))>=90,"100")))))) -> #N/A | T4: =IF(MATCH(H4,Inherited!A:A),IF((((_xlfn.XLOOKUP(Assessment!H5,Inherited!A:A,Inherited!B:B))/100)*(_xlfn.XLOOKUP(Assessment!H5,Inherited!A:A,Inherited!F:F)))+(((100-(_xlfn.XLOOKUP(Assessment!H5,Inherited!A:A,Inherited!B:B)))/100)*IF(AA4="1. Non Compliant (0%)","0",IF(AA4="2. Somewhat Compliant (25%)","25",IF(AA4="3. Partially Compliant (50%)","50",IF(AA4="4. Mostly Compliant (75%)","75",IF(AA4="5. Fully Compliant (100%)","100"))))))<=10,"0", IF(AND((((_xlfn.XLOOKUP(Assessment!H5,Inherited!A:A,Inherited!B:B))/100)*(_xlfn.XLOOKUP(Assessment!H5,Inherited!A:A,Inherited!F:F)))+(((100-(_xlfn.XLOOKUP(Assessment!H5,Inherited!A:A,Inherited!B:B)))/100)*IF(AA4="1. Non Compliant (0%)","0",IF(AA4="2. Somewhat Compliant (25%)","25",IF(AA4="3. Partially Compliant (50%)","50",IF(AA4="4. Mostly Compliant (75%)","75",IF(AA4="5. Fully Compliant (100%)","100"))))))>=11,(((_xlfn.XLOOKUP(Assessment!H5,Inherited!A:A,Inherited!B:B))/100)*(_xlfn.XLOOKUP(Assessment!H5,Inherited!A:A,Inherited!F:F)))+(((100-(_xlfn.XLOOKUP(Assessment!H5,Inherited!A:A,Inherited!B:B)))/100)*IF(AA4="1. Non Compliant (0%)","0",IF(AA4="2. Somewhat Compliant (25%)","25",IF(AA4="3. Partially Compliant (50%)","50",IF(AA4="4. Mostly Compliant (75%)","75",IF(AA4="5. Fully Compliant (100%)","100"))))))<=32),"25",IF(AND((((_xlfn.XLOOKUP(Assessment!H5,Inherited!A:A,Inherited!B:B))/100)*(_xlfn.XLOOKUP(Assessment!H5,Inherited!A:A,Inherited!F:F)))+(((100-(_xlfn.XLOOKUP(Assessment!H5,Inherited!A:A,Inherited!B:B)))/100)*IF(AA4="1. Non Compliant (0%)","0",IF(AA4="2. Somewhat Compliant (25%)","25",IF(AA4="3. Partially Compliant (50%)","50",IF(AA4="4. Mostly Compliant (75%)","75",IF(AA4="5. Fully Compliant (100%)","100"))))))>=33,(((_xlfn.XLOOKUP(Assessment!H5,Inherited!A:A,Inherited!B:B))/100)*(_xlfn.XLOOKUP(Assessment!H5,Inherited!A:A,Inherited!F:F)))+(((100-(_xlfn.XLOOKUP(Assessment!H5,Inherited!A:A,Inherited!B:B)))/100)*IF(AA4="1. Non Compliant (0%)","0",IF(AA4="2. Somewhat Compliant (25%)","25",IF(AA4="3. Partially Compliant (50%)","50",IF(AA4="4. Mostly Compliant (75%)","75",IF(AA4="5. Fully Compliant (100%)","100"))))))<=65),"50",IF(AND((((_xlfn.XLOOKUP(Assessment!H5,Inherited!A:A,Inherited!B:B))/100)*(_xlfn.XLOOKUP(Assessment!H5,Inherited!A:A,Inherited!F:F)))+(((100-(_xlfn.XLOOKUP(Assessment!H5,Inherited!A:A,Inherited!B:B)))/100)*IF(AA4="1. Non Compliant (0%)","0",IF(AA4="2. Somewhat Compliant (25%)","25",IF(AA4="3. Partially Compliant (50%)","50",IF(AA4="4. Mostly Compliant (75%)","75",IF(AA4="5. Fully Compliant (100%)","100"))))))>=66,(((_xlfn.XLOOKUP(Assessment!H5,Inherited!A:A,Inherited!B:B))/100)*(_xlfn.XLOOKUP(Assessment!H5,Inherited!A:A,Inherited!F:F)))+(((100-(_xlfn.XLOOKUP(Assessment!H5,Inherited!A:A,Inherited!B:B)))/100)*IF(AA4="1. Non Compliant (0%)","0",IF(AA4="2. Somewhat Compliant (25%)","25",IF(AA4="3. Partially Compliant (50%)","50",IF(AA4="4. Mostly Compliant (75%)","75",IF(AA4="5. Fully Compliant (100%)","100"))))))<=89),"75",IF((((_xlfn.XLOOKUP(Assessment!H5,Inherited!A:A,Inherited!B:B))/100)*(_xlfn.XLOOKUP(Assessment!H5,Inherited!A:A,Inherited!F:F)))+(((100-(_xlfn.XLOOKUP(Assessment!H5,Inherited!A:A,Inherited!B:B)))/100)*IF(AA4="1. Non Compliant (0%)","0",IF(AA4="2. Somewhat Compliant (25%)","25",IF(AA4="3. Partially Compliant (50%)","50",IF(AA4="4. Mostly Compliant (75%)","75",IF(AA4="5. Fully Compliant (100%)","100"))))))>=90,"100")))))) -> #N/A | U4: =IF(MATCH(H4,Inherited!A:A),IF((((_xlfn.XLOOKUP(Assessment!H5,Inherited!A:A,Inherited!B:B))/100)*(_xlfn.XLOOKUP(Assessment!H5,Inherited!A:A,Inherited!G:G)))+(((100-(_xlfn.XLOOKUP(Assessment!H5,Inherited!A:A,Inherited!B:B)))/100)*IF(AB4="1. Non Compliant (0%)","0",IF(AB4="2. Somewhat Compliant (25%)","25",IF(AB4="3. Partially Compliant (50%)","50",IF(AB4="4. Mostly Compliant (75%)","75",IF(AB4="5. Fully Compliant (100%)","100"))))))<=10,"0", IF(AND((((_xlfn.XLOOKUP(Assessment!H5,Inherited!A:A,Inherited!B:B))/100)*(_xlfn.XLOOKUP(Assessment!H5,Inherited!A:A,Inherited!G:G)))+(((100-(_xlfn.XLOOKUP(Assessment!H5,Inherited!A:A,Inherited!B:B)))/100)*IF(AB4="1. Non Compliant (0%)","0",IF(AB4="2. Somewhat Compliant (25%)","25",IF(AB4="3. Partially Compliant (50%)","50",IF(AB4="4. Mostly Compliant (75%)","75",IF(AB4="5. Fully Compliant (100%)","100"))))))>=11,(((_xlfn.XLOOKUP(Assessment!H5,Inherited!A:A,Inherited!B:B))/100)*(_xlfn.XLOOKUP(Assessment!H5,Inherited!A:A,Inherited!G:G)))+(((100-(_xlfn.XLOOKUP(Assessment!H5,Inherited!A:A,Inherited!B:B)))/100)*IF(AB4="1. Non Compliant (0%)","0",IF(AB4="2. Somewhat Compliant (25%)","25",IF(AB4="3. Partially Compliant (50%)","50",IF(AB4="4. Mostly Compliant (75%)","75",IF(AB4="5. Fully Compliant (100%)","100"))))))<=32),"25",IF(AND((((_xlfn.XLOOKUP(Assessment!H5,Inherited!A:A,Inherited!B:B))/100)*(_xlfn.XLOOKUP(Assessment!H5,Inherited!A:A,Inherited!G:G)))+(((100-(_xlfn.XLOOKUP(Assessment!H5,Inherited!A:A,Inherited!B:B)))/100)*IF(AB4="1. Non Compliant (0%)","0",IF(AB4="2. Somewhat Compliant (25%)","25",IF(AB4="3. Partially Compliant (50%)","50",IF(AB4="4. Mostly Compliant (75%)","75",IF(AB4="5. Fully Compliant (100%)","100"))))))>=33,(((_xlfn.XLOOKUP(Assessment!H5,Inherited!A:A,Inherited!B:B))/100)*(_xlfn.XLOOKUP(Assessment!H5,Inherited!A:A,Inherited!G:G)))+(((100-(_xlfn.XLOOKUP(Assessment!H5,Inherited!A:A,Inherited!B:B)))/100)*IF(AB4="1. Non Compliant (0%)","0",IF(AB4="2. Somewhat Compliant (25%)","25",IF(AB4="3. Partially Compliant (50%)","50",IF(AB4="4. Mostly Compliant (75%)","75",IF(AB4="5. Fully Compliant (100%)","100"))))))<=65),"50",IF(AND((((_xlfn.XLOOKUP(Assessment!H5,Inherited!A:A,Inherited!B:B))/100)*(_xlfn.XLOOKUP(Assessment!H5,Inherited!A:A,Inherited!G:G)))+(((100-(_xlfn.XLOOKUP(Assessment!H5,Inherited!A:A,Inherited!B:B)))/100)*IF(AB4="1. Non Compliant (0%)","0",IF(AB4="2. Somewhat Compliant (25%)","25",IF(AB4="3. Partially Compliant (50%)","50",IF(AB4="4. Mostly Compliant (75%)","75",IF(AB4="5. Fully Compliant (100%)","100"))))))>=66,(((_xlfn.XLOOKUP(Assessment!H5,Inherited!A:A,Inherited!B:B))/100)*(_xlfn.XLOOKUP(Assessment!H5,Inherited!A:A,Inherited!G:G)))+(((100-(_xlfn.XLOOKUP(Assessment!H5,Inherited!A:A,Inherited!B:B)))/100)*IF(AB4="1. Non Compliant (0%)","0",IF(AB4="2. Somewhat Compliant (25%)","25",IF(AB4="3. Partially Compliant (50%)","50",IF(AB4="4. Mostly Compliant (75%)","75",IF(AB4="5. Fully Compliant (100%)","100"))))))<=89),"75",IF((((_xlfn.XLOOKUP(Assessment!H5,Inherited!A:A,Inherited!B:B))/100)*(_xlfn.XLOOKUP(Assessment!H5,Inherited!A:A,Inherited!G:G)))+(((100-(_xlfn.XLOOKUP(Assessment!H5,Inherited!A:A,Inherited!B:B)))/100)*IF(AB4="1. Non Compliant (0%)","0",IF(AB4="2. Somewhat Compliant (25%)","25",IF(AB4="3. Partially Compliant (50%)","50",IF(AB4="4. Mostly Compliant (75%)","75",IF(AB4="5. Fully Compliant (100%)","100"))))))>=90,"100")))))) -> #N/A | V4: Yes | Z4: 1. Non Compliant (0%) | AK4: Michael Wood - VP of AI Engineering Kyle Smith - IT Operations and AI Expert | AL4: AI policies and procedures are not formally maintained at this time. Documentation will be developed and integrated to existing Merge policies and procedures | AP4: Gap: AI policies and procedures considering the details of the requirement statement are not formally maintained at this time. Recommendation: Management should ensure that AI policies and procedures are developed considering the following: - defines relative legal requirements related to AI - defines guidelines on ethical use and design of AI - defines domain-specific guidelines and frameworks related to AI - defines technology trends and advancements related to areas of AI - defines societal and political implications of the deployment of AI systems - defines external stakeholder perceptions, needs, and expectations - defines how the use of AI can affect the ability of the organization to meet contractual obligations and guarantees - defines contractual relationships during the design and production of AI systems and services - defines how the use of AI can increase the complexity of networks and dependencies - defines how an AI system can replace an existing system - defines the risk benefits and risk transfers of an AI system versus the existing system can be undertaken, considering safety, environmental, social, technical and financial issues | AX4: =_xlfn.CONCAT("A-LIGN finished its review of this control on ",AR4, " during the scheduled fieldwork window (",Intro!$B$4,")."& CHAR(10)& CHAR(10)) -> A-LIGN finished its review of this control on during the scheduled fieldwork window (Fieldwork: xx/xx/xxxx - xx/xx/xxxx). | AY4: =IF(AQ4<>"",(_xlfn.CONCAT("Inheritance note: "& CHAR(10),AQ4& CHAR(10)& CHAR(10))),"") | AZ4: =IFERROR(IF(AD4<>"",_xlfn.CONCAT("Examined the following policy during fieldwork:"& CHAR(10),AD4& CHAR(10)& CHAR(10),IF(AND(X4<>"5. Fully Compliant (100%)",AE4<>""),"Reviewed policy exception note:"& CHAR(10) & AE4 & CHAR(10) & CHAR(10),"")),""),"") | BA4: =IFERROR(IF(AH4<>"",_xlfn.CONCAT("Examined the following process during fieldwork:"& CHAR(10),AH4& CHAR(10)& CHAR(10),IF(AND(Y4<>"5. Fully Compliant (100%)",AI4<>""),"Reviewed process exception note:"& CHAR(10) & AI4 & CHAR(10) & CHAR(10),"")),""),"") | BB4: =IF(AK4<>"",(_xlfn.CONCAT("Inquired of the following workforce member: "& CHAR(10),AK4& CHAR(10)& CHAR(10),"Inquiry lead to the following conclusions: "& CHAR(10),AL4& CHAR(10) & CHAR(10))),"") -> Inquired of the following workforce member: Michael Wood - VP of AI Engineering Kyle Smith - IT Operations and AI Expert Inquiry lead to the following conclusions: AI policies and procedures are not formally maintained at this time. Documentation will be developed and integrated to existing Merge policies and procedures | BC4: =IF(AM4<>"",(_xlfn.CONCAT("Observed the following live during fieldwork: "& CHAR(10),AM4& CHAR(10) & CHAR(10))),"") | BD4: =_xlfn.CONCAT("Examined the following evidence during fieldwork:"& CHAR(10),AN4& CHAR(10)& CHAR(10),IF(AO4<>"","Reviewed evidence note:"& CHAR(10)&AO4& CHAR(10) & CHAR(10),"Reviewed evidence addressed the requirement statement."& CHAR(10) & CHAR(10)),IF(AND(AP4<>"5. Fully Compliant (100%)",AP4<>""),"Reviewed evidence exception note: "& CHAR(10) & AP4 & CHAR(10) & CHAR(10),"")) -> Examined the following evidence during fieldwork: Reviewed evidence addressed the requirement statement. Reviewed evidence exception note: Gap: AI policies and procedures considering the details of the requirement statement are not formally maintained at this time. Recommendation: Management should ensure that AI policies and procedures are developed considering the following: - defines relative legal requirements related to AI - defines guidelines on ethical use and design of AI - defines domain-specific guidelines and frameworks related to AI - defines technology trends and advancements related to areas of AI - defines societal and political implications of the deployment of AI systems - defines external stakeholder perceptions, needs, and expectations - defines how the use of AI can affect the ability of the organization to meet contractual obligations and guarantees - defines contractual relationships during the design and production of AI systems and services - defines how the use of AI can increase the complexity of networks and dependencies - defines how an AI system can replace an existing system - defines the risk benefits and risk transfers of an AI system versus the existing system can be undertaken, considering safety, environmental, social, technical and financial issues | BE4: =IF(AT4<>"",(_xlfn.CONCAT("Examined the following measure/metric during fieldwork:"& CHAR(10),AT4& CHAR(10)& CHAR(10),"Reviewed measure/metric note:"& CHAR(10),AU4 & CHAR(10) & CHAR(10))),"") | BF4: =IF(AV4<>"",(_xlfn.CONCAT("Examined the following measure/metric management during fieldwork:"& CHAR(10),AV4& CHAR(10)& CHAR(10),"Reviewed measure/metric management note:"& CHAR(10),AW4 & CHAR(10) & CHAR(10))),"") | BG4: =_xlfn.CONCAT((IF((COUNTIF('Sample Tables'!B:B,"")>0)=TRUE,_xlfn.CONCAT("",""),IF((COUNTIF('Sample Tables'!B:B,"")>0)=FALSE,""))),) | BH4: =IF(V4="No","Not Applicable: "&W4,(_xlfn.CONCAT(AX4,AY4,AZ4,BA4,BB4,BC4,BD4,BE4,BF4,BG4))) -> A-LIGN finished its review of this control on during the scheduled fieldwork window (Fieldwork: xx/xx/xxxx - xx/xx/xxxx). Inquired of the following workforce member: Michael Wood - VP of AI Engineering Kyle Smith - IT Operations and AI Expert Inquiry lead to the following conclusions: AI policies and procedures are not formally maintained at this time. Documentation will be developed and integrated to existing Merge policies and procedures Examined the following evidence during fieldwork: Reviewed evidence addressed the requirement statement. Reviewed evidence exception note: Gap: AI policies and procedures considering the details of the requirement statement are not formally maintained at this time. Recommendation: Management should ensure that AI policies and procedures are developed considering the following: - defines relative legal requirements related to AI - defines guidelines on ethical use and design of AI - defines domain-specific guidelines and frameworks related to AI - defines technology trends and advancements related to areas of AI - defines societal and political implications of the deployment of AI systems - defines external stakeholder perceptions, needs, and expectations - defines how the use of AI can affect the ability of the organization to meet contractual obligations and guarantees - defines contractual relationships during the design and production of AI systems and services - defines how the use of AI can increase the complexity of networks and dependencies - defines how an AI system can replace an existing system - defines the risk benefits and risk transfers of an AI system versus the existing system can be undertaken, considering safety, environmental, social, technical and financial issues
C5: =IF(V5="No","Not Applicable",(IF(X5="1. Non Compliant (0%)","0",IF(X5="2. Somewhat Compliant (25%)","25",IF(X5="3. Partially Compliant (50%)","50",IF(X5="4. Mostly Compliant (75%)","75",IF(X5="5. Fully Compliant (100%)","100")))))*0.15)+((IF(Y5="1. Non Compliant (0%)","0",IF(Y5="2. Somewhat Compliant (25%)","25",IF(Y5="3. Partially Compliant (50%)","50",IF(Y5="4. Mostly Compliant (75%)","75",IF(Y5="5. Fully Compliant (100%)","100"))))))*0.2)+(IF(Z5="1. Non Compliant (0%)","0",IF(Z5="2. Somewhat Compliant (25%)","25",IF(Z5="3. Partially Compliant (50%)","50",IF(Z5="4. Mostly Compliant (75%)","75",IF(Z5="5. Fully Compliant (100%)","100")))))*0.4)+(IF(AA5="1. Non Compliant (0%)","0",IF(AA5="2. Somewhat Compliant (25%)","25",IF(AA5="3. Partially Compliant (50%)","50",IF(AA5="4. Mostly Compliant (75%)","75",IF(AA5="5. Fully Compliant (100%)","100")))))*0.1)+(IF(AB5="1. Non Compliant (0%)","0",IF(AB5="2. Somewhat Compliant (25%)","25",IF(AB5="3. Partially Compliant (50%)","50",IF(AB5="4. Mostly Compliant (75%)","75",IF(AB5="5. Fully Compliant (100%)","100")))))*0.15)) -> 0 | D5: =IF(AND((_xlfn.XLOOKUP(J5,'Fields & Revisions'!$H:$H,'Fields & Revisions'!$I:$I))<70.99,(OR(Z5="4. Mostly Compliant (75%)",Z5="3. Partially Compliant (50%)",Z5="2. Somewhat Compliant (25%)",Z5="1. Non Compliant (0%)"))),"Yes","No") -> Yes | E5: =IF(ISERROR(VLOOKUP(H5,Scope!A:A,1,FALSE)),"No","Yes") -> Yes | F5: 01 Information Protection Program | G5: 2810.0 | H5: 01.03aISO23894Organizational.13 | I5: ISO/IEC 23894 | J5: 03.a Risk Management Program Development | K5: The organization maintains documentation of the following aspects of the internal context of organization's development and/or use of AI: |the effect that an AI system can have on the organization’s culture by shifting and introducing new responsibilities, roles and tasks; |any additional international, regional, national and local standards and guidelines that are imposed by the use of AI systems; |the additional risks to organizational knowledge related to transparency and explainability of AI systems; |the use of AI systems can result in changes to the number of human resources needed to realize a certain capability, or in a variation of the type of resources needed, for instance, deskilling or loss of expertise where human decision-making is increasingly supported by AI systems; |the specific knowledge in AI technologies and data science required to develop and use AI systems; |the availability of AI tools, platforms and libraries which can enable the development of AI systems without there being a full understanding of the technology, its limitations and potential pitfalls; |the potential for AI to raise issues and opportunities related to intellectual property for specific AI systems; |how AI systems can be used to automate, optimize and enhance data handling; |as consumers of data, additional quality and completeness constraints on data and information can be imposed by AI systems; |internal stakeholder perceptions, needs, and expectations; |how the use of AI systems can increase the complexity of interdependencies and interconnections; |the consideration that the use of AI systems can increase the need for specialized training.|| | L5: Examine evidence that all evaluative elements within the requirement statement have been implemented as defined in the HITRUST scoring rubric, using a sample based test where possible for each evaluative element._x000D_ _x000D_ _x000D_ Example test(s):_x000D_ For example, obtain and examine evidence to confirm the organization has documented its considerations of the internal context of the organization per the elements stipulated in the requirement statement. | M5: Documentation: Artificial Intelligence Program - defines the effect that an AI system can have on the organization’s culture by shifting and introducing new responsibilities, roles and tasks - defines any additional international, regional, national and local standards and guidelines that are imposed by the use of AI systems - defines the additional risks to organizational knowledge related to transparency and explainability of AI systems - defines that the use of AI systems can result in changes to the number of human resources needed to realize a certain capability, or in a variation of the type of resources needed - defines the specific knowledge in AI technologies and data science required to develop and use AI systems - defines the availability of AI tools, platforms and libraries which can enable the development of AI systems without there being a full understanding of the technology, its limitations and potential pitfalls - defines the potential for AI to raise issues and opportunities related to intellectual property for specific AI systems - defines how AI systems can be used to automate, optimize and enhance data handling - defines additional quality and completeness constraints on data and information can be imposed by AI systems - defines how the use of AI systems can increase the complexity of interdependencies and interconnections - defines the consideration that the use of AI systems can increase the need for specialized training | N5: No | O5: =_xlfn.XLOOKUP(G5,SRMs!$A:$A,SRMs!$D:$D) -> NO INHERITANCE | P5: =IFERROR(VLOOKUP(H5,Inherited!A:B,2,FALSE),"") | Q5: =IF(MATCH(H5,Inherited!A:A),IF((((_xlfn.XLOOKUP(Assessment!H6,Inherited!A:A,Inherited!B:B))/100)*(_xlfn.XLOOKUP(Assessment!H6,Inherited!A:A,Inherited!C:C)))+(((100-(_xlfn.XLOOKUP(Assessment!H6,Inherited!A:A,Inherited!B:B)))/100)*IF(X5="1. Non Compliant (0%)","0",IF(X5="2. Somewhat Compliant (25%)","25",IF(X5="3. Partially Compliant (50%)","50",IF(X5="4. Mostly Compliant (75%)","75",IF(X5="5. Fully Compliant (100%)","100"))))))<=10,"0", IF(AND((((_xlfn.XLOOKUP(Assessment!H6,Inherited!A:A,Inherited!B:B))/100)*(_xlfn.XLOOKUP(Assessment!H6,Inherited!A:A,Inherited!C:C)))+(((100-(_xlfn.XLOOKUP(Assessment!H6,Inherited!A:A,Inherited!B:B)))/100)*IF(X5="1. Non Compliant (0%)","0",IF(X5="2. Somewhat Compliant (25%)","25",IF(X5="3. Partially Compliant (50%)","50",IF(X5="4. Mostly Compliant (75%)","75",IF(X5="5. Fully Compliant (100%)","100"))))))>=11,(((_xlfn.XLOOKUP(Assessment!H6,Inherited!A:A,Inherited!B:B))/100)*(_xlfn.XLOOKUP(Assessment!H6,Inherited!A:A,Inherited!C:C)))+(((100-(_xlfn.XLOOKUP(Assessment!H6,Inherited!A:A,Inherited!B:B)))/100)*IF(X5="1. Non Compliant (0%)","0",IF(X5="2. Somewhat Compliant (25%)","25",IF(X5="3. Partially Compliant (50%)","50",IF(X5="4. Mostly Compliant (75%)","75",IF(X5="5. Fully Compliant (100%)","100"))))))<=32),"25",IF(AND((((_xlfn.XLOOKUP(Assessment!H6,Inherited!A:A,Inherited!B:B))/100)*(_xlfn.XLOOKUP(Assessment!H6,Inherited!A:A,Inherited!C:C)))+(((100-(_xlfn.XLOOKUP(Assessment!H6,Inherited!A:A,Inherited!B:B)))/100)*IF(X5="1. Non Compliant (0%)","0",IF(X5="2. Somewhat Compliant (25%)","25",IF(X5="3. Partially Compliant (50%)","50",IF(X5="4. Mostly Compliant (75%)","75",IF(X5="5. Fully Compliant (100%)","100"))))))>=33,(((_xlfn.XLOOKUP(Assessment!H6,Inherited!A:A,Inherited!B:B))/100)*(_xlfn.XLOOKUP(Assessment!H6,Inherited!A:A,Inherited!C:C)))+(((100-(_xlfn.XLOOKUP(Assessment!H6,Inherited!A:A,Inherited!B:B)))/100)*IF(X5="1. Non Compliant (0%)","0",IF(X5="2. Somewhat Compliant (25%)","25",IF(X5="3. Partially Compliant (50%)","50",IF(X5="4. Mostly Compliant (75%)","75",IF(X5="5. Fully Compliant (100%)","100"))))))<=65),"50",IF(AND((((_xlfn.XLOOKUP(Assessment!H6,Inherited!A:A,Inherited!B:B))/100)*(_xlfn.XLOOKUP(Assessment!H6,Inherited!A:A,Inherited!C:C)))+(((100-(_xlfn.XLOOKUP(Assessment!H6,Inherited!A:A,Inherited!B:B)))/100)*IF(X5="1. Non Compliant (0%)","0",IF(X5="2. Somewhat Compliant (25%)","25",IF(X5="3. Partially Compliant (50%)","50",IF(X5="4. Mostly Compliant (75%)","75",IF(X5="5. Fully Compliant (100%)","100"))))))>=66,(((_xlfn.XLOOKUP(Assessment!H6,Inherited!A:A,Inherited!B:B))/100)*(_xlfn.XLOOKUP(Assessment!H6,Inherited!A:A,Inherited!C:C)))+(((100-(_xlfn.XLOOKUP(Assessment!H6,Inherited!A:A,Inherited!B:B)))/100)*IF(X5="1. Non Compliant (0%)","0",IF(X5="2. Somewhat Compliant (25%)","25",IF(X5="3. Partially Compliant (50%)","50",IF(X5="4. Mostly Compliant (75%)","75",IF(X5="5. Fully Compliant (100%)","100"))))))<=89),"75",IF((((_xlfn.XLOOKUP(Assessment!H6,Inherited!A:A,Inherited!B:B))/100)*(_xlfn.XLOOKUP(Assessment!H6,Inherited!A:A,Inherited!C:C)))+(((100-(_xlfn.XLOOKUP(Assessment!H6,Inherited!A:A,Inherited!B:B)))/100)*IF(X5="1. Non Compliant (0%)","0",IF(X5="2. Somewhat Compliant (25%)","25",IF(X5="3. Partially Compliant (50%)","50",IF(X5="4. Mostly Compliant (75%)","75",IF(X5="5. Fully Compliant (100%)","100"))))))>=90,"100")))))) -> #N/A | R5: =IF(MATCH(H5,Inherited!A:A),IF((((_xlfn.XLOOKUP(Assessment!H6,Inherited!A:A,Inherited!B:B))/100)*(_xlfn.XLOOKUP(Assessment!H6,Inherited!A:A,Inherited!D:D)))+(((100-(_xlfn.XLOOKUP(Assessment!H6,Inherited!A:A,Inherited!B:B)))/100)*IF(Y5="1. Non Compliant (0%)","0",IF(Y5="2. Somewhat Compliant (25%)","25",IF(Y5="3. Partially Compliant (50%)","50",IF(Y5="4. Mostly Compliant (75%)","75",IF(Y5="5. Fully Compliant (100%)","100"))))))<=10,"0", IF(AND((((_xlfn.XLOOKUP(Assessment!H6,Inherited!A:A,Inherited!B:B))/100)*(_xlfn.XLOOKUP(Assessment!H6,Inherited!A:A,Inherited!D:D)))+(((100-(_xlfn.XLOOKUP(Assessment!H6,Inherited!A:A,Inherited!B:B)))/100)*IF(Y5="1. Non Compliant (0%)","0",IF(Y5="2. Somewhat Compliant (25%)","25",IF(Y5="3. Partially Compliant (50%)","50",IF(Y5="4. Mostly Compliant (75%)","75",IF(Y5="5. Fully Compliant (100%)","100"))))))>=11,(((_xlfn.XLOOKUP(Assessment!H6,Inherited!A:A,Inherited!B:B))/100)*(_xlfn.XLOOKUP(Assessment!H6,Inherited!A:A,Inherited!D:D)))+(((100-(_xlfn.XLOOKUP(Assessment!H6,Inherited!A:A,Inherited!B:B)))/100)*IF(Y5="1. Non Compliant (0%)","0",IF(Y5="2. Somewhat Compliant (25%)","25",IF(Y5="3. Partially Compliant (50%)","50",IF(Y5="4. Mostly Compliant (75%)","75",IF(Y5="5. Fully Compliant (100%)","100"))))))<=32),"25",IF(AND((((_xlfn.XLOOKUP(Assessment!H6,Inherited!A:A,Inherited!B:B))/100)*(_xlfn.XLOOKUP(Assessment!H6,Inherited!A:A,Inherited!D:D)))+(((100-(_xlfn.XLOOKUP(Assessment!H6,Inherited!A:A,Inherited!B:B)))/100)*IF(Y5="1. Non Compliant (0%)","0",IF(Y5="2. Somewhat Compliant (25%)","25",IF(Y5="3. Partially Compliant (50%)","50",IF(Y5="4. Mostly Compliant (75%)","75",IF(Y5="5. Fully Compliant (100%)","100"))))))>=33,(((_xlfn.XLOOKUP(Assessment!H6,Inherited!A:A,Inherited!B:B))/100)*(_xlfn.XLOOKUP(Assessment!H6,Inherited!A:A,Inherited!D:D)))+(((100-(_xlfn.XLOOKUP(Assessment!H6,Inherited!A:A,Inherited!B:B)))/100)*IF(Y5="1. Non Compliant (0%)","0",IF(Y5="2. Somewhat Compliant (25%)","25",IF(Y5="3. Partially Compliant (50%)","50",IF(Y5="4. Mostly Compliant (75%)","75",IF(Y5="5. Fully Compliant (100%)","100"))))))<=65),"50",IF(AND((((_xlfn.XLOOKUP(Assessment!H6,Inherited!A:A,Inherited!B:B))/100)*(_xlfn.XLOOKUP(Assessment!H6,Inherited!A:A,Inherited!D:D)))+(((100-(_xlfn.XLOOKUP(Assessment!H6,Inherited!A:A,Inherited!B:B)))/100)*IF(Y5="1. Non Compliant (0%)","0",IF(Y5="2. Somewhat Compliant (25%)","25",IF(Y5="3. Partially Compliant (50%)","50",IF(Y5="4. Mostly Compliant (75%)","75",IF(Y5="5. Fully Compliant (100%)","100"))))))>=66,(((_xlfn.XLOOKUP(Assessment!H6,Inherited!A:A,Inherited!B:B))/100)*(_xlfn.XLOOKUP(Assessment!H6,Inherited!A:A,Inherited!D:D)))+(((100-(_xlfn.XLOOKUP(Assessment!H6,Inherited!A:A,Inherited!B:B)))/100)*IF(Y5="1. Non Compliant (0%)","0",IF(Y5="2. Somewhat Compliant (25%)","25",IF(Y5="3. Partially Compliant (50%)","50",IF(Y5="4. Mostly Compliant (75%)","75",IF(Y5="5. Fully Compliant (100%)","100"))))))<=89),"75",IF((((_xlfn.XLOOKUP(Assessment!H6,Inherited!A:A,Inherited!B:B))/100)*(_xlfn.XLOOKUP(Assessment!H6,Inherited!A:A,Inherited!D:D)))+(((100-(_xlfn.XLOOKUP(Assessment!H6,Inherited!A:A,Inherited!B:B)))/100)*IF(Y5="1. Non Compliant (0%)","0",IF(Y5="2. Somewhat Compliant (25%)","25",IF(Y5="3. Partially Compliant (50%)","50",IF(Y5="4. Mostly Compliant (75%)","75",IF(Y5="5. Fully Compliant (100%)","100"))))))>=90,"100")))))) -> #N/A | S5: =IF(MATCH(H5,Inherited!A:A),IF((((_xlfn.XLOOKUP(Assessment!H6,Inherited!A:A,Inherited!B:B))/100)*(_xlfn.XLOOKUP(Assessment!H6,Inherited!A:A,Inherited!E:E)))+(((100-(_xlfn.XLOOKUP(Assessment!H6,Inherited!A:A,Inherited!B:B)))/100)*IF(Z5="1. Non Compliant (0%)","0",IF(Z5="2. Somewhat Compliant (25%)","25",IF(Z5="3. Partially Compliant (50%)","50",IF(Z5="4. Mostly Compliant (75%)","75",IF(Z5="5. Fully Compliant (100%)","100"))))))<=10,"0", IF(AND((((_xlfn.XLOOKUP(Assessment!H6,Inherited!A:A,Inherited!B:B))/100)*(_xlfn.XLOOKUP(Assessment!H6,Inherited!A:A,Inherited!E:E)))+(((100-(_xlfn.XLOOKUP(Assessment!H6,Inherited!A:A,Inherited!B:B)))/100)*IF(Z5="1. Non Compliant (0%)","0",IF(Z5="2. Somewhat Compliant (25%)","25",IF(Z5="3. Partially Compliant (50%)","50",IF(Z5="4. Mostly Compliant (75%)","75",IF(Z5="5. Fully Compliant (100%)","100"))))))>=11,(((_xlfn.XLOOKUP(Assessment!H6,Inherited!A:A,Inherited!B:B))/100)*(_xlfn.XLOOKUP(Assessment!H6,Inherited!A:A,Inherited!E:E)))+(((100-(_xlfn.XLOOKUP(Assessment!H6,Inherited!A:A,Inherited!B:B)))/100)*IF(Z5="1. Non Compliant (0%)","0",IF(Z5="2. Somewhat Compliant (25%)","25",IF(Z5="3. Partially Compliant (50%)","50",IF(Z5="4. Mostly Compliant (75%)","75",IF(Z5="5. Fully Compliant (100%)","100"))))))<=32),"25",IF(AND((((_xlfn.XLOOKUP(Assessment!H6,Inherited!A:A,Inherited!B:B))/100)*(_xlfn.XLOOKUP(Assessment!H6,Inherited!A:A,Inherited!E:E)))+(((100-(_xlfn.XLOOKUP(Assessment!H6,Inherited!A:A,Inherited!B:B)))/100)*IF(Z5="1. Non Compliant (0%)","0",IF(Z5="2. Somewhat Compliant (25%)","25",IF(Z5="3. Partially Compliant (50%)","50",IF(Z5="4. Mostly Compliant (75%)","75",IF(Z5="5. Fully Compliant (100%)","100"))))))>=33,(((_xlfn.XLOOKUP(Assessment!H6,Inherited!A:A,Inherited!B:B))/100)*(_xlfn.XLOOKUP(Assessment!H6,Inherited!A:A,Inherited!E:E)))+(((100-(_xlfn.XLOOKUP(Assessment!H6,Inherited!A:A,Inherited!B:B)))/100)*IF(Z5="1. Non Compliant (0%)","0",IF(Z5="2. Somewhat Compliant (25%)","25",IF(Z5="3. Partially Compliant (50%)","50",IF(Z5="4. Mostly Compliant (75%)","75",IF(Z5="5. Fully Compliant (100%)","100"))))))<=65),"50",IF(AND((((_xlfn.XLOOKUP(Assessment!H6,Inherited!A:A,Inherited!B:B))/100)*(_xlfn.XLOOKUP(Assessment!H6,Inherited!A:A,Inherited!E:E)))+(((100-(_xlfn.XLOOKUP(Assessment!H6,Inherited!A:A,Inherited!B:B)))/100)*IF(Z5="1. Non Compliant (0%)","0",IF(Z5="2. Somewhat Compliant (25%)","25",IF(Z5="3. Partially Compliant (50%)","50",IF(Z5="4. Mostly Compliant (75%)","75",IF(Z5="5. Fully Compliant (100%)","100"))))))>=66,(((_xlfn.XLOOKUP(Assessment!H6,Inherited!A:A,Inherited!B:B))/100)*(_xlfn.XLOOKUP(Assessment!H6,Inherited!A:A,Inherited!E:E)))+(((100-(_xlfn.XLOOKUP(Assessment!H6,Inherited!A:A,Inherited!B:B)))/100)*IF(Z5="1. Non Compliant (0%)","0",IF(Z5="2. Somewhat Compliant (25%)","25",IF(Z5="3. Partially Compliant (50%)","50",IF(Z5="4. Mostly Compliant (75%)","75",IF(Z5="5. Fully Compliant (100%)","100"))))))<=89),"75",IF((((_xlfn.XLOOKUP(Assessment!H6,Inherited!A:A,Inherited!B:B))/100)*(_xlfn.XLOOKUP(Assessment!H6,Inherited!A:A,Inherited!E:E)))+(((100-(_xlfn.XLOOKUP(Assessment!H6,Inherited!A:A,Inherited!B:B)))/100)*IF(Z5="1. Non Compliant (0%)","0",IF(Z5="2. Somewhat Compliant (25%)","25",IF(Z5="3. Partially Compliant (50%)","50",IF(Z5="4. Mostly Compliant (75%)","75",IF(Z5="5. Fully Compliant (100%)","100"))))))>=90,"100")))))) -> #N/A | T5: =IF(MATCH(H5,Inherited!A:A),IF((((_xlfn.XLOOKUP(Assessment!H6,Inherited!A:A,Inherited!B:B))/100)*(_xlfn.XLOOKUP(Assessment!H6,Inherited!A:A,Inherited!F:F)))+(((100-(_xlfn.XLOOKUP(Assessment!H6,Inherited!A:A,Inherited!B:B)))/100)*IF(AA5="1. Non Compliant (0%)","0",IF(AA5="2. Somewhat Compliant (25%)","25",IF(AA5="3. Partially Compliant (50%)","50",IF(AA5="4. Mostly Compliant (75%)","75",IF(AA5="5. Fully Compliant (100%)","100"))))))<=10,"0", IF(AND((((_xlfn.XLOOKUP(Assessment!H6,Inherited!A:A,Inherited!B:B))/100)*(_xlfn.XLOOKUP(Assessment!H6,Inherited!A:A,Inherited!F:F)))+(((100-(_xlfn.XLOOKUP(Assessment!H6,Inherited!A:A,Inherited!B:B)))/100)*IF(AA5="1. Non Compliant (0%)","0",IF(AA5="2. Somewhat Compliant (25%)","25",IF(AA5="3. Partially Compliant (50%)","50",IF(AA5="4. Mostly Compliant (75%)","75",IF(AA5="5. Fully Compliant (100%)","100"))))))>=11,(((_xlfn.XLOOKUP(Assessment!H6,Inherited!A:A,Inherited!B:B))/100)*(_xlfn.XLOOKUP(Assessment!H6,Inherited!A:A,Inherited!F:F)))+(((100-(_xlfn.XLOOKUP(Assessment!H6,Inherited!A:A,Inherited!B:B)))/100)*IF(AA5="1. Non Compliant (0%)","0",IF(AA5="2. Somewhat Compliant (25%)","25",IF(AA5="3. Partially Compliant (50%)","50",IF(AA5="4. Mostly Compliant (75%)","75",IF(AA5="5. Fully Compliant (100%)","100"))))))<=32),"25",IF(AND((((_xlfn.XLOOKUP(Assessment!H6,Inherited!A:A,Inherited!B:B))/100)*(_xlfn.XLOOKUP(Assessment!H6,Inherited!A:A,Inherited!F:F)))+(((100-(_xlfn.XLOOKUP(Assessment!H6,Inherited!A:A,Inherited!B:B)))/100)*IF(AA5="1. Non Compliant (0%)","0",IF(AA5="2. Somewhat Compliant (25%)","25",IF(AA5="3. Partially Compliant (50%)","50",IF(AA5="4. Mostly Compliant (75%)","75",IF(AA5="5. Fully Compliant (100%)","100"))))))>=33,(((_xlfn.XLOOKUP(Assessment!H6,Inherited!A:A,Inherited!B:B))/100)*(_xlfn.XLOOKUP(Assessment!H6,Inherited!A:A,Inherited!F:F)))+(((100-(_xlfn.XLOOKUP(Assessment!H6,Inherited!A:A,Inherited!B:B)))/100)*IF(AA5="1. Non Compliant (0%)","0",IF(AA5="2. Somewhat Compliant (25%)","25",IF(AA5="3. Partially Compliant (50%)","50",IF(AA5="4. Mostly Compliant (75%)","75",IF(AA5="5. Fully Compliant (100%)","100"))))))<=65),"50",IF(AND((((_xlfn.XLOOKUP(Assessment!H6,Inherited!A:A,Inherited!B:B))/100)*(_xlfn.XLOOKUP(Assessment!H6,Inherited!A:A,Inherited!F:F)))+(((100-(_xlfn.XLOOKUP(Assessment!H6,Inherited!A:A,Inherited!B:B)))/100)*IF(AA5="1. Non Compliant (0%)","0",IF(AA5="2. Somewhat Compliant (25%)","25",IF(AA5="3. Partially Compliant (50%)","50",IF(AA5="4. Mostly Compliant (75%)","75",IF(AA5="5. Fully Compliant (100%)","100"))))))>=66,(((_xlfn.XLOOKUP(Assessment!H6,Inherited!A:A,Inherited!B:B))/100)*(_xlfn.XLOOKUP(Assessment!H6,Inherited!A:A,Inherited!F:F)))+(((100-(_xlfn.XLOOKUP(Assessment!H6,Inherited!A:A,Inherited!B:B)))/100)*IF(AA5="1. Non Compliant (0%)","0",IF(AA5="2. Somewhat Compliant (25%)","25",IF(AA5="3. Partially Compliant (50%)","50",IF(AA5="4. Mostly Compliant (75%)","75",IF(AA5="5. Fully Compliant (100%)","100"))))))<=89),"75",IF((((_xlfn.XLOOKUP(Assessment!H6,Inherited!A:A,Inherited!B:B))/100)*(_xlfn.XLOOKUP(Assessment!H6,Inherited!A:A,Inherited!F:F)))+(((100-(_xlfn.XLOOKUP(Assessment!H6,Inherited!A:A,Inherited!B:B)))/100)*IF(AA5="1. Non Compliant (0%)","0",IF(AA5="2. Somewhat Compliant (25%)","25",IF(AA5="3. Partially Compliant (50%)","50",IF(AA5="4. Mostly Compliant (75%)","75",IF(AA5="5. Fully Compliant (100%)","100"))))))>=90,"100")))))) -> #N/A | U5: =IF(MATCH(H5,Inherited!A:A),IF((((_xlfn.XLOOKUP(Assessment!H6,Inherited!A:A,Inherited!B:B))/100)*(_xlfn.XLOOKUP(Assessment!H6,Inherited!A:A,Inherited!G:G)))+(((100-(_xlfn.XLOOKUP(Assessment!H6,Inherited!A:A,Inherited!B:B)))/100)*IF(AB5="1. Non Compliant (0%)","0",IF(AB5="2. Somewhat Compliant (25%)","25",IF(AB5="3. Partially Compliant (50%)","50",IF(AB5="4. Mostly Compliant (75%)","75",IF(AB5="5. Fully Compliant (100%)","100"))))))<=10,"0", IF(AND((((_xlfn.XLOOKUP(Assessment!H6,Inherited!A:A,Inherited!B:B))/100)*(_xlfn.XLOOKUP(Assessment!H6,Inherited!A:A,Inherited!G:G)))+(((100-(_xlfn.XLOOKUP(Assessment!H6,Inherited!A:A,Inherited!B:B)))/100)*IF(AB5="1. Non Compliant (0%)","0",IF(AB5="2. Somewhat Compliant (25%)","25",IF(AB5="3. Partially Compliant (50%)","50",IF(AB5="4. Mostly Compliant (75%)","75",IF(AB5="5. Fully Compliant (100%)","100"))))))>=11,(((_xlfn.XLOOKUP(Assessment!H6,Inherited!A:A,Inherited!B:B))/100)*(_xlfn.XLOOKUP(Assessment!H6,Inherited!A:A,Inherited!G:G)))+(((100-(_xlfn.XLOOKUP(Assessment!H6,Inherited!A:A,Inherited!B:B)))/100)*IF(AB5="1. Non Compliant (0%)","0",IF(AB5="2. Somewhat Compliant (25%)","25",IF(AB5="3. Partially Compliant (50%)","50",IF(AB5="4. Mostly Compliant (75%)","75",IF(AB5="5. Fully Compliant (100%)","100"))))))<=32),"25",IF(AND((((_xlfn.XLOOKUP(Assessment!H6,Inherited!A:A,Inherited!B:B))/100)*(_xlfn.XLOOKUP(Assessment!H6,Inherited!A:A,Inherited!G:G)))+(((100-(_xlfn.XLOOKUP(Assessment!H6,Inherited!A:A,Inherited!B:B)))/100)*IF(AB5="1. Non Compliant (0%)","0",IF(AB5="2. Somewhat Compliant (25%)","25",IF(AB5="3. Partially Compliant (50%)","50",IF(AB5="4. Mostly Compliant (75%)","75",IF(AB5="5. Fully Compliant (100%)","100"))))))>=33,(((_xlfn.XLOOKUP(Assessment!H6,Inherited!A:A,Inherited!B:B))/100)*(_xlfn.XLOOKUP(Assessment!H6,Inherited!A:A,Inherited!G:G)))+(((100-(_xlfn.XLOOKUP(Assessment!H6,Inherited!A:A,Inherited!B:B)))/100)*IF(AB5="1. Non Compliant (0%)","0",IF(AB5="2. Somewhat Compliant (25%)","25",IF(AB5="3. Partially Compliant (50%)","50",IF(AB5="4. Mostly Compliant (75%)","75",IF(AB5="5. Fully Compliant (100%)","100"))))))<=65),"50",IF(AND((((_xlfn.XLOOKUP(Assessment!H6,Inherited!A:A,Inherited!B:B))/100)*(_xlfn.XLOOKUP(Assessment!H6,Inherited!A:A,Inherited!G:G)))+(((100-(_xlfn.XLOOKUP(Assessment!H6,Inherited!A:A,Inherited!B:B)))/100)*IF(AB5="1. Non Compliant (0%)","0",IF(AB5="2. Somewhat Compliant (25%)","25",IF(AB5="3. Partially Compliant (50%)","50",IF(AB5="4. Mostly Compliant (75%)","75",IF(AB5="5. Fully Compliant (100%)","100"))))))>=66,(((_xlfn.XLOOKUP(Assessment!H6,Inherited!A:A,Inherited!B:B))/100)*(_xlfn.XLOOKUP(Assessment!H6,Inherited!A:A,Inherited!G:G)))+(((100-(_xlfn.XLOOKUP(Assessment!H6,Inherited!A:A,Inherited!B:B)))/100)*IF(AB5="1. Non Compliant (0%)","0",IF(AB5="2. Somewhat Compliant (25%)","25",IF(AB5="3. Partially Compliant (50%)","50",IF(AB5="4. Mostly Compliant (75%)","75",IF(AB5="5. Fully Compliant (100%)","100"))))))<=89),"75",IF((((_xlfn.XLOOKUP(Assessment!H6,Inherited!A:A,Inherited!B:B))/100)*(_xlfn.XLOOKUP(Assessment!H6,Inherited!A:A,Inherited!G:G)))+(((100-(_xlfn.XLOOKUP(Assessment!H6,Inherited!A:A,Inherited!B:B)))/100)*IF(AB5="1. Non Compliant (0%)","0",IF(AB5="2. Somewhat Compliant (25%)","25",IF(AB5="3. Partially Compliant (50%)","50",IF(AB5="4. Mostly Compliant (75%)","75",IF(AB5="5. Fully Compliant (100%)","100"))))))>=90,"100")))))) -> #N/A | V5: Yes | Z5: 1. Non Compliant (0%) | AK5: Michael Wood - VP of AI Engineering Kyle Smith - IT Operations and AI Expert | AL5: AI policies and procedures are not formally maintained at this time. Documentation will be developed and integrated to existing Merge policies and procedures | AP5: Gap: AI policies and procedures considering the details of the requirement statement are not formally maintained at this time. Recommendation: Management should ensure that AI policies and procedures are developed considering the following: - defines the effect that an AI system can have on the organization’s culture by shifting and introducing new responsibilities, roles and tasks - defines any additional international, regional, national and local standards and guidelines that are imposed by the use of AI systems - defines the additional risks to organizational knowledge related to transparency and explainability of AI systems - defines that the use of AI systems can result in changes to the number of human resources needed to realize a certain capability, or in a variation of the type of resources needed - defines the specific knowledge in AI technologies and data science required to develop and use AI systems - defines the availability of AI tools, platforms and libraries which can enable the development of AI systems without there being a full understanding of the technology, its limitations and potential pitfalls - defines the potential for AI to raise issues and opportunities related to intellectual property for specific AI systems - defines how AI systems can be used to automate, optimize and enhance data handling - defines additional quality and completeness constraints on data and information can be imposed by AI systems - defines how the use of AI systems can increase the complexity of interdependencies and interconnections - defines the consideration that the use of AI systems can increase the need for specialized training | AX5: =_xlfn.CONCAT("A-LIGN finished its review of this control on ",AR5, " during the scheduled fieldwork window (",Intro!$B$4,")."& CHAR(10)& CHAR(10)) -> A-LIGN finished its review of this control on during the scheduled fieldwork window (Fieldwork: xx/xx/xxxx - xx/xx/xxxx). | AY5: =IF(AQ5<>"",(_xlfn.CONCAT("Inheritance note: "& CHAR(10),AQ5& CHAR(10)& CHAR(10))),"") | AZ5: =IFERROR(IF(AD5<>"",_xlfn.CONCAT("Examined the following policy during fieldwork:"& CHAR(10),AD5& CHAR(10)& CHAR(10),IF(AND(X5<>"5. Fully Compliant (100%)",AE5<>""),"Reviewed policy exception note:"& CHAR(10) & AE5 & CHAR(10) & CHAR(10),"")),""),"") | BA5: =IFERROR(IF(AH5<>"",_xlfn.CONCAT("Examined the following process during fieldwork:"& CHAR(10),AH5& CHAR(10)& CHAR(10),IF(AND(Y5<>"5. Fully Compliant (100%)",AI5<>""),"Reviewed process exception note:"& CHAR(10) & AI5 & CHAR(10) & CHAR(10),"")),""),"") | BB5: =IF(AK5<>"",(_xlfn.CONCAT("Inquired of the following workforce member: "& CHAR(10),AK5& CHAR(10)& CHAR(10),"Inquiry lead to the following conclusions: "& CHAR(10),AL5& CHAR(10) & CHAR(10))),"") -> Inquired of the following workforce member: Michael Wood - VP of AI Engineering Kyle Smith - IT Operations and AI Expert Inquiry lead to the following conclusions: AI policies and procedures are not formally maintained at this time. Documentation will be developed and integrated to existing Merge policies and procedures | BC5: =IF(AM5<>"",(_xlfn.CONCAT("Observed the following live during fieldwork: "& CHAR(10),AM5& CHAR(10) & CHAR(10))),"") | BD5: =_xlfn.CONCAT("Examined the following evidence during fieldwork:"& CHAR(10),AN5& CHAR(10)& CHAR(10),IF(AO5<>"","Reviewed evidence note:"& CHAR(10)&AO5& CHAR(10) & CHAR(10),"Reviewed evidence addressed the requirement statement."& CHAR(10) & CHAR(10)),IF(AND(AP5<>"5. Fully Compliant (100%)",AP5<>""),"Reviewed evidence exception note: "& CHAR(10) & AP5 & CHAR(10) & CHAR(10),"")) -> Examined the following evidence during fieldwork: Reviewed evidence addressed the requirement statement. Reviewed evidence exception note: Gap: AI policies and procedures considering the details of the requirement statement are not formally maintained at this time. Recommendation: Management should ensure that AI policies and procedures are developed considering the following: - defines the effect that an AI system can have on the organization’s culture by shifting and introducing new responsibilities, roles and tasks - defines any additional international, regional, national and local standards and guidelines that are imposed by the use of AI systems - defines the additional risks to organizational knowledge related to transparency and explainability of AI systems - defines that the use of AI systems can result in changes to the number of human resources needed to realize a certain capability, or in a variation of the type of resources needed - defines the specific knowledge in AI technologies and data science required to develop and use AI systems - defines the availability of AI tools, platforms and libraries which can enable the development of AI systems without there being a full understanding of the technology, its limitations and potential pitfalls - defines the potential for AI to raise issues and opportunities related to intellectual property for specific AI systems - defines how AI systems can be used to automate, optimize and enhance data handling - defines additional quality and completeness constraints on data and information can be imposed by AI systems - defines how the use of AI systems can increase the complexity of interdependencies and interconnections - defines the consideration that the use of AI systems can increase the need for specialized training | BE5: =IF(AT5<>"",(_xlfn.CONCAT("Examined the following measure/metric during fieldwork:"& CHAR(10),AT5& CHAR(10)& CHAR(10),"Reviewed measure/metric note:"& CHAR(10),AU5 & CHAR(10) & CHAR(10))),"") | BF5: =IF(AV5<>"",(_xlfn.CONCAT("Examined the following measure/metric management during fieldwork:"& CHAR(10),AV5& CHAR(10)& CHAR(10),"Reviewed measure/metric management note:"& CHAR(10),AW5 & CHAR(10) & CHAR(10))),"") | BG5: =_xlfn.CONCAT((IF((COUNTIF('Sample Tables'!B:B,"")>0)=TRUE,_xlfn.CONCAT("",""),IF((COUNTIF('Sample Tables'!B:B,"")>0)=FALSE,""))),) | BH5: =IF(V5="No","Not Applicable: "&W5,(_xlfn.CONCAT(AX5,AY5,AZ5,BA5,BB5,BC5,BD5,BE5,BF5,BG5))) -> A-LIGN finished its review of this control on during the scheduled fieldwork window (Fieldwork: xx/xx/xxxx - xx/xx/xxxx). Inquired of the following workforce member: Michael Wood - VP of AI Engineering Kyle Smith - IT Operations and AI Expert Inquiry lead to the following conclusions: AI policies and procedures are not formally maintained at this time. Documentation will be developed and integrated to existing Merge policies and procedures Examined the following evidence during fieldwork: Reviewed evidence addressed the requirement statement. Reviewed evidence exception note: Gap: AI policies and procedures considering the details of the requirement statement are not formally maintained at this time. Recommendation: Management should ensure that AI policies and procedures are developed considering the following: - defines the effect that an AI system can have on the organization’s culture by shifting and introducing new responsibilities, roles and tasks - defines any additional international, regional, national and local standards and guidelines that are imposed by the use of AI systems - defines the additional risks to organizational knowledge related to transparency and explainability of AI systems - defines that the use of AI systems can result in changes to the number of human resources needed to realize a certain capability, or in a variation of the type of resources needed - defines the specific knowledge in AI technologies and data science required to develop and use AI systems - defines the availability of AI tools, platforms and libraries which can enable the development of AI systems without there being a full understanding of the technology, its limitations and potential pitfalls - defines the potential for AI to raise issues and opportunities related to intellectual property for specific AI systems - defines how AI systems can be used to automate, optimize and enhance data handling - defines additional quality and completeness constraints on data and information can be imposed by AI systems - defines how the use of AI systems can increase the complexity of interdependencies and interconnections - defines the consideration that the use of AI systems can increase the need for specialized training
C6: =IF(V6="No","Not Applicable",(IF(X6="1. Non Compliant (0%)","0",IF(X6="2. Somewhat Compliant (25%)","25",IF(X6="3. Partially Compliant (50%)","50",IF(X6="4. Mostly Compliant (75%)","75",IF(X6="5. Fully Compliant (100%)","100")))))*0.15)+((IF(Y6="1. Non Compliant (0%)","0",IF(Y6="2. Somewhat Compliant (25%)","25",IF(Y6="3. Partially Compliant (50%)","50",IF(Y6="4. Mostly Compliant (75%)","75",IF(Y6="5. Fully Compliant (100%)","100"))))))*0.2)+(IF(Z6="1. Non Compliant (0%)","0",IF(Z6="2. Somewhat Compliant (25%)","25",IF(Z6="3. Partially Compliant (50%)","50",IF(Z6="4. Mostly Compliant (75%)","75",IF(Z6="5. Fully Compliant (100%)","100")))))*0.4)+(IF(AA6="1. Non Compliant (0%)","0",IF(AA6="2. Somewhat Compliant (25%)","25",IF(AA6="3. Partially Compliant (50%)","50",IF(AA6="4. Mostly Compliant (75%)","75",IF(AA6="5. Fully Compliant (100%)","100")))))*0.1)+(IF(AB6="1. Non Compliant (0%)","0",IF(AB6="2. Somewhat Compliant (25%)","25",IF(AB6="3. Partially Compliant (50%)","50",IF(AB6="4. Mostly Compliant (75%)","75",IF(AB6="5. Fully Compliant (100%)","100")))))*0.15)) -> 0 | D6: =IF(AND((_xlfn.XLOOKUP(J6,'Fields & Revisions'!$H:$H,'Fields & Revisions'!$I:$I))<70.99,(OR(Z6="4. Mostly Compliant (75%)",Z6="3. Partially Compliant (50%)",Z6="2. Somewhat Compliant (25%)",Z6="1. Non Compliant (0%)"))),"Yes","No") -> Yes | E6: =IF(ISERROR(VLOOKUP(H6,Scope!A:A,1,FALSE)),"No","Yes") -> Yes | F6: 01 Information Protection Program | G6: 2790.0 | H6: 01.03aISO23894Organizational.25 | I6: ISO/IEC 23894 | J6: 03.a Risk Management Program Development | K6: The organization |aligns the AI system project-level processes with the organization’s objectives.|| | L6: Examine evidence that all evaluative elements within the requirement statement have been implemented as defined in the HITRUST scoring rubric, using a sample based test where possible for each evaluative element._x000D_ _x000D_ _x000D_ Example test(s):_x000D_ For example, obtain and examine evidence to confirm the organization has aligned AI system project-level processes with the organization\'s objectives. | M6: Evidence Test: Artificial Intelligence - AI system project-level processes are aligned with the organization's objective | N6: No | O6: =_xlfn.XLOOKUP(G6,SRMs!$A:$A,SRMs!$D:$D) -> NO INHERITANCE | P6: =IFERROR(VLOOKUP(H6,Inherited!A:B,2,FALSE),"") | Q6: =IF(MATCH(H6,Inherited!A:A),IF((((_xlfn.XLOOKUP(Assessment!H7,Inherited!A:A,Inherited!B:B))/100)*(_xlfn.XLOOKUP(Assessment!H7,Inherited!A:A,Inherited!C:C)))+(((100-(_xlfn.XLOOKUP(Assessment!H7,Inherited!A:A,Inherited!B:B)))/100)*IF(X6="1. Non Compliant (0%)","0",IF(X6="2. Somewhat Compliant (25%)","25",IF(X6="3. Partially Compliant (50%)","50",IF(X6="4. Mostly Compliant (75%)","75",IF(X6="5. Fully Compliant (100%)","100"))))))<=10,"0", IF(AND((((_xlfn.XLOOKUP(Assessment!H7,Inherited!A:A,Inherited!B:B))/100)*(_xlfn.XLOOKUP(Assessment!H7,Inherited!A:A,Inherited!C:C)))+(((100-(_xlfn.XLOOKUP(Assessment!H7,Inherited!A:A,Inherited!B:B)))/100)*IF(X6="1. Non Compliant (0%)","0",IF(X6="2. Somewhat Compliant (25%)","25",IF(X6="3. Partially Compliant (50%)","50",IF(X6="4. Mostly Compliant (75%)","75",IF(X6="5. Fully Compliant (100%)","100"))))))>=11,(((_xlfn.XLOOKUP(Assessment!H7,Inherited!A:A,Inherited!B:B))/100)*(_xlfn.XLOOKUP(Assessment!H7,Inherited!A:A,Inherited!C:C)))+(((100-(_xlfn.XLOOKUP(Assessment!H7,Inherited!A:A,Inherited!B:B)))/100)*IF(X6="1. Non Compliant (0%)","0",IF(X6="2. Somewhat Compliant (25%)","25",IF(X6="3. Partially Compliant (50%)","50",IF(X6="4. Mostly Compliant (75%)","75",IF(X6="5. Fully Compliant (100%)","100"))))))<=32),"25",IF(AND((((_xlfn.XLOOKUP(Assessment!H7,Inherited!A:A,Inherited!B:B))/100)*(_xlfn.XLOOKUP(Assessment!H7,Inherited!A:A,Inherited!C:C)))+(((100-(_xlfn.XLOOKUP(Assessment!H7,Inherited!A:A,Inherited!B:B)))/100)*IF(X6="1. Non Compliant (0%)","0",IF(X6="2. Somewhat Compliant (25%)","25",IF(X6="3. Partially Compliant (50%)","50",IF(X6="4. Mostly Compliant (75%)","75",IF(X6="5. Fully Compliant (100%)","100"))))))>=33,(((_xlfn.XLOOKUP(Assessment!H7,Inherited!A:A,Inherited!B:B))/100)*(_xlfn.XLOOKUP(Assessment!H7,Inherited!A:A,Inherited!C:C)))+(((100-(_xlfn.XLOOKUP(Assessment!H7,Inherited!A:A,Inherited!B:B)))/100)*IF(X6="1. Non Compliant (0%)","0",IF(X6="2. Somewhat Compliant (25%)","25",IF(X6="3. Partially Compliant (50%)","50",IF(X6="4. Mostly Compliant (75%)","75",IF(X6="5. Fully Compliant (100%)","100"))))))<=65),"50",IF(AND((((_xlfn.XLOOKUP(Assessment!H7,Inherited!A:A,Inherited!B:B))/100)*(_xlfn.XLOOKUP(Assessment!H7,Inherited!A:A,Inherited!C:C)))+(((100-(_xlfn.XLOOKUP(Assessment!H7,Inherited!A:A,Inherited!B:B)))/100)*IF(X6="1. Non Compliant (0%)","0",IF(X6="2. Somewhat Compliant (25%)","25",IF(X6="3. Partially Compliant (50%)","50",IF(X6="4. Mostly Compliant (75%)","75",IF(X6="5. Fully Compliant (100%)","100"))))))>=66,(((_xlfn.XLOOKUP(Assessment!H7,Inherited!A:A,Inherited!B:B))/100)*(_xlfn.XLOOKUP(Assessment!H7,Inherited!A:A,Inherited!C:C)))+(((100-(_xlfn.XLOOKUP(Assessment!H7,Inherited!A:A,Inherited!B:B)))/100)*IF(X6="1. Non Compliant (0%)","0",IF(X6="2. Somewhat Compliant (25%)","25",IF(X6="3. Partially Compliant (50%)","50",IF(X6="4. Mostly Compliant (75%)","75",IF(X6="5. Fully Compliant (100%)","100"))))))<=89),"75",IF((((_xlfn.XLOOKUP(Assessment!H7,Inherited!A:A,Inherited!B:B))/100)*(_xlfn.XLOOKUP(Assessment!H7,Inherited!A:A,Inherited!C:C)))+(((100-(_xlfn.XLOOKUP(Assessment!H7,Inherited!A:A,Inherited!B:B)))/100)*IF(X6="1. Non Compliant (0%)","0",IF(X6="2. Somewhat Compliant (25%)","25",IF(X6="3. Partially Compliant (50%)","50",IF(X6="4. Mostly Compliant (75%)","75",IF(X6="5. Fully Compliant (100%)","100"))))))>=90,"100")))))) -> #N/A | R6: =IF(MATCH(H6,Inherited!A:A),IF((((_xlfn.XLOOKUP(Assessment!H7,Inherited!A:A,Inherited!B:B))/100)*(_xlfn.XLOOKUP(Assessment!H7,Inherited!A:A,Inherited!D:D)))+(((100-(_xlfn.XLOOKUP(Assessment!H7,Inherited!A:A,Inherited!B:B)))/100)*IF(Y6="1. Non Compliant (0%)","0",IF(Y6="2. Somewhat Compliant (25%)","25",IF(Y6="3. Partially Compliant (50%)","50",IF(Y6="4. Mostly Compliant (75%)","75",IF(Y6="5. Fully Compliant (100%)","100"))))))<=10,"0", IF(AND((((_xlfn.XLOOKUP(Assessment!H7,Inherited!A:A,Inherited!B:B))/100)*(_xlfn.XLOOKUP(Assessment!H7,Inherited!A:A,Inherited!D:D)))+(((100-(_xlfn.XLOOKUP(Assessment!H7,Inherited!A:A,Inherited!B:B)))/100)*IF(Y6="1. Non Compliant (0%)","0",IF(Y6="2. Somewhat Compliant (25%)","25",IF(Y6="3. Partially Compliant (50%)","50",IF(Y6="4. Mostly Compliant (75%)","75",IF(Y6="5. Fully Compliant (100%)","100"))))))>=11,(((_xlfn.XLOOKUP(Assessment!H7,Inherited!A:A,Inherited!B:B))/100)*(_xlfn.XLOOKUP(Assessment!H7,Inherited!A:A,Inherited!D:D)))+(((100-(_xlfn.XLOOKUP(Assessment!H7,Inherited!A:A,Inherited!B:B)))/100)*IF(Y6="1. Non Compliant (0%)","0",IF(Y6="2. Somewhat Compliant (25%)","25",IF(Y6="3. Partially Compliant (50%)","50",IF(Y6="4. Mostly Compliant (75%)","75",IF(Y6="5. Fully Compliant (100%)","100"))))))<=32),"25",IF(AND((((_xlfn.XLOOKUP(Assessment!H7,Inherited!A:A,Inherited!B:B))/100)*(_xlfn.XLOOKUP(Assessment!H7,Inherited!A:A,Inherited!D:D)))+(((100-(_xlfn.XLOOKUP(Assessment!H7,Inherited!A:A,Inherited!B:B)))/100)*IF(Y6="1. Non Compliant (0%)","0",IF(Y6="2. Somewhat Compliant (25%)","25",IF(Y6="3. Partially Compliant (50%)","50",IF(Y6="4. Mostly Compliant (75%)","75",IF(Y6="5. Fully Compliant (100%)","100"))))))>=33,(((_xlfn.XLOOKUP(Assessment!H7,Inherited!A:A,Inherited!B:B))/100)*(_xlfn.XLOOKUP(Assessment!H7,Inherited!A:A,Inherited!D:D)))+(((100-(_xlfn.XLOOKUP(Assessment!H7,Inherited!A:A,Inherited!B:B)))/100)*IF(Y6="1. Non Compliant (0%)","0",IF(Y6="2. Somewhat Compliant (25%)","25",IF(Y6="3. Partially Compliant (50%)","50",IF(Y6="4. Mostly Compliant (75%)","75",IF(Y6="5. Fully Compliant (100%)","100"))))))<=65),"50",IF(AND((((_xlfn.XLOOKUP(Assessment!H7,Inherited!A:A,Inherited!B:B))/100)*(_xlfn.XLOOKUP(Assessment!H7,Inherited!A:A,Inherited!D:D)))+(((100-(_xlfn.XLOOKUP(Assessment!H7,Inherited!A:A,Inherited!B:B)))/100)*IF(Y6="1. Non Compliant (0%)","0",IF(Y6="2. Somewhat Compliant (25%)","25",IF(Y6="3. Partially Compliant (50%)","50",IF(Y6="4. Mostly Compliant (75%)","75",IF(Y6="5. Fully Compliant (100%)","100"))))))>=66,(((_xlfn.XLOOKUP(Assessment!H7,Inherited!A:A,Inherited!B:B))/100)*(_xlfn.XLOOKUP(Assessment!H7,Inherited!A:A,Inherited!D:D)))+(((100-(_xlfn.XLOOKUP(Assessment!H7,Inherited!A:A,Inherited!B:B)))/100)*IF(Y6="1. Non Compliant (0%)","0",IF(Y6="2. Somewhat Compliant (25%)","25",IF(Y6="3. Partially Compliant (50%)","50",IF(Y6="4. Mostly Compliant (75%)","75",IF(Y6="5. Fully Compliant (100%)","100"))))))<=89),"75",IF((((_xlfn.XLOOKUP(Assessment!H7,Inherited!A:A,Inherited!B:B))/100)*(_xlfn.XLOOKUP(Assessment!H7,Inherited!A:A,Inherited!D:D)))+(((100-(_xlfn.XLOOKUP(Assessment!H7,Inherited!A:A,Inherited!B:B)))/100)*IF(Y6="1. Non Compliant (0%)","0",IF(Y6="2. Somewhat Compliant (25%)","25",IF(Y6="3. Partially Compliant (50%)","50",IF(Y6="4. Mostly Compliant (75%)","75",IF(Y6="5. Fully Compliant (100%)","100"))))))>=90,"100")))))) -> #N/A | S6: =IF(MATCH(H6,Inherited!A:A),IF((((_xlfn.XLOOKUP(Assessment!H7,Inherited!A:A,Inherited!B:B))/100)*(_xlfn.XLOOKUP(Assessment!H7,Inherited!A:A,Inherited!E:E)))+(((100-(_xlfn.XLOOKUP(Assessment!H7,Inherited!A:A,Inherited!B:B)))/100)*IF(Z6="1. Non Compliant (0%)","0",IF(Z6="2. Somewhat Compliant (25%)","25",IF(Z6="3. Partially Compliant (50%)","50",IF(Z6="4. Mostly Compliant (75%)","75",IF(Z6="5. Fully Compliant (100%)","100"))))))<=10,"0", IF(AND((((_xlfn.XLOOKUP(Assessment!H7,Inherited!A:A,Inherited!B:B))/100)*(_xlfn.XLOOKUP(Assessment!H7,Inherited!A:A,Inherited!E:E)))+(((100-(_xlfn.XLOOKUP(Assessment!H7,Inherited!A:A,Inherited!B:B)))/100)*IF(Z6="1. Non Compliant (0%)","0",IF(Z6="2. Somewhat Compliant (25%)","25",IF(Z6="3. Partially Compliant (50%)","50",IF(Z6="4. Mostly Compliant (75%)","75",IF(Z6="5. Fully Compliant (100%)","100"))))))>=11,(((_xlfn.XLOOKUP(Assessment!H7,Inherited!A:A,Inherited!B:B))/100)*(_xlfn.XLOOKUP(Assessment!H7,Inherited!A:A,Inherited!E:E)))+(((100-(_xlfn.XLOOKUP(Assessment!H7,Inherited!A:A,Inherited!B:B)))/100)*IF(Z6="1. Non Compliant (0%)","0",IF(Z6="2. Somewhat Compliant (25%)","25",IF(Z6="3. Partially Compliant (50%)","50",IF(Z6="4. Mostly Compliant (75%)","75",IF(Z6="5. Fully Compliant (100%)","100"))))))<=32),"25",IF(AND((((_xlfn.XLOOKUP(Assessment!H7,Inherited!A:A,Inherited!B:B))/100)*(_xlfn.XLOOKUP(Assessment!H7,Inherited!A:A,Inherited!E:E)))+(((100-(_xlfn.XLOOKUP(Assessment!H7,Inherited!A:A,Inherited!B:B)))/100)*IF(Z6="1. Non Compliant (0%)","0",IF(Z6="2. Somewhat Compliant (25%)","25",IF(Z6="3. Partially Compliant (50%)","50",IF(Z6="4. Mostly Compliant (75%)","75",IF(Z6="5. Fully Compliant (100%)","100"))))))>=33,(((_xlfn.XLOOKUP(Assessment!H7,Inherited!A:A,Inherited!B:B))/100)*(_xlfn.XLOOKUP(Assessment!H7,Inherited!A:A,Inherited!E:E)))+(((100-(_xlfn.XLOOKUP(Assessment!H7,Inherited!A:A,Inherited!B:B)))/100)*IF(Z6="1. Non Compliant (0%)","0",IF(Z6="2. Somewhat Compliant (25%)","25",IF(Z6="3. Partially Compliant (50%)","50",IF(Z6="4. Mostly Compliant (75%)","75",IF(Z6="5. Fully Compliant (100%)","100"))))))<=65),"50",IF(AND((((_xlfn.XLOOKUP(Assessment!H7,Inherited!A:A,Inherited!B:B))/100)*(_xlfn.XLOOKUP(Assessment!H7,Inherited!A:A,Inherited!E:E)))+(((100-(_xlfn.XLOOKUP(Assessment!H7,Inherited!A:A,Inherited!B:B)))/100)*IF(Z6="1. Non Compliant (0%)","0",IF(Z6="2. Somewhat Compliant (25%)","25",IF(Z6="3. Partially Compliant (50%)","50",IF(Z6="4. Mostly Compliant (75%)","75",IF(Z6="5. Fully Compliant (100%)","100"))))))>=66,(((_xlfn.XLOOKUP(Assessment!H7,Inherited!A:A,Inherited!B:B))/100)*(_xlfn.XLOOKUP(Assessment!H7,Inherited!A:A,Inherited!E:E)))+(((100-(_xlfn.XLOOKUP(Assessment!H7,Inherited!A:A,Inherited!B:B)))/100)*IF(Z6="1. Non Compliant (0%)","0",IF(Z6="2. Somewhat Compliant (25%)","25",IF(Z6="3. Partially Compliant (50%)","50",IF(Z6="4. Mostly Compliant (75%)","75",IF(Z6="5. Fully Compliant (100%)","100"))))))<=89),"75",IF((((_xlfn.XLOOKUP(Assessment!H7,Inherited!A:A,Inherited!B:B))/100)*(_xlfn.XLOOKUP(Assessment!H7,Inherited!A:A,Inherited!E:E)))+(((100-(_xlfn.XLOOKUP(Assessment!H7,Inherited!A:A,Inherited!B:B)))/100)*IF(Z6="1. Non Compliant (0%)","0",IF(Z6="2. Somewhat Compliant (25%)","25",IF(Z6="3. Partially Compliant (50%)","50",IF(Z6="4. Mostly Compliant (75%)","75",IF(Z6="5. Fully Compliant (100%)","100"))))))>=90,"100")))))) -> #N/A | T6: =IF(MATCH(H6,Inherited!A:A),IF((((_xlfn.XLOOKUP(Assessment!H7,Inherited!A:A,Inherited!B:B))/100)*(_xlfn.XLOOKUP(Assessment!H7,Inherited!A:A,Inherited!F:F)))+(((100-(_xlfn.XLOOKUP(Assessment!H7,Inherited!A:A,Inherited!B:B)))/100)*IF(AA6="1. Non Compliant (0%)","0",IF(AA6="2. Somewhat Compliant (25%)","25",IF(AA6="3. Partially Compliant (50%)","50",IF(AA6="4. Mostly Compliant (75%)","75",IF(AA6="5. Fully Compliant (100%)","100"))))))<=10,"0", IF(AND((((_xlfn.XLOOKUP(Assessment!H7,Inherited!A:A,Inherited!B:B))/100)*(_xlfn.XLOOKUP(Assessment!H7,Inherited!A:A,Inherited!F:F)))+(((100-(_xlfn.XLOOKUP(Assessment!H7,Inherited!A:A,Inherited!B:B)))/100)*IF(AA6="1. Non Compliant (0%)","0",IF(AA6="2. Somewhat Compliant (25%)","25",IF(AA6="3. Partially Compliant (50%)","50",IF(AA6="4. Mostly Compliant (75%)","75",IF(AA6="5. Fully Compliant (100%)","100"))))))>=11,(((_xlfn.XLOOKUP(Assessment!H7,Inherited!A:A,Inherited!B:B))/100)*(_xlfn.XLOOKUP(Assessment!H7,Inherited!A:A,Inherited!F:F)))+(((100-(_xlfn.XLOOKUP(Assessment!H7,Inherited!A:A,Inherited!B:B)))/100)*IF(AA6="1. Non Compliant (0%)","0",IF(AA6="2. Somewhat Compliant (25%)","25",IF(AA6="3. Partially Compliant (50%)","50",IF(AA6="4. Mostly Compliant (75%)","75",IF(AA6="5. Fully Compliant (100%)","100"))))))<=32),"25",IF(AND((((_xlfn.XLOOKUP(Assessment!H7,Inherited!A:A,Inherited!B:B))/100)*(_xlfn.XLOOKUP(Assessment!H7,Inherited!A:A,Inherited!F:F)))+(((100-(_xlfn.XLOOKUP(Assessment!H7,Inherited!A:A,Inherited!B:B)))/100)*IF(AA6="1. Non Compliant (0%)","0",IF(AA6="2. Somewhat Compliant (25%)","25",IF(AA6="3. Partially Compliant (50%)","50",IF(AA6="4. Mostly Compliant (75%)","75",IF(AA6="5. Fully Compliant (100%)","100"))))))>=33,(((_xlfn.XLOOKUP(Assessment!H7,Inherited!A:A,Inherited!B:B))/100)*(_xlfn.XLOOKUP(Assessment!H7,Inherited!A:A,Inherited!F:F)))+(((100-(_xlfn.XLOOKUP(Assessment!H7,Inherited!A:A,Inherited!B:B)))/100)*IF(AA6="1. Non Compliant (0%)","0",IF(AA6="2. Somewhat Compliant (25%)","25",IF(AA6="3. Partially Compliant (50%)","50",IF(AA6="4. Mostly Compliant (75%)","75",IF(AA6="5. Fully Compliant (100%)","100"))))))<=65),"50",IF(AND((((_xlfn.XLOOKUP(Assessment!H7,Inherited!A:A,Inherited!B:B))/100)*(_xlfn.XLOOKUP(Assessment!H7,Inherited!A:A,Inherited!F:F)))+(((100-(_xlfn.XLOOKUP(Assessment!H7,Inherited!A:A,Inherited!B:B)))/100)*IF(AA6="1. Non Compliant (0%)","0",IF(AA6="2. Somewhat Compliant (25%)","25",IF(AA6="3. Partially Compliant (50%)","50",IF(AA6="4. Mostly Compliant (75%)","75",IF(AA6="5. Fully Compliant (100%)","100"))))))>=66,(((_xlfn.XLOOKUP(Assessment!H7,Inherited!A:A,Inherited!B:B))/100)*(_xlfn.XLOOKUP(Assessment!H7,Inherited!A:A,Inherited!F:F)))+(((100-(_xlfn.XLOOKUP(Assessment!H7,Inherited!A:A,Inherited!B:B)))/100)*IF(AA6="1. Non Compliant (0%)","0",IF(AA6="2. Somewhat Compliant (25%)","25",IF(AA6="3. Partially Compliant (50%)","50",IF(AA6="4. Mostly Compliant (75%)","75",IF(AA6="5. Fully Compliant (100%)","100"))))))<=89),"75",IF((((_xlfn.XLOOKUP(Assessment!H7,Inherited!A:A,Inherited!B:B))/100)*(_xlfn.XLOOKUP(Assessment!H7,Inherited!A:A,Inherited!F:F)))+(((100-(_xlfn.XLOOKUP(Assessment!H7,Inherited!A:A,Inherited!B:B)))/100)*IF(AA6="1. Non Compliant (0%)","0",IF(AA6="2. Somewhat Compliant (25%)","25",IF(AA6="3. Partially Compliant (50%)","50",IF(AA6="4. Mostly Compliant (75%)","75",IF(AA6="5. Fully Compliant (100%)","100"))))))>=90,"100")))))) -> #N/A | U6: =IF(MATCH(H6,Inherited!A:A),IF((((_xlfn.XLOOKUP(Assessment!H7,Inherited!A:A,Inherited!B:B))/100)*(_xlfn.XLOOKUP(Assessment!H7,Inherited!A:A,Inherited!G:G)))+(((100-(_xlfn.XLOOKUP(Assessment!H7,Inherited!A:A,Inherited!B:B)))/100)*IF(AB6="1. Non Compliant (0%)","0",IF(AB6="2. Somewhat Compliant (25%)","25",IF(AB6="3. Partially Compliant (50%)","50",IF(AB6="4. Mostly Compliant (75%)","75",IF(AB6="5. Fully Compliant (100%)","100"))))))<=10,"0", IF(AND((((_xlfn.XLOOKUP(Assessment!H7,Inherited!A:A,Inherited!B:B))/100)*(_xlfn.XLOOKUP(Assessment!H7,Inherited!A:A,Inherited!G:G)))+(((100-(_xlfn.XLOOKUP(Assessment!H7,Inherited!A:A,Inherited!B:B)))/100)*IF(AB6="1. Non Compliant (0%)","0",IF(AB6="2. Somewhat Compliant (25%)","25",IF(AB6="3. Partially Compliant (50%)","50",IF(AB6="4. Mostly Compliant (75%)","75",IF(AB6="5. Fully Compliant (100%)","100"))))))>=11,(((_xlfn.XLOOKUP(Assessment!H7,Inherited!A:A,Inherited!B:B))/100)*(_xlfn.XLOOKUP(Assessment!H7,Inherited!A:A,Inherited!G:G)))+(((100-(_xlfn.XLOOKUP(Assessment!H7,Inherited!A:A,Inherited!B:B)))/100)*IF(AB6="1. Non Compliant (0%)","0",IF(AB6="2. Somewhat Compliant (25%)","25",IF(AB6="3. Partially Compliant (50%)","50",IF(AB6="4. Mostly Compliant (75%)","75",IF(AB6="5. Fully Compliant (100%)","100"))))))<=32),"25",IF(AND((((_xlfn.XLOOKUP(Assessment!H7,Inherited!A:A,Inherited!B:B))/100)*(_xlfn.XLOOKUP(Assessment!H7,Inherited!A:A,Inherited!G:G)))+(((100-(_xlfn.XLOOKUP(Assessment!H7,Inherited!A:A,Inherited!B:B)))/100)*IF(AB6="1. Non Compliant (0%)","0",IF(AB6="2. Somewhat Compliant (25%)","25",IF(AB6="3. Partially Compliant (50%)","50",IF(AB6="4. Mostly Compliant (75%)","75",IF(AB6="5. Fully Compliant (100%)","100"))))))>=33,(((_xlfn.XLOOKUP(Assessment!H7,Inherited!A:A,Inherited!B:B))/100)*(_xlfn.XLOOKUP(Assessment!H7,Inherited!A:A,Inherited!G:G)))+(((100-(_xlfn.XLOOKUP(Assessment!H7,Inherited!A:A,Inherited!B:B)))/100)*IF(AB6="1. Non Compliant (0%)","0",IF(AB6="2. Somewhat Compliant (25%)","25",IF(AB6="3. Partially Compliant (50%)","50",IF(AB6="4. Mostly Compliant (75%)","75",IF(AB6="5. Fully Compliant (100%)","100"))))))<=65),"50",IF(AND((((_xlfn.XLOOKUP(Assessment!H7,Inherited!A:A,Inherited!B:B))/100)*(_xlfn.XLOOKUP(Assessment!H7,Inherited!A:A,Inherited!G:G)))+(((100-(_xlfn.XLOOKUP(Assessment!H7,Inherited!A:A,Inherited!B:B)))/100)*IF(AB6="1. Non Compliant (0%)","0",IF(AB6="2. Somewhat Compliant (25%)","25",IF(AB6="3. Partially Compliant (50%)","50",IF(AB6="4. Mostly Compliant (75%)","75",IF(AB6="5. Fully Compliant (100%)","100"))))))>=66,(((_xlfn.XLOOKUP(Assessment!H7,Inherited!A:A,Inherited!B:B))/100)*(_xlfn.XLOOKUP(Assessment!H7,Inherited!A:A,Inherited!G:G)))+(((100-(_xlfn.XLOOKUP(Assessment!H7,Inherited!A:A,Inherited!B:B)))/100)*IF(AB6="1. Non Compliant (0%)","0",IF(AB6="2. Somewhat Compliant (25%)","25",IF(AB6="3. Partially Compliant (50%)","50",IF(AB6="4. Mostly Compliant (75%)","75",IF(AB6="5. Fully Compliant (100%)","100"))))))<=89),"75",IF((((_xlfn.XLOOKUP(Assessment!H7,Inherited!A:A,Inherited!B:B))/100)*(_xlfn.XLOOKUP(Assessment!H7,Inherited!A:A,Inherited!G:G)))+(((100-(_xlfn.XLOOKUP(Assessment!H7,Inherited!A:A,Inherited!B:B)))/100)*IF(AB6="1. Non Compliant (0%)","0",IF(AB6="2. Somewhat Compliant (25%)","25",IF(AB6="3. Partially Compliant (50%)","50",IF(AB6="4. Mostly Compliant (75%)","75",IF(AB6="5. Fully Compliant (100%)","100"))))))>=90,"100")))))) -> #N/A | V6: Yes | Z6: 1. Non Compliant (0%) | AK6: Michael Wood - VP of AI Engineering Kyle Smith - IT Operations and AI Expert | AL6: AI policies and procedures are not formally maintained at this time. Documentation will be developed and integrated to existing Merge policies and procedures | AP6: Gap: AI policies and procedures considering the details of the requirement statement are not formally maintained at this time. Recommendation: Management should ensure that AI policies and procedures are developed considering the following: - AI system project-level processes are aligned with the organization's objective | AX6: =_xlfn.CONCAT("A-LIGN finished its review of this control on ",AR6, " during the scheduled fieldwork window (",Intro!$B$4,")."& CHAR(10)& CHAR(10)) -> A-LIGN finished its review of this control on during the scheduled fieldwork window (Fieldwork: xx/xx/xxxx - xx/xx/xxxx). | AY6: =IF(AQ6<>"",(_xlfn.CONCAT("Inheritance note: "& CHAR(10),AQ6& CHAR(10)& CHAR(10))),"") | AZ6: =IFERROR(IF(AD6<>"",_xlfn.CONCAT("Examined the following policy during fieldwork:"& CHAR(10),AD6& CHAR(10)& CHAR(10),IF(AND(X6<>"5. Fully Compliant (100%)",AE6<>""),"Reviewed policy exception note:"& CHAR(10) & AE6 & CHAR(10) & CHAR(10),"")),""),"") | BA6: =IFERROR(IF(AH6<>"",_xlfn.CONCAT("Examined the following process during fieldwork:"& CHAR(10),AH6& CHAR(10)& CHAR(10),IF(AND(Y6<>"5. Fully Compliant (100%)",AI6<>""),"Reviewed process exception note:"& CHAR(10) & AI6 & CHAR(10) & CHAR(10),"")),""),"") | BB6: =IF(AK6<>"",(_xlfn.CONCAT("Inquired of the following workforce member: "& CHAR(10),AK6& CHAR(10)& CHAR(10),"Inquiry lead to the following conclusions: "& CHAR(10),AL6& CHAR(10) & CHAR(10))),"") -> Inquired of the following workforce member: Michael Wood - VP of AI Engineering Kyle Smith - IT Operations and AI Expert Inquiry lead to the following conclusions: AI policies and procedures are not formally maintained at this time. Documentation will be developed and integrated to existing Merge policies and procedures | BC6: =IF(AM6<>"",(_xlfn.CONCAT("Observed the following live during fieldwork: "& CHAR(10),AM6& CHAR(10) & CHAR(10))),"") | BD6: =_xlfn.CONCAT("Examined the following evidence during fieldwork:"& CHAR(10),AN6& CHAR(10)& CHAR(10),IF(AO6<>"","Reviewed evidence note:"& CHAR(10)&AO6& CHAR(10) & CHAR(10),"Reviewed evidence addressed the requirement statement."& CHAR(10) & CHAR(10)),IF(AND(AP6<>"5. Fully Compliant (100%)",AP6<>""),"Reviewed evidence exception note: "& CHAR(10) & AP6 & CHAR(10) & CHAR(10),"")) -> Examined the following evidence during fieldwork: Reviewed evidence addressed the requirement statement. Reviewed evidence exception note: Gap: AI policies and procedures considering the details of the requirement statement are not formally maintained at this time. Recommendation: Management should ensure that AI policies and procedures are developed considering the following: - AI system project-level processes are aligned with the organization's objective | BE6: =IF(AT6<>"",(_xlfn.CONCAT("Examined the following measure/metric during fieldwork:"& CHAR(10),AT6& CHAR(10)& CHAR(10),"Reviewed measure/metric note:"& CHAR(10),AU6 & CHAR(10) & CHAR(10))),"") | BF6: =IF(AV6<>"",(_xlfn.CONCAT("Examined the following measure/metric management during fieldwork:"& CHAR(10),AV6& CHAR(10)& CHAR(10),"Reviewed measure/metric management note:"& CHAR(10),AW6 & CHAR(10) & CHAR(10))),"") | BG6: =_xlfn.CONCAT((IF((COUNTIF('Sample Tables'!B:B,"")>0)=TRUE,_xlfn.CONCAT("",""),IF((COUNTIF('Sample Tables'!B:B,"")>0)=FALSE,""))),) | BH6: =IF(V6="No","Not Applicable: "&W6,(_xlfn.CONCAT(AX6,AY6,AZ6,BA6,BB6,BC6,BD6,BE6,BF6,BG6))) -> A-LIGN finished its review of this control on during the scheduled fieldwork window (Fieldwork: xx/xx/xxxx - xx/xx/xxxx). Inquired of the following workforce member: Michael Wood - VP of AI Engineering Kyle Smith - IT Operations and AI Expert Inquiry lead to the following conclusions: AI policies and procedures are not formally maintained at this time. Documentation will be developed and integrated to existing Merge policies and procedures Examined the following evidence during fieldwork: Reviewed evidence addressed the requirement statement. Reviewed evidence exception note: Gap: AI policies and procedures considering the details of the requirement statement are not formally maintained at this time. Recommendation: Management should ensure that AI policies and procedures are developed considering the following: - AI system project-level processes are aligned with the organization's objective
C7: =IF(V7="No","Not Applicable",(IF(X7="1. Non Compliant (0%)","0",IF(X7="2. Somewhat Compliant (25%)","25",IF(X7="3. Partially Compliant (50%)","50",IF(X7="4. Mostly Compliant (75%)","75",IF(X7="5. Fully Compliant (100%)","100")))))*0.15)+((IF(Y7="1. Non Compliant (0%)","0",IF(Y7="2. Somewhat Compliant (25%)","25",IF(Y7="3. Partially Compliant (50%)","50",IF(Y7="4. Mostly Compliant (75%)","75",IF(Y7="5. Fully Compliant (100%)","100"))))))*0.2)+(IF(Z7="1. Non Compliant (0%)","0",IF(Z7="2. Somewhat Compliant (25%)","25",IF(Z7="3. Partially Compliant (50%)","50",IF(Z7="4. Mostly Compliant (75%)","75",IF(Z7="5. Fully Compliant (100%)","100")))))*0.4)+(IF(AA7="1. Non Compliant (0%)","0",IF(AA7="2. Somewhat Compliant (25%)","25",IF(AA7="3. Partially Compliant (50%)","50",IF(AA7="4. Mostly Compliant (75%)","75",IF(AA7="5. Fully Compliant (100%)","100")))))*0.1)+(IF(AB7="1. Non Compliant (0%)","0",IF(AB7="2. Somewhat Compliant (25%)","25",IF(AB7="3. Partially Compliant (50%)","50",IF(AB7="4. Mostly Compliant (75%)","75",IF(AB7="5. Fully Compliant (100%)","100")))))*0.15)) -> 0 | D7: =IF(AND((_xlfn.XLOOKUP(J7,'Fields & Revisions'!$H:$H,'Fields & Revisions'!$I:$I))<70.99,(OR(Z7="4. Mostly Compliant (75%)",Z7="3. Partially Compliant (50%)",Z7="2. Somewhat Compliant (25%)",Z7="1. Non Compliant (0%)"))),"Yes","No") -> Yes | E7: =IF(ISERROR(VLOOKUP(H7,Scope!A:A,1,FALSE)),"No","Yes") -> Yes | F7: 01 Information Protection Program | G7: 2826.0 | H7: 01.03aISO31000Organizational.1 | I7: ISO 31000 | J7: 03.a Risk Management Program Development | K7: The organization, as part of the risk management process, considers the following when specifying risk criteria: |the nature and type of uncertainties that can affect outcomes and objectives (both tangible and intangible), |how consequences (both positive and negative) and likelihood will be defined and measured, |time-related factors, |consistency in the use of measurements, |how the level of risk is to be determined, |how combinations and sequences of multiple risks will be taken into account, and |the organization’s capacity. | L7: Examine evidence that all evaluative elements within the requirement statement have been implemented as defined in the HITRUST scoring rubric, using a sample based test where possible for each evaluative element._x000D_ _x000D_ _x000D_ Example test(s):_x000D_ For example, obtain and examine the risk management process documentation and _x000D_ confirm the organization documented consideration of the elements prescribed in the requirement statement. | M7: Documentation: Risk Management Program - assesses the following risk criteria: nature and type of uncertainties that can affect outcomes and objectives (both tangible and intangible) - assesses the following risk criteria: how consequences (both positive and negative) and likelihood will be defined and measured - assesses the following risk criteria: time-related factors - assesses the following risk criteria: consistency in the use of measurements - assesses the following risk criteria: how the level of risk is to be determined - assesses the following risk criteria: how combinations and sequences of multiple risks will be taken into account - assesses the following risk criteria: the organization’s capacity | N7: No | O7: =_xlfn.XLOOKUP(G7,SRMs!$A:$A,SRMs!$D:$D) -> NO INHERITANCE | P7: =IFERROR(VLOOKUP(H7,Inherited!A:B,2,FALSE),"") | Q7: =IF(MATCH(H7,Inherited!A:A),IF((((_xlfn.XLOOKUP(Assessment!H8,Inherited!A:A,Inherited!B:B))/100)*(_xlfn.XLOOKUP(Assessment!H8,Inherited!A:A,Inherited!C:C)))+(((100-(_xlfn.XLOOKUP(Assessment!H8,Inherited!A:A,Inherited!B:B)))/100)*IF(X7="1. Non Compliant (0%)","0",IF(X7="2. Somewhat Compliant (25%)","25",IF(X7="3. Partially Compliant (50%)","50",IF(X7="4. Mostly Compliant (75%)","75",IF(X7="5. Fully Compliant (100%)","100"))))))<=10,"0", IF(AND((((_xlfn.XLOOKUP(Assessment!H8,Inherited!A:A,Inherited!B:B))/100)*(_xlfn.XLOOKUP(Assessment!H8,Inherited!A:A,Inherited!C:C)))+(((100-(_xlfn.XLOOKUP(Assessment!H8,Inherited!A:A,Inherited!B:B)))/100)*IF(X7="1. Non Compliant (0%)","0",IF(X7="2. Somewhat Compliant (25%)","25",IF(X7="3. Partially Compliant (50%)","50",IF(X7="4. Mostly Compliant (75%)","75",IF(X7="5. Fully Compliant (100%)","100"))))))>=11,(((_xlfn.XLOOKUP(Assessment!H8,Inherited!A:A,Inherited!B:B))/100)*(_xlfn.XLOOKUP(Assessment!H8,Inherited!A:A,Inherited!C:C)))+(((100-(_xlfn.XLOOKUP(Assessment!H8,Inherited!A:A,Inherited!B:B)))/100)*IF(X7="1. Non Compliant (0%)","0",IF(X7="2. Somewhat Compliant (25%)","25",IF(X7="3. Partially Compliant (50%)","50",IF(X7="4. Mostly Compliant (75%)","75",IF(X7="5. Fully Compliant (100%)","100"))))))<=32),"25",IF(AND((((_xlfn.XLOOKUP(Assessment!H8,Inherited!A:A,Inherited!B:B))/100)*(_xlfn.XLOOKUP(Assessment!H8,Inherited!A:A,Inherited!C:C)))+(((100-(_xlfn.XLOOKUP(Assessment!H8,Inherited!A:A,Inherited!B:B)))/100)*IF(X7="1. Non Compliant (0%)","0",IF(X7="2. Somewhat Compliant (25%)","25",IF(X7="3. Partially Compliant (50%)","50",IF(X7="4. Mostly Compliant (75%)","75",IF(X7="5. Fully Compliant (100%)","100"))))))>=33,(((_xlfn.XLOOKUP(Assessment!H8,Inherited!A:A,Inherited!B:B))/100)*(_xlfn.XLOOKUP(Assessment!H8,Inherited!A:A,Inherited!C:C)))+(((100-(_xlfn.XLOOKUP(Assessment!H8,Inherited!A:A,Inherited!B:B)))/100)*IF(X7="1. Non Compliant (0%)","0",IF(X7="2. Somewhat Compliant (25%)","25",IF(X7="3. Partially Compliant (50%)","50",IF(X7="4. Mostly Compliant (75%)","75",IF(X7="5. Fully Compliant (100%)","100"))))))<=65),"50",IF(AND((((_xlfn.XLOOKUP(Assessment!H8,Inherited!A:A,Inherited!B:B))/100)*(_xlfn.XLOOKUP(Assessment!H8,Inherited!A:A,Inherited!C:C)))+(((100-(_xlfn.XLOOKUP(Assessment!H8,Inherited!A:A,Inherited!B:B)))/100)*IF(X7="1. Non Compliant (0%)","0",IF(X7="2. Somewhat Compliant (25%)","25",IF(X7="3. Partially Compliant (50%)","50",IF(X7="4. Mostly Compliant (75%)","75",IF(X7="5. Fully Compliant (100%)","100"))))))>=66,(((_xlfn.XLOOKUP(Assessment!H8,Inherited!A:A,Inherited!B:B))/100)*(_xlfn.XLOOKUP(Assessment!H8,Inherited!A:A,Inherited!C:C)))+(((100-(_xlfn.XLOOKUP(Assessment!H8,Inherited!A:A,Inherited!B:B)))/100)*IF(X7="1. Non Compliant (0%)","0",IF(X7="2. Somewhat Compliant (25%)","25",IF(X7="3. Partially Compliant (50%)","50",IF(X7="4. Mostly Compliant (75%)","75",IF(X7="5. Fully Compliant (100%)","100"))))))<=89),"75",IF((((_xlfn.XLOOKUP(Assessment!H8,Inherited!A:A,Inherited!B:B))/100)*(_xlfn.XLOOKUP(Assessment!H8,Inherited!A:A,Inherited!C:C)))+(((100-(_xlfn.XLOOKUP(Assessment!H8,Inherited!A:A,Inherited!B:B)))/100)*IF(X7="1. Non Compliant (0%)","0",IF(X7="2. Somewhat Compliant (25%)","25",IF(X7="3. Partially Compliant (50%)","50",IF(X7="4. Mostly Compliant (75%)","75",IF(X7="5. Fully Compliant (100%)","100"))))))>=90,"100")))))) -> #N/A | R7: =IF(MATCH(H7,Inherited!A:A),IF((((_xlfn.XLOOKUP(Assessment!H8,Inherited!A:A,Inherited!B:B))/100)*(_xlfn.XLOOKUP(Assessment!H8,Inherited!A:A,Inherited!D:D)))+(((100-(_xlfn.XLOOKUP(Assessment!H8,Inherited!A:A,Inherited!B:B)))/100)*IF(Y7="1. Non Compliant (0%)","0",IF(Y7="2. Somewhat Compliant (25%)","25",IF(Y7="3. Partially Compliant (50%)","50",IF(Y7="4. Mostly Compliant (75%)","75",IF(Y7="5. Fully Compliant (100%)","100"))))))<=10,"0", IF(AND((((_xlfn.XLOOKUP(Assessment!H8,Inherited!A:A,Inherited!B:B))/100)*(_xlfn.XLOOKUP(Assessment!H8,Inherited!A:A,Inherited!D:D)))+(((100-(_xlfn.XLOOKUP(Assessment!H8,Inherited!A:A,Inherited!B:B)))/100)*IF(Y7="1. Non Compliant (0%)","0",IF(Y7="2. Somewhat Compliant (25%)","25",IF(Y7="3. Partially Compliant (50%)","50",IF(Y7="4. Mostly Compliant (75%)","75",IF(Y7="5. Fully Compliant (100%)","100"))))))>=11,(((_xlfn.XLOOKUP(Assessment!H8,Inherited!A:A,Inherited!B:B))/100)*(_xlfn.XLOOKUP(Assessment!H8,Inherited!A:A,Inherited!D:D)))+(((100-(_xlfn.XLOOKUP(Assessment!H8,Inherited!A:A,Inherited!B:B)))/100)*IF(Y7="1. Non Compliant (0%)","0",IF(Y7="2. Somewhat Compliant (25%)","25",IF(Y7="3. Partially Compliant (50%)","50",IF(Y7="4. Mostly Compliant (75%)","75",IF(Y7="5. Fully Compliant (100%)","100"))))))<=32),"25",IF(AND((((_xlfn.XLOOKUP(Assessment!H8,Inherited!A:A,Inherited!B:B))/100)*(_xlfn.XLOOKUP(Assessment!H8,Inherited!A:A,Inherited!D:D)))+(((100-(_xlfn.XLOOKUP(Assessment!H8,Inherited!A:A,Inherited!B:B)))/100)*IF(Y7="1. Non Compliant (0%)","0",IF(Y7="2. Somewhat Compliant (25%)","25",IF(Y7="3. Partially Compliant (50%)","50",IF(Y7="4. Mostly Compliant (75%)","75",IF(Y7="5. Fully Compliant (100%)","100"))))))>=33,(((_xlfn.XLOOKUP(Assessment!H8,Inherited!A:A,Inherited!B:B))/100)*(_xlfn.XLOOKUP(Assessment!H8,Inherited!A:A,Inherited!D:D)))+(((100-(_xlfn.XLOOKUP(Assessment!H8,Inherited!A:A,Inherited!B:B)))/100)*IF(Y7="1. Non Compliant (0%)","0",IF(Y7="2. Somewhat Compliant (25%)","25",IF(Y7="3. Partially Compliant (50%)","50",IF(Y7="4. Mostly Compliant (75%)","75",IF(Y7="5. Fully Compliant (100%)","100"))))))<=65),"50",IF(AND((((_xlfn.XLOOKUP(Assessment!H8,Inherited!A:A,Inherited!B:B))/100)*(_xlfn.XLOOKUP(Assessment!H8,Inherited!A:A,Inherited!D:D)))+(((100-(_xlfn.XLOOKUP(Assessment!H8,Inherited!A:A,Inherited!B:B)))/100)*IF(Y7="1. Non Compliant (0%)","0",IF(Y7="2. Somewhat Compliant (25%)","25",IF(Y7="3. Partially Compliant (50%)","50",IF(Y7="4. Mostly Compliant (75%)","75",IF(Y7="5. Fully Compliant (100%)","100"))))))>=66,(((_xlfn.XLOOKUP(Assessment!H8,Inherited!A:A,Inherited!B:B))/100)*(_xlfn.XLOOKUP(Assessment!H8,Inherited!A:A,Inherited!D:D)))+(((100-(_xlfn.XLOOKUP(Assessment!H8,Inherited!A:A,Inherited!B:B)))/100)*IF(Y7="1. Non Compliant (0%)","0",IF(Y7="2. Somewhat Compliant (25%)","25",IF(Y7="3. Partially Compliant (50%)","50",IF(Y7="4. Mostly Compliant (75%)","75",IF(Y7="5. Fully Compliant (100%)","100"))))))<=89),"75",IF((((_xlfn.XLOOKUP(Assessment!H8,Inherited!A:A,Inherited!B:B))/100)*(_xlfn.XLOOKUP(Assessment!H8,Inherited!A:A,Inherited!D:D)))+(((100-(_xlfn.XLOOKUP(Assessment!H8,Inherited!A:A,Inherited!B:B)))/100)*IF(Y7="1. Non Compliant (0%)","0",IF(Y7="2. Somewhat Compliant (25%)","25",IF(Y7="3. Partially Compliant (50%)","50",IF(Y7="4. Mostly Compliant (75%)","75",IF(Y7="5. Fully Compliant (100%)","100"))))))>=90,"100")))))) -> #N/A | S7: =IF(MATCH(H7,Inherited!A:A),IF((((_xlfn.XLOOKUP(Assessment!H8,Inherited!A:A,Inherited!B:B))/100)*(_xlfn.XLOOKUP(Assessment!H8,Inherited!A:A,Inherited!E:E)))+(((100-(_xlfn.XLOOKUP(Assessment!H8,Inherited!A:A,Inherited!B:B)))/100)*IF(Z7="1. Non Compliant (0%)","0",IF(Z7="2. Somewhat Compliant (25%)","25",IF(Z7="3. Partially Compliant (50%)","50",IF(Z7="4. Mostly Compliant (75%)","75",IF(Z7="5. Fully Compliant (100%)","100"))))))<=10,"0", IF(AND((((_xlfn.XLOOKUP(Assessment!H8,Inherited!A:A,Inherited!B:B))/100)*(_xlfn.XLOOKUP(Assessment!H8,Inherited!A:A,Inherited!E:E)))+(((100-(_xlfn.XLOOKUP(Assessment!H8,Inherited!A:A,Inherited!B:B)))/100)*IF(Z7="1. Non Compliant (0%)","0",IF(Z7="2. Somewhat Compliant (25%)","25",IF(Z7="3. Partially Compliant (50%)","50",IF(Z7="4. Mostly Compliant (75%)","75",IF(Z7="5. Fully Compliant (100%)","100"))))))>=11,(((_xlfn.XLOOKUP(Assessment!H8,Inherited!A:A,Inherited!B:B))/100)*(_xlfn.XLOOKUP(Assessment!H8,Inherited!A:A,Inherited!E:E)))+(((100-(_xlfn.XLOOKUP(Assessment!H8,Inherited!A:A,Inherited!B:B)))/100)*IF(Z7="1. Non Compliant (0%)","0",IF(Z7="2. Somewhat Compliant (25%)","25",IF(Z7="3. Partially Compliant (50%)","50",IF(Z7="4. Mostly Compliant (75%)","75",IF(Z7="5. Fully Compliant (100%)","100"))))))<=32),"25",IF(AND((((_xlfn.XLOOKUP(Assessment!H8,Inherited!A:A,Inherited!B:B))/100)*(_xlfn.XLOOKUP(Assessment!H8,Inherited!A:A,Inherited!E:E)))+(((100-(_xlfn.XLOOKUP(Assessment!H8,Inherited!A:A,Inherited!B:B)))/100)*IF(Z7="1. Non Compliant (0%)","0",IF(Z7="2. Somewhat Compliant (25%)","25",IF(Z7="3. Partially Compliant (50%)","50",IF(Z7="4. Mostly Compliant (75%)","75",IF(Z7="5. Fully Compliant (100%)","100"))))))>=33,(((_xlfn.XLOOKUP(Assessment!H8,Inherited!A:A,Inherited!B:B))/100)*(_xlfn.XLOOKUP(Assessment!H8,Inherited!A:A,Inherited!E:E)))+(((100-(_xlfn.XLOOKUP(Assessment!H8,Inherited!A:A,Inherited!B:B)))/100)*IF(Z7="1. Non Compliant (0%)","0",IF(Z7="2. Somewhat Compliant (25%)","25",IF(Z7="3. Partially Compliant (50%)","50",IF(Z7="4. Mostly Compliant (75%)","75",IF(Z7="5. Fully Compliant (100%)","100"))))))<=65),"50",IF(AND((((_xlfn.XLOOKUP(Assessment!H8,Inherited!A:A,Inherited!B:B))/100)*(_xlfn.XLOOKUP(Assessment!H8,Inherited!A:A,Inherited!E:E)))+(((100-(_xlfn.XLOOKUP(Assessment!H8,Inherited!A:A,Inherited!B:B)))/100)*IF(Z7="1. Non Compliant (0%)","0",IF(Z7="2. Somewhat Compliant (25%)","25",IF(Z7="3. Partially Compliant (50%)","50",IF(Z7="4. Mostly Compliant (75%)","75",IF(Z7="5. Fully Compliant (100%)","100"))))))>=66,(((_xlfn.XLOOKUP(Assessment!H8,Inherited!A:A,Inherited!B:B))/100)*(_xlfn.XLOOKUP(Assessment!H8,Inherited!A:A,Inherited!E:E)))+(((100-(_xlfn.XLOOKUP(Assessment!H8,Inherited!A:A,Inherited!B:B)))/100)*IF(Z7="1. Non Compliant (0%)","0",IF(Z7="2. Somewhat Compliant (25%)","25",IF(Z7="3. Partially Compliant (50%)","50",IF(Z7="4. Mostly Compliant (75%)","75",IF(Z7="5. Fully Compliant (100%)","100"))))))<=89),"75",IF((((_xlfn.XLOOKUP(Assessment!H8,Inherited!A:A,Inherited!B:B))/100)*(_xlfn.XLOOKUP(Assessment!H8,Inherited!A:A,Inherited!E:E)))+(((100-(_xlfn.XLOOKUP(Assessment!H8,Inherited!A:A,Inherited!B:B)))/100)*IF(Z7="1. Non Compliant (0%)","0",IF(Z7="2. Somewhat Compliant (25%)","25",IF(Z7="3. Partially Compliant (50%)","50",IF(Z7="4. Mostly Compliant (75%)","75",IF(Z7="5. Fully Compliant (100%)","100"))))))>=90,"100")))))) -> #N/A | T7: =IF(MATCH(H7,Inherited!A:A),IF((((_xlfn.XLOOKUP(Assessment!H8,Inherited!A:A,Inherited!B:B))/100)*(_xlfn.XLOOKUP(Assessment!H8,Inherited!A:A,Inherited!F:F)))+(((100-(_xlfn.XLOOKUP(Assessment!H8,Inherited!A:A,Inherited!B:B)))/100)*IF(AA7="1. Non Compliant (0%)","0",IF(AA7="2. Somewhat Compliant (25%)","25",IF(AA7="3. Partially Compliant (50%)","50",IF(AA7="4. Mostly Compliant (75%)","75",IF(AA7="5. Fully Compliant (100%)","100"))))))<=10,"0", IF(AND((((_xlfn.XLOOKUP(Assessment!H8,Inherited!A:A,Inherited!B:B))/100)*(_xlfn.XLOOKUP(Assessment!H8,Inherited!A:A,Inherited!F:F)))+(((100-(_xlfn.XLOOKUP(Assessment!H8,Inherited!A:A,Inherited!B:B)))/100)*IF(AA7="1. Non Compliant (0%)","0",IF(AA7="2. Somewhat Compliant (25%)","25",IF(AA7="3. Partially Compliant (50%)","50",IF(AA7="4. Mostly Compliant (75%)","75",IF(AA7="5. Fully Compliant (100%)","100"))))))>=11,(((_xlfn.XLOOKUP(Assessment!H8,Inherited!A:A,Inherited!B:B))/100)*(_xlfn.XLOOKUP(Assessment!H8,Inherited!A:A,Inherited!F:F)))+(((100-(_xlfn.XLOOKUP(Assessment!H8,Inherited!A:A,Inherited!B:B)))/100)*IF(AA7="1. Non Compliant (0%)","0",IF(AA7="2. Somewhat Compliant (25%)","25",IF(AA7="3. Partially Compliant (50%)","50",IF(AA7="4. Mostly Compliant (75%)","75",IF(AA7="5. Fully Compliant (100%)","100"))))))<=32),"25",IF(AND((((_xlfn.XLOOKUP(Assessment!H8,Inherited!A:A,Inherited!B:B))/100)*(_xlfn.XLOOKUP(Assessment!H8,Inherited!A:A,Inherited!F:F)))+(((100-(_xlfn.XLOOKUP(Assessment!H8,Inherited!A:A,Inherited!B:B)))/100)*IF(AA7="1. Non Compliant (0%)","0",IF(AA7="2. Somewhat Compliant (25%)","25",IF(AA7="3. Partially Compliant (50%)","50",IF(AA7="4. Mostly Compliant (75%)","75",IF(AA7="5. Fully Compliant (100%)","100"))))))>=33,(((_xlfn.XLOOKUP(Assessment!H8,Inherited!A:A,Inherited!B:B))/100)*(_xlfn.XLOOKUP(Assessment!H8,Inherited!A:A,Inherited!F:F)))+(((100-(_xlfn.XLOOKUP(Assessment!H8,Inherited!A:A,Inherited!B:B)))/100)*IF(AA7="1. Non Compliant (0%)","0",IF(AA7="2. Somewhat Compliant (25%)","25",IF(AA7="3. Partially Compliant (50%)","50",IF(AA7="4. Mostly Compliant (75%)","75",IF(AA7="5. Fully Compliant (100%)","100"))))))<=65),"50",IF(AND((((_xlfn.XLOOKUP(Assessment!H8,Inherited!A:A,Inherited!B:B))/100)*(_xlfn.XLOOKUP(Assessment!H8,Inherited!A:A,Inherited!F:F)))+(((100-(_xlfn.XLOOKUP(Assessment!H8,Inherited!A:A,Inherited!B:B)))/100)*IF(AA7="1. Non Compliant (0%)","0",IF(AA7="2. Somewhat Compliant (25%)","25",IF(AA7="3. Partially Compliant (50%)","50",IF(AA7="4. Mostly Compliant (75%)","75",IF(AA7="5. Fully Compliant (100%)","100"))))))>=66,(((_xlfn.XLOOKUP(Assessment!H8,Inherited!A:A,Inherited!B:B))/100)*(_xlfn.XLOOKUP(Assessment!H8,Inherited!A:A,Inherited!F:F)))+(((100-(_xlfn.XLOOKUP(Assessment!H8,Inherited!A:A,Inherited!B:B)))/100)*IF(AA7="1. Non Compliant (0%)","0",IF(AA7="2. Somewhat Compliant (25%)","25",IF(AA7="3. Partially Compliant (50%)","50",IF(AA7="4. Mostly Compliant (75%)","75",IF(AA7="5. Fully Compliant (100%)","100"))))))<=89),"75",IF((((_xlfn.XLOOKUP(Assessment!H8,Inherited!A:A,Inherited!B:B))/100)*(_xlfn.XLOOKUP(Assessment!H8,Inherited!A:A,Inherited!F:F)))+(((100-(_xlfn.XLOOKUP(Assessment!H8,Inherited!A:A,Inherited!B:B)))/100)*IF(AA7="1. Non Compliant (0%)","0",IF(AA7="2. Somewhat Compliant (25%)","25",IF(AA7="3. Partially Compliant (50%)","50",IF(AA7="4. Mostly Compliant (75%)","75",IF(AA7="5. Fully Compliant (100%)","100"))))))>=90,"100")))))) -> #N/A | U7: =IF(MATCH(H7,Inherited!A:A),IF((((_xlfn.XLOOKUP(Assessment!H8,Inherited!A:A,Inherited!B:B))/100)*(_xlfn.XLOOKUP(Assessment!H8,Inherited!A:A,Inherited!G:G)))+(((100-(_xlfn.XLOOKUP(Assessment!H8,Inherited!A:A,Inherited!B:B)))/100)*IF(AB7="1. Non Compliant (0%)","0",IF(AB7="2. Somewhat Compliant (25%)","25",IF(AB7="3. Partially Compliant (50%)","50",IF(AB7="4. Mostly Compliant (75%)","75",IF(AB7="5. Fully Compliant (100%)","100"))))))<=10,"0", IF(AND((((_xlfn.XLOOKUP(Assessment!H8,Inherited!A:A,Inherited!B:B))/100)*(_xlfn.XLOOKUP(Assessment!H8,Inherited!A:A,Inherited!G:G)))+(((100-(_xlfn.XLOOKUP(Assessment!H8,Inherited!A:A,Inherited!B:B)))/100)*IF(AB7="1. Non Compliant (0%)","0",IF(AB7="2. Somewhat Compliant (25%)","25",IF(AB7="3. Partially Compliant (50%)","50",IF(AB7="4. Mostly Compliant (75%)","75",IF(AB7="5. Fully Compliant (100%)","100"))))))>=11,(((_xlfn.XLOOKUP(Assessment!H8,Inherited!A:A,Inherited!B:B))/100)*(_xlfn.XLOOKUP(Assessment!H8,Inherited!A:A,Inherited!G:G)))+(((100-(_xlfn.XLOOKUP(Assessment!H8,Inherited!A:A,Inherited!B:B)))/100)*IF(AB7="1. Non Compliant (0%)","0",IF(AB7="2. Somewhat Compliant (25%)","25",IF(AB7="3. Partially Compliant (50%)","50",IF(AB7="4. Mostly Compliant (75%)","75",IF(AB7="5. Fully Compliant (100%)","100"))))))<=32),"25",IF(AND((((_xlfn.XLOOKUP(Assessment!H8,Inherited!A:A,Inherited!B:B))/100)*(_xlfn.XLOOKUP(Assessment!H8,Inherited!A:A,Inherited!G:G)))+(((100-(_xlfn.XLOOKUP(Assessment!H8,Inherited!A:A,Inherited!B:B)))/100)*IF(AB7="1. Non Compliant (0%)","0",IF(AB7="2. Somewhat Compliant (25%)","25",IF(AB7="3. Partially Compliant (50%)","50",IF(AB7="4. Mostly Compliant (75%)","75",IF(AB7="5. Fully Compliant (100%)","100"))))))>=33,(((_xlfn.XLOOKUP(Assessment!H8,Inherited!A:A,Inherited!B:B))/100)*(_xlfn.XLOOKUP(Assessment!H8,Inherited!A:A,Inherited!G:G)))+(((100-(_xlfn.XLOOKUP(Assessment!H8,Inherited!A:A,Inherited!B:B)))/100)*IF(AB7="1. Non Compliant (0%)","0",IF(AB7="2. Somewhat Compliant (25%)","25",IF(AB7="3. Partially Compliant (50%)","50",IF(AB7="4. Mostly Compliant (75%)","75",IF(AB7="5. Fully Compliant (100%)","100"))))))<=65),"50",IF(AND((((_xlfn.XLOOKUP(Assessment!H8,Inherited!A:A,Inherited!B:B))/100)*(_xlfn.XLOOKUP(Assessment!H8,Inherited!A:A,Inherited!G:G)))+(((100-(_xlfn.XLOOKUP(Assessment!H8,Inherited!A:A,Inherited!B:B)))/100)*IF(AB7="1. Non Compliant (0%)","0",IF(AB7="2. Somewhat Compliant (25%)","25",IF(AB7="3. Partially Compliant (50%)","50",IF(AB7="4. Mostly Compliant (75%)","75",IF(AB7="5. Fully Compliant (100%)","100"))))))>=66,(((_xlfn.XLOOKUP(Assessment!H8,Inherited!A:A,Inherited!B:B))/100)*(_xlfn.XLOOKUP(Assessment!H8,Inherited!A:A,Inherited!G:G)))+(((100-(_xlfn.XLOOKUP(Assessment!H8,Inherited!A:A,Inherited!B:B)))/100)*IF(AB7="1. Non Compliant (0%)","0",IF(AB7="2. Somewhat Compliant (25%)","25",IF(AB7="3. Partially Compliant (50%)","50",IF(AB7="4. Mostly Compliant (75%)","75",IF(AB7="5. Fully Compliant (100%)","100"))))))<=89),"75",IF((((_xlfn.XLOOKUP(Assessment!H8,Inherited!A:A,Inherited!B:B))/100)*(_xlfn.XLOOKUP(Assessment!H8,Inherited!A:A,Inherited!G:G)))+(((100-(_xlfn.XLOOKUP(Assessment!H8,Inherited!A:A,Inherited!B:B)))/100)*IF(AB7="1. Non Compliant (0%)","0",IF(AB7="2. Somewhat Compliant (25%)","25",IF(AB7="3. Partially Compliant (50%)","50",IF(AB7="4. Mostly Compliant (75%)","75",IF(AB7="5. Fully Compliant (100%)","100"))))))>=90,"100")))))) -> #N/A | V7: Yes | Z7: 1. Non Compliant (0%) | AK7: Michael Wood - VP of AI Engineering Kyle Smith - IT Operations and AI Expert | AL7: AI policies and procedures are not formally maintained at this time. Documentation will be developed and integrated to existing Merge policies and procedures | AP7: Gap: AI policies and procedures considering the details of the requirement statement are not formally maintained at this time. Recommendation: Management should ensure that AI policies and procedures are developed considering the following: - assesses the following risk criteria: nature and type of uncertainties that can affect outcomes and objectives (both tangible and intangible) - assesses the following risk criteria: how consequences (both positive and negative) and likelihood will be defined and measured - assesses the following risk criteria: time-related factors - assesses the following risk criteria: consistency in the use of measurements - assesses the following risk criteria: how the level of risk is to be determined - assesses the following risk criteria: how combinations and sequences of multiple risks will be taken into account - assesses the following risk criteria: the organization’s capacity | AX7: =_xlfn.CONCAT("A-LIGN finished its review of this control on ",AR7, " during the scheduled fieldwork window (",Intro!$B$4,")."& CHAR(10)& CHAR(10)) -> A-LIGN finished its review of this control on during the scheduled fieldwork window (Fieldwork: xx/xx/xxxx - xx/xx/xxxx). | AY7: =IF(AQ7<>"",(_xlfn.CONCAT("Inheritance note: "& CHAR(10),AQ7& CHAR(10)& CHAR(10))),"") | AZ7: =IFERROR(IF(AD7<>"",_xlfn.CONCAT("Examined the following policy during fieldwork:"& CHAR(10),AD7& CHAR(10)& CHAR(10),IF(AND(X7<>"5. Fully Compliant (100%)",AE7<>""),"Reviewed policy exception note:"& CHAR(10) & AE7 & CHAR(10) & CHAR(10),"")),""),"") | BA7: =IFERROR(IF(AH7<>"",_xlfn.CONCAT("Examined the following process during fieldwork:"& CHAR(10),AH7& CHAR(10)& CHAR(10),IF(AND(Y7<>"5. Fully Compliant (100%)",AI7<>""),"Reviewed process exception note:"& CHAR(10) & AI7 & CHAR(10) & CHAR(10),"")),""),"") | BB7: =IF(AK7<>"",(_xlfn.CONCAT("Inquired of the following workforce member: "& CHAR(10),AK7& CHAR(10)& CHAR(10),"Inquiry lead to the following conclusions: "& CHAR(10),AL7& CHAR(10) & CHAR(10))),"") -> Inquired of the following workforce member: Michael Wood - VP of AI Engineering Kyle Smith - IT Operations and AI Expert Inquiry lead to the following conclusions: AI policies and procedures are not formally maintained at this time. Documentation will be developed and integrated to existing Merge policies and procedures | BC7: =IF(AM7<>"",(_xlfn.CONCAT("Observed the following live during fieldwork: "& CHAR(10),AM7& CHAR(10) & CHAR(10))),"") | BD7: =_xlfn.CONCAT("Examined the following evidence during fieldwork:"& CHAR(10),AN7& CHAR(10)& CHAR(10),IF(AO7<>"","Reviewed evidence note:"& CHAR(10)&AO7& CHAR(10) & CHAR(10),"Reviewed evidence addressed the requirement statement."& CHAR(10) & CHAR(10)),IF(AND(AP7<>"5. Fully Compliant (100%)",AP7<>""),"Reviewed evidence exception note: "& CHAR(10) & AP7 & CHAR(10) & CHAR(10),"")) -> Examined the following evidence during fieldwork: Reviewed evidence addressed the requirement statement. Reviewed evidence exception note: Gap: AI policies and procedures considering the details of the requirement statement are not formally maintained at this time. Recommendation: Management should ensure that AI policies and procedures are developed considering the following: - assesses the following risk criteria: nature and type of uncertainties that can affect outcomes and objectives (both tangible and intangible) - assesses the following risk criteria: how consequences (both positive and negative) and likelihood will be defined and measured - assesses the following risk criteria: time-related factors - assesses the following risk criteria: consistency in the use of measurements - assesses the following risk criteria: how the level of risk is to be determined - assesses the following risk criteria: how combinations and sequences of multiple risks will be taken into account - assesses the following risk criteria: the organization’s capacity | BE7: =IF(AT7<>"",(_xlfn.CONCAT("Examined the following measure/metric during fieldwork:"& CHAR(10),AT7& CHAR(10)& CHAR(10),"Reviewed measure/metric note:"& CHAR(10),AU7 & CHAR(10) & CHAR(10))),"") | BF7: =IF(AV7<>"",(_xlfn.CONCAT("Examined the following measure/metric management during fieldwork:"& CHAR(10),AV7& CHAR(10)& CHAR(10),"Reviewed measure/metric management note:"& CHAR(10),AW7 & CHAR(10) & CHAR(10))),"") | BG7: =_xlfn.CONCAT((IF((COUNTIF('Sample Tables'!B:B,"")>0)=TRUE,_xlfn.CONCAT("",""),IF((COUNTIF('Sample Tables'!B:B,"")>0)=FALSE,""))),) | BH7: =IF(V7="No","Not Applicable: "&W7,(_xlfn.CONCAT(AX7,AY7,AZ7,BA7,BB7,BC7,BD7,BE7,BF7,BG7))) -> A-LIGN finished its review of this control on during the scheduled fieldwork window (Fieldwork: xx/xx/xxxx - xx/xx/xxxx). Inquired of the following workforce member: Michael Wood - VP of AI Engineering Kyle Smith - IT Operations and AI Expert Inquiry lead to the following conclusions: AI policies and procedures are not formally maintained at this time. Documentation will be developed and integrated to existing Merge policies and procedures Examined the following evidence during fieldwork: Reviewed evidence addressed the requirement statement. Reviewed evidence exception note: Gap: AI policies and procedures considering the details of the requirement statement are not formally maintained at this time. Recommendation: Management should ensure that AI policies and procedures are developed considering the following: - assesses the following risk criteria: nature and type of uncertainties that can affect outcomes and objectives (both tangible and intangible) - assesses the following risk criteria: how consequences (both positive and negative) and likelihood will be defined and measured - assesses the following risk criteria: time-related factors - assesses the following risk criteria: consistency in the use of measurements - assesses the following risk criteria: how the level of risk is to be determined - assesses the following risk criteria: how combinations and sequences of multiple risks will be taken into account - assesses the following risk criteria: the organization’s capacity
C8: =IF(V8="No","Not Applicable",(IF(X8="1. Non Compliant (0%)","0",IF(X8="2. Somewhat Compliant (25%)","25",IF(X8="3. Partially Compliant (50%)","50",IF(X8="4. Mostly Compliant (75%)","75",IF(X8="5. Fully Compliant (100%)","100")))))*0.15)+((IF(Y8="1. Non Compliant (0%)","0",IF(Y8="2. Somewhat Compliant (25%)","25",IF(Y8="3. Partially Compliant (50%)","50",IF(Y8="4. Mostly Compliant (75%)","75",IF(Y8="5. Fully Compliant (100%)","100"))))))*0.2)+(IF(Z8="1. Non Compliant (0%)","0",IF(Z8="2. Somewhat Compliant (25%)","25",IF(Z8="3. Partially Compliant (50%)","50",IF(Z8="4. Mostly Compliant (75%)","75",IF(Z8="5. Fully Compliant (100%)","100")))))*0.4)+(IF(AA8="1. Non Compliant (0%)","0",IF(AA8="2. Somewhat Compliant (25%)","25",IF(AA8="3. Partially Compliant (50%)","50",IF(AA8="4. Mostly Compliant (75%)","75",IF(AA8="5. Fully Compliant (100%)","100")))))*0.1)+(IF(AB8="1. Non Compliant (0%)","0",IF(AB8="2. Somewhat Compliant (25%)","25",IF(AB8="3. Partially Compliant (50%)","50",IF(AB8="4. Mostly Compliant (75%)","75",IF(AB8="5. Fully Compliant (100%)","100")))))*0.15)) -> 0 | D8: =IF(AND((_xlfn.XLOOKUP(J8,'Fields & Revisions'!$H:$H,'Fields & Revisions'!$I:$I))<70.99,(OR(Z8="4. Mostly Compliant (75%)",Z8="3. Partially Compliant (50%)",Z8="2. Somewhat Compliant (25%)",Z8="1. Non Compliant (0%)"))),"Yes","No") -> Yes | E8: =IF(ISERROR(VLOOKUP(H8,Scope!A:A,1,FALSE)),"No","Yes") -> Yes | F8: 01 Information Protection Program | G8: 2827.0 | H8: 01.03aISO31000Organizational.2 | I8: ISO 31000 | J8: 03.a Risk Management Program Development | K8: The organization, as part of risk identification, documents its consideration of: |tangible and intangible sources of risk; |causes and events; |threats and opportunities; |vulnerabilities and capabilities; |changes in the external and internal context; |indicators of emerging risks; |the nature and value of assets and resources; |consequences and their impact on objectives; |limitations of knowledge and reliability of information; |time-related factors; |biases, assumptions and beliefs of those involved.|| | L8: Examine evidence that all evaluative elements within the requirement statement have been implemented as defined in the HITRUST scoring rubric, using a sample based test where possible for each evaluative element._x000D_ _x000D_ _x000D_ Example test(s):_x000D_ For example, obtain and examine the risk identification documentation and _x000D_ confirm the organization documented consideration of the elements prescribed in the requirement statement. | M8: Documentation: Risk Management Program - assesses the following risk criteria: tangible and intangible sources of risk - assesses the following risk criteria: causes and events - assesses the following risk criteria: time-related factors - assesses the following risk criteria: changes in the external and internal context - assesses the following risk criteria: how the level of risk is to be determined - assesses the following risk criteria: how combinations and sequences of multiple risks will be taken into account - assesses the following risk criteria: the organization’s capacity - assesses the following risk criteria: threats and opportunities - assesses the following risk criteria: vulnerabilities and capabilities - assesses the following risk criteria: the nature and value of assets and resources - assesses the following risk criteria: consequences and their impact on objectives - assesses the following risk criteria: indicators of emerging risks - assesses the following risk criteria: limitations of knowledge and reliability of information - assesses the following risk criteria: biases, assumptions and beliefs of those involved | N8: No | O8: =_xlfn.XLOOKUP(G8,SRMs!$A:$A,SRMs!$D:$D) -> NO INHERITANCE | P8: =IFERROR(VLOOKUP(H8,Inherited!A:B,2,FALSE),"") | Q8: =IF(MATCH(H8,Inherited!A:A),IF((((_xlfn.XLOOKUP(Assessment!H9,Inherited!A:A,Inherited!B:B))/100)*(_xlfn.XLOOKUP(Assessment!H9,Inherited!A:A,Inherited!C:C)))+(((100-(_xlfn.XLOOKUP(Assessment!H9,Inherited!A:A,Inherited!B:B)))/100)*IF(X8="1. Non Compliant (0%)","0",IF(X8="2. Somewhat Compliant (25%)","25",IF(X8="3. Partially Compliant (50%)","50",IF(X8="4. Mostly Compliant (75%)","75",IF(X8="5. Fully Compliant (100%)","100"))))))<=10,"0", IF(AND((((_xlfn.XLOOKUP(Assessment!H9,Inherited!A:A,Inherited!B:B))/100)*(_xlfn.XLOOKUP(Assessment!H9,Inherited!A:A,Inherited!C:C)))+(((100-(_xlfn.XLOOKUP(Assessment!H9,Inherited!A:A,Inherited!B:B)))/100)*IF(X8="1. Non Compliant (0%)","0",IF(X8="2. Somewhat Compliant (25%)","25",IF(X8="3. Partially Compliant (50%)","50",IF(X8="4. Mostly Compliant (75%)","75",IF(X8="5. Fully Compliant (100%)","100"))))))>=11,(((_xlfn.XLOOKUP(Assessment!H9,Inherited!A:A,Inherited!B:B))/100)*(_xlfn.XLOOKUP(Assessment!H9,Inherited!A:A,Inherited!C:C)))+(((100-(_xlfn.XLOOKUP(Assessment!H9,Inherited!A:A,Inherited!B:B)))/100)*IF(X8="1. Non Compliant (0%)","0",IF(X8="2. Somewhat Compliant (25%)","25",IF(X8="3. Partially Compliant (50%)","50",IF(X8="4. Mostly Compliant (75%)","75",IF(X8="5. Fully Compliant (100%)","100"))))))<=32),"25",IF(AND((((_xlfn.XLOOKUP(Assessment!H9,Inherited!A:A,Inherited!B:B))/100)*(_xlfn.XLOOKUP(Assessment!H9,Inherited!A:A,Inherited!C:C)))+(((100-(_xlfn.XLOOKUP(Assessment!H9,Inherited!A:A,Inherited!B:B)))/100)*IF(X8="1. Non Compliant (0%)","0",IF(X8="2. Somewhat Compliant (25%)","25",IF(X8="3. Partially Compliant (50%)","50",IF(X8="4. Mostly Compliant (75%)","75",IF(X8="5. Fully Compliant (100%)","100"))))))>=33,(((_xlfn.XLOOKUP(Assessment!H9,Inherited!A:A,Inherited!B:B))/100)*(_xlfn.XLOOKUP(Assessment!H9,Inherited!A:A,Inherited!C:C)))+(((100-(_xlfn.XLOOKUP(Assessment!H9,Inherited!A:A,Inherited!B:B)))/100)*IF(X8="1. Non Compliant (0%)","0",IF(X8="2. Somewhat Compliant (25%)","25",IF(X8="3. Partially Compliant (50%)","50",IF(X8="4. Mostly Compliant (75%)","75",IF(X8="5. Fully Compliant (100%)","100"))))))<=65),"50",IF(AND((((_xlfn.XLOOKUP(Assessment!H9,Inherited!A:A,Inherited!B:B))/100)*(_xlfn.XLOOKUP(Assessment!H9,Inherited!A:A,Inherited!C:C)))+(((100-(_xlfn.XLOOKUP(Assessment!H9,Inherited!A:A,Inherited!B:B)))/100)*IF(X8="1. Non Compliant (0%)","0",IF(X8="2. Somewhat Compliant (25%)","25",IF(X8="3. Partially Compliant (50%)","50",IF(X8="4. Mostly Compliant (75%)","75",IF(X8="5. Fully Compliant (100%)","100"))))))>=66,(((_xlfn.XLOOKUP(Assessment!H9,Inherited!A:A,Inherited!B:B))/100)*(_xlfn.XLOOKUP(Assessment!H9,Inherited!A:A,Inherited!C:C)))+(((100-(_xlfn.XLOOKUP(Assessment!H9,Inherited!A:A,Inherited!B:B)))/100)*IF(X8="1. Non Compliant (0%)","0",IF(X8="2. Somewhat Compliant (25%)","25",IF(X8="3. Partially Compliant (50%)","50",IF(X8="4. Mostly Compliant (75%)","75",IF(X8="5. Fully Compliant (100%)","100"))))))<=89),"75",IF((((_xlfn.XLOOKUP(Assessment!H9,Inherited!A:A,Inherited!B:B))/100)*(_xlfn.XLOOKUP(Assessment!H9,Inherited!A:A,Inherited!C:C)))+(((100-(_xlfn.XLOOKUP(Assessment!H9,Inherited!A:A,Inherited!B:B)))/100)*IF(X8="1. Non Compliant (0%)","0",IF(X8="2. Somewhat Compliant (25%)","25",IF(X8="3. Partially Compliant (50%)","50",IF(X8="4. Mostly Compliant (75%)","75",IF(X8="5. Fully Compliant (100%)","100"))))))>=90,"100")))))) -> #N/A | R8: =IF(MATCH(H8,Inherited!A:A),IF((((_xlfn.XLOOKUP(Assessment!H9,Inherited!A:A,Inherited!B:B))/100)*(_xlfn.XLOOKUP(Assessment!H9,Inherited!A:A,Inherited!D:D)))+(((100-(_xlfn.XLOOKUP(Assessment!H9,Inherited!A:A,Inherited!B:B)))/100)*IF(Y8="1. Non Compliant (0%)","0",IF(Y8="2. Somewhat Compliant (25%)","25",IF(Y8="3. Partially Compliant (50%)","50",IF(Y8="4. Mostly Compliant (75%)","75",IF(Y8="5. Fully Compliant (100%)","100"))))))<=10,"0", IF(AND((((_xlfn.XLOOKUP(Assessment!H9,Inherited!A:A,Inherited!B:B))/100)*(_xlfn.XLOOKUP(Assessment!H9,Inherited!A:A,Inherited!D:D)))+(((100-(_xlfn.XLOOKUP(Assessment!H9,Inherited!A:A,Inherited!B:B)))/100)*IF(Y8="1. Non Compliant (0%)","0",IF(Y8="2. Somewhat Compliant (25%)","25",IF(Y8="3. Partially Compliant (50%)","50",IF(Y8="4. Mostly Compliant (75%)","75",IF(Y8="5. Fully Compliant (100%)","100"))))))>=11,(((_xlfn.XLOOKUP(Assessment!H9,Inherited!A:A,Inherited!B:B))/100)*(_xlfn.XLOOKUP(Assessment!H9,Inherited!A:A,Inherited!D:D)))+(((100-(_xlfn.XLOOKUP(Assessment!H9,Inherited!A:A,Inherited!B:B)))/100)*IF(Y8="1. Non Compliant (0%)","0",IF(Y8="2. Somewhat Compliant (25%)","25",IF(Y8="3. Partially Compliant (50%)","50",IF(Y8="4. Mostly Compliant (75%)","75",IF(Y8="5. Fully Compliant (100%)","100"))))))<=32),"25",IF(AND((((_xlfn.XLOOKUP(Assessment!H9,Inherited!A:A,Inherited!B:B))/100)*(_xlfn.XLOOKUP(Assessment!H9,Inherited!A:A,Inherited!D:D)))+(((100-(_xlfn.XLOOKUP(Assessment!H9,Inherited!A:A,Inherited!B:B)))/100)*IF(Y8="1. Non Compliant (0%)","0",IF(Y8="2. Somewhat Compliant (25%)","25",IF(Y8="3. Partially Compliant (50%)","50",IF(Y8="4. Mostly Compliant (75%)","75",IF(Y8="5. Fully Compliant (100%)","100"))))))>=33,(((_xlfn.XLOOKUP(Assessment!H9,Inherited!A:A,Inherited!B:B))/100)*(_xlfn.XLOOKUP(Assessment!H9,Inherited!A:A,Inherited!D:D)))+(((100-(_xlfn.XLOOKUP(Assessment!H9,Inherited!A:A,Inherited!B:B)))/100)*IF(Y8="1. Non Compliant (0%)","0",IF(Y8="2. Somewhat Compliant (25%)","25",IF(Y8="3. Partially Compliant (50%)","50",IF(Y8="4. Mostly Compliant (75%)","75",IF(Y8="5. Fully Compliant (100%)","100"))))))<=65),"50",IF(AND((((_xlfn.XLOOKUP(Assessment!H9,Inherited!A:A,Inherited!B:B))/100)*(_xlfn.XLOOKUP(Assessment!H9,Inherited!A:A,Inherited!D:D)))+(((100-(_xlfn.XLOOKUP(Assessment!H9,Inherited!A:A,Inherited!B:B)))/100)*IF(Y8="1. Non Compliant (0%)","0",IF(Y8="2. Somewhat Compliant (25%)","25",IF(Y8="3. Partially Compliant (50%)","50",IF(Y8="4. Mostly Compliant (75%)","75",IF(Y8="5. Fully Compliant (100%)","100"))))))>=66,(((_xlfn.XLOOKUP(Assessment!H9,Inherited!A:A,Inherited!B:B))/100)*(_xlfn.XLOOKUP(Assessment!H9,Inherited!A:A,Inherited!D:D)))+(((100-(_xlfn.XLOOKUP(Assessment!H9,Inherited!A:A,Inherited!B:B)))/100)*IF(Y8="1. Non Compliant (0%)","0",IF(Y8="2. Somewhat Compliant (25%)","25",IF(Y8="3. Partially Compliant (50%)","50",IF(Y8="4. Mostly Compliant (75%)","75",IF(Y8="5. Fully Compliant (100%)","100"))))))<=89),"75",IF((((_xlfn.XLOOKUP(Assessment!H9,Inherited!A:A,Inherited!B:B))/100)*(_xlfn.XLOOKUP(Assessment!H9,Inherited!A:A,Inherited!D:D)))+(((100-(_xlfn.XLOOKUP(Assessment!H9,Inherited!A:A,Inherited!B:B)))/100)*IF(Y8="1. Non Compliant (0%)","0",IF(Y8="2. Somewhat Compliant (25%)","25",IF(Y8="3. Partially Compliant (50%)","50",IF(Y8="4. Mostly Compliant (75%)","75",IF(Y8="5. Fully Compliant (100%)","100"))))))>=90,"100")))))) -> #N/A | S8: =IF(MATCH(H8,Inherited!A:A),IF((((_xlfn.XLOOKUP(Assessment!H9,Inherited!A:A,Inherited!B:B))/100)*(_xlfn.XLOOKUP(Assessment!H9,Inherited!A:A,Inherited!E:E)))+(((100-(_xlfn.XLOOKUP(Assessment!H9,Inherited!A:A,Inherited!B:B)))/100)*IF(Z8="1. Non Compliant (0%)","0",IF(Z8="2. Somewhat Compliant (25%)","25",IF(Z8="3. Partially Compliant (50%)","50",IF(Z8="4. Mostly Compliant (75%)","75",IF(Z8="5. Fully Compliant (100%)","100"))))))<=10,"0", IF(AND((((_xlfn.XLOOKUP(Assessment!H9,Inherited!A:A,Inherited!B:B))/100)*(_xlfn.XLOOKUP(Assessment!H9,Inherited!A:A,Inherited!E:E)))+(((100-(_xlfn.XLOOKUP(Assessment!H9,Inherited!A:A,Inherited!B:B)))/100)*IF(Z8="1. Non Compliant (0%)","0",IF(Z8="2. Somewhat Compliant (25%)","25",IF(Z8="3. Partially Compliant (50%)","50",IF(Z8="4. Mostly Compliant (75%)","75",IF(Z8="5. Fully Compliant (100%)","100"))))))>=11,(((_xlfn.XLOOKUP(Assessment!H9,Inherited!A:A,Inherited!B:B))/100)*(_xlfn.XLOOKUP(Assessment!H9,Inherited!A:A,Inherited!E:E)))+(((100-(_xlfn.XLOOKUP(Assessment!H9,Inherited!A:A,Inherited!B:B)))/100)*IF(Z8="1. Non Compliant (0%)","0",IF(Z8="2. Somewhat Compliant (25%)","25",IF(Z8="3. Partially Compliant (50%)","50",IF(Z8="4. Mostly Compliant (75%)","75",IF(Z8="5. Fully Compliant (100%)","100"))))))<=32),"25",IF(AND((((_xlfn.XLOOKUP(Assessment!H9,Inherited!A:A,Inherited!B:B))/100)*(_xlfn.XLOOKUP(Assessment!H9,Inherited!A:A,Inherited!E:E)))+(((100-(_xlfn.XLOOKUP(Assessment!H9,Inherited!A:A,Inherited!B:B)))/100)*IF(Z8="1. Non Compliant (0%)","0",IF(Z8="2. Somewhat Compliant (25%)","25",IF(Z8="3. Partially Compliant (50%)","50",IF(Z8="4. Mostly Compliant (75%)","75",IF(Z8="5. Fully Compliant (100%)","100"))))))>=33,(((_xlfn.XLOOKUP(Assessment!H9,Inherited!A:A,Inherited!B:B))/100)*(_xlfn.XLOOKUP(Assessment!H9,Inherited!A:A,Inherited!E:E)))+(((100-(_xlfn.XLOOKUP(Assessment!H9,Inherited!A:A,Inherited!B:B)))/100)*IF(Z8="1. Non Compliant (0%)","0",IF(Z8="2. Somewhat Compliant (25%)","25",IF(Z8="3. Partially Compliant (50%)","50",IF(Z8="4. Mostly Compliant (75%)","75",IF(Z8="5. Fully Compliant (100%)","100"))))))<=65),"50",IF(AND((((_xlfn.XLOOKUP(Assessment!H9,Inherited!A:A,Inherited!B:B))/100)*(_xlfn.XLOOKUP(Assessment!H9,Inherited!A:A,Inherited!E:E)))+(((100-(_xlfn.XLOOKUP(Assessment!H9,Inherited!A:A,Inherited!B:B)))/100)*IF(Z8="1. Non Compliant (0%)","0",IF(Z8="2. Somewhat Compliant (25%)","25",IF(Z8="3. Partially Compliant (50%)","50",IF(Z8="4. Mostly Compliant (75%)","75",IF(Z8="5. Fully Compliant (100%)","100"))))))>=66,(((_xlfn.XLOOKUP(Assessment!H9,Inherited!A:A,Inherited!B:B))/100)*(_xlfn.XLOOKUP(Assessment!H9,Inherited!A:A,Inherited!E:E)))+(((100-(_xlfn.XLOOKUP(Assessment!H9,Inherited!A:A,Inherited!B:B)))/100)*IF(Z8="1. Non Compliant (0%)","0",IF(Z8="2. Somewhat Compliant (25%)","25",IF(Z8="3. Partially Compliant (50%)","50",IF(Z8="4. Mostly Compliant (75%)","75",IF(Z8="5. Fully Compliant (100%)","100"))))))<=89),"75",IF((((_xlfn.XLOOKUP(Assessment!H9,Inherited!A:A,Inherited!B:B))/100)*(_xlfn.XLOOKUP(Assessment!H9,Inherited!A:A,Inherited!E:E)))+(((100-(_xlfn.XLOOKUP(Assessment!H9,Inherited!A:A,Inherited!B:B)))/100)*IF(Z8="1. Non Compliant (0%)","0",IF(Z8="2. Somewhat Compliant (25%)","25",IF(Z8="3. Partially Compliant (50%)","50",IF(Z8="4. Mostly Compliant (75%)","75",IF(Z8="5. Fully Compliant (100%)","100"))))))>=90,"100")))))) -> #N/A | T8: =IF(MATCH(H8,Inherited!A:A),IF((((_xlfn.XLOOKUP(Assessment!H9,Inherited!A:A,Inherited!B:B))/100)*(_xlfn.XLOOKUP(Assessment!H9,Inherited!A:A,Inherited!F:F)))+(((100-(_xlfn.XLOOKUP(Assessment!H9,Inherited!A:A,Inherited!B:B)))/100)*IF(AA8="1. Non Compliant (0%)","0",IF(AA8="2. Somewhat Compliant (25%)","25",IF(AA8="3. Partially Compliant (50%)","50",IF(AA8="4. Mostly Compliant (75%)","75",IF(AA8="5. Fully Compliant (100%)","100"))))))<=10,"0", IF(AND((((_xlfn.XLOOKUP(Assessment!H9,Inherited!A:A,Inherited!B:B))/100)*(_xlfn.XLOOKUP(Assessment!H9,Inherited!A:A,Inherited!F:F)))+(((100-(_xlfn.XLOOKUP(Assessment!H9,Inherited!A:A,Inherited!B:B)))/100)*IF(AA8="1. Non Compliant (0%)","0",IF(AA8="2. Somewhat Compliant (25%)","25",IF(AA8="3. Partially Compliant (50%)","50",IF(AA8="4. Mostly Compliant (75%)","75",IF(AA8="5. Fully Compliant (100%)","100"))))))>=11,(((_xlfn.XLOOKUP(Assessment!H9,Inherited!A:A,Inherited!B:B))/100)*(_xlfn.XLOOKUP(Assessment!H9,Inherited!A:A,Inherited!F:F)))+(((100-(_xlfn.XLOOKUP(Assessment!H9,Inherited!A:A,Inherited!B:B)))/100)*IF(AA8="1. Non Compliant (0%)","0",IF(AA8="2. Somewhat Compliant (25%)","25",IF(AA8="3. Partially Compliant (50%)","50",IF(AA8="4. Mostly Compliant (75%)","75",IF(AA8="5. Fully Compliant (100%)","100"))))))<=32),"25",IF(AND((((_xlfn.XLOOKUP(Assessment!H9,Inherited!A:A,Inherited!B:B))/100)*(_xlfn.XLOOKUP(Assessment!H9,Inherited!A:A,Inherited!F:F)))+(((100-(_xlfn.XLOOKUP(Assessment!H9,Inherited!A:A,Inherited!B:B)))/100)*IF(AA8="1. Non Compliant (0%)","0",IF(AA8="2. Somewhat Compliant (25%)","25",IF(AA8="3. Partially Compliant (50%)","50",IF(AA8="4. Mostly Compliant (75%)","75",IF(AA8="5. Fully Compliant (100%)","100"))))))>=33,(((_xlfn.XLOOKUP(Assessment!H9,Inherited!A:A,Inherited!B:B))/100)*(_xlfn.XLOOKUP(Assessment!H9,Inherited!A:A,Inherited!F:F)))+(((100-(_xlfn.XLOOKUP(Assessment!H9,Inherited!A:A,Inherited!B:B)))/100)*IF(AA8="1. Non Compliant (0%)","0",IF(AA8="2. Somewhat Compliant (25%)","25",IF(AA8="3. Partially Compliant (50%)","50",IF(AA8="4. Mostly Compliant (75%)","75",IF(AA8="5. Fully Compliant (100%)","100"))))))<=65),"50",IF(AND((((_xlfn.XLOOKUP(Assessment!H9,Inherited!A:A,Inherited!B:B))/100)*(_xlfn.XLOOKUP(Assessment!H9,Inherited!A:A,Inherited!F:F)))+(((100-(_xlfn.XLOOKUP(Assessment!H9,Inherited!A:A,Inherited!B:B)))/100)*IF(AA8="1. Non Compliant (0%)","0",IF(AA8="2. Somewhat Compliant (25%)","25",IF(AA8="3. Partially Compliant (50%)","50",IF(AA8="4. Mostly Compliant (75%)","75",IF(AA8="5. Fully Compliant (100%)","100"))))))>=66,(((_xlfn.XLOOKUP(Assessment!H9,Inherited!A:A,Inherited!B:B))/100)*(_xlfn.XLOOKUP(Assessment!H9,Inherited!A:A,Inherited!F:F)))+(((100-(_xlfn.XLOOKUP(Assessment!H9,Inherited!A:A,Inherited!B:B)))/100)*IF(AA8="1. Non Compliant (0%)","0",IF(AA8="2. Somewhat Compliant (25%)","25",IF(AA8="3. Partially Compliant (50%)","50",IF(AA8="4. Mostly Compliant (75%)","75",IF(AA8="5. Fully Compliant (100%)","100"))))))<=89),"75",IF((((_xlfn.XLOOKUP(Assessment!H9,Inherited!A:A,Inherited!B:B))/100)*(_xlfn.XLOOKUP(Assessment!H9,Inherited!A:A,Inherited!F:F)))+(((100-(_xlfn.XLOOKUP(Assessment!H9,Inherited!A:A,Inherited!B:B)))/100)*IF(AA8="1. Non Compliant (0%)","0",IF(AA8="2. Somewhat Compliant (25%)","25",IF(AA8="3. Partially Compliant (50%)","50",IF(AA8="4. Mostly Compliant (75%)","75",IF(AA8="5. Fully Compliant (100%)","100"))))))>=90,"100")))))) -> #N/A | U8: =IF(MATCH(H8,Inherited!A:A),IF((((_xlfn.XLOOKUP(Assessment!H9,Inherited!A:A,Inherited!B:B))/100)*(_xlfn.XLOOKUP(Assessment!H9,Inherited!A:A,Inherited!G:G)))+(((100-(_xlfn.XLOOKUP(Assessment!H9,Inherited!A:A,Inherited!B:B)))/100)*IF(AB8="1. Non Compliant (0%)","0",IF(AB8="2. Somewhat Compliant (25%)","25",IF(AB8="3. Partially Compliant (50%)","50",IF(AB8="4. Mostly Compliant (75%)","75",IF(AB8="5. Fully Compliant (100%)","100"))))))<=10,"0", IF(AND((((_xlfn.XLOOKUP(Assessment!H9,Inherited!A:A,Inherited!B:B))/100)*(_xlfn.XLOOKUP(Assessment!H9,Inherited!A:A,Inherited!G:G)))+(((100-(_xlfn.XLOOKUP(Assessment!H9,Inherited!A:A,Inherited!B:B)))/100)*IF(AB8="1. Non Compliant (0%)","0",IF(AB8="2. Somewhat Compliant (25%)","25",IF(AB8="3. Partially Compliant (50%)","50",IF(AB8="4. Mostly Compliant (75%)","75",IF(AB8="5. Fully Compliant (100%)","100"))))))>=11,(((_xlfn.XLOOKUP(Assessment!H9,Inherited!A:A,Inherited!B:B))/100)*(_xlfn.XLOOKUP(Assessment!H9,Inherited!A:A,Inherited!G:G)))+(((100-(_xlfn.XLOOKUP(Assessment!H9,Inherited!A:A,Inherited!B:B)))/100)*IF(AB8="1. Non Compliant (0%)","0",IF(AB8="2. Somewhat Compliant (25%)","25",IF(AB8="3. Partially Compliant (50%)","50",IF(AB8="4. Mostly Compliant (75%)","75",IF(AB8="5. Fully Compliant (100%)","100"))))))<=32),"25",IF(AND((((_xlfn.XLOOKUP(Assessment!H9,Inherited!A:A,Inherited!B:B))/100)*(_xlfn.XLOOKUP(Assessment!H9,Inherited!A:A,Inherited!G:G)))+(((100-(_xlfn.XLOOKUP(Assessment!H9,Inherited!A:A,Inherited!B:B)))/100)*IF(AB8="1. Non Compliant (0%)","0",IF(AB8="2. Somewhat Compliant (25%)","25",IF(AB8="3. Partially Compliant (50%)","50",IF(AB8="4. Mostly Compliant (75%)","75",IF(AB8="5. Fully Compliant (100%)","100"))))))>=33,(((_xlfn.XLOOKUP(Assessment!H9,Inherited!A:A,Inherited!B:B))/100)*(_xlfn.XLOOKUP(Assessment!H9,Inherited!A:A,Inherited!G:G)))+(((100-(_xlfn.XLOOKUP(Assessment!H9,Inherited!A:A,Inherited!B:B)))/100)*IF(AB8="1. Non Compliant (0%)","0",IF(AB8="2. Somewhat Compliant (25%)","25",IF(AB8="3. Partially Compliant (50%)","50",IF(AB8="4. Mostly Compliant (75%)","75",IF(AB8="5. Fully Compliant (100%)","100"))))))<=65),"50",IF(AND((((_xlfn.XLOOKUP(Assessment!H9,Inherited!A:A,Inherited!B:B))/100)*(_xlfn.XLOOKUP(Assessment!H9,Inherited!A:A,Inherited!G:G)))+(((100-(_xlfn.XLOOKUP(Assessment!H9,Inherited!A:A,Inherited!B:B)))/100)*IF(AB8="1. Non Compliant (0%)","0",IF(AB8="2. Somewhat Compliant (25%)","25",IF(AB8="3. Partially Compliant (50%)","50",IF(AB8="4. Mostly Compliant (75%)","75",IF(AB8="5. Fully Compliant (100%)","100"))))))>=66,(((_xlfn.XLOOKUP(Assessment!H9,Inherited!A:A,Inherited!B:B))/100)*(_xlfn.XLOOKUP(Assessment!H9,Inherited!A:A,Inherited!G:G)))+(((100-(_xlfn.XLOOKUP(Assessment!H9,Inherited!A:A,Inherited!B:B)))/100)*IF(AB8="1. Non Compliant (0%)","0",IF(AB8="2. Somewhat Compliant (25%)","25",IF(AB8="3. Partially Compliant (50%)","50",IF(AB8="4. Mostly Compliant (75%)","75",IF(AB8="5. Fully Compliant (100%)","100"))))))<=89),"75",IF((((_xlfn.XLOOKUP(Assessment!H9,Inherited!A:A,Inherited!B:B))/100)*(_xlfn.XLOOKUP(Assessment!H9,Inherited!A:A,Inherited!G:G)))+(((100-(_xlfn.XLOOKUP(Assessment!H9,Inherited!A:A,Inherited!B:B)))/100)*IF(AB8="1. Non Compliant (0%)","0",IF(AB8="2. Somewhat Compliant (25%)","25",IF(AB8="3. Partially Compliant (50%)","50",IF(AB8="4. Mostly Compliant (75%)","75",IF(AB8="5. Fully Compliant (100%)","100"))))))>=90,"100")))))) -> #N/A | V8: Yes | Z8: 1. Non Compliant (0%) | AK8: Michael Wood - VP of AI Engineering Kyle Smith - IT Operations and AI Expert | AL8: AI policies and procedures are not formally maintained at this time. Documentation will be developed and integrated to existing Merge policies and procedures | AP8: Gap: AI policies and procedures considering the details of the requirement statement are not formally maintained at this time. Recommendation: Management should ensure that AI policies and procedures are developed considering the following: - assesses the following risk criteria: tangible and intangible sources of risk - assesses the following risk criteria: causes and events - assesses the following risk criteria: time-related factors - assesses the following risk criteria: changes in the external and internal context - assesses the following risk criteria: how the level of risk is to be determined - assesses the following risk criteria: how combinations and sequences of multiple risks will be taken into account - assesses the following risk criteria: the organization’s capacity - assesses the following risk criteria: threats and opportunities - assesses the following risk criteria: vulnerabilities and capabilities - assesses the following risk criteria: the nature and value of assets and resources - assesses the following risk criteria: consequences and their impact on objectives - assesses the following risk criteria: indicators of emerging risks - assesses the following risk criteria: limitations of knowledge and reliability of information - assesses the following risk criteria: biases, assumptions and beliefs of those involved | AX8: =_xlfn.CONCAT("A-LIGN finished its review of this control on ",AR8, " during the scheduled fieldwork window (",Intro!$B$4,")."& CHAR(10)& CHAR(10)) -> A-LIGN finished its review of this control on during the scheduled fieldwork window (Fieldwork: xx/xx/xxxx - xx/xx/xxxx). | AY8: =IF(AQ8<>"",(_xlfn.CONCAT("Inheritance note: "& CHAR(10),AQ8& CHAR(10)& CHAR(10))),"") | AZ8: =IFERROR(IF(AD8<>"",_xlfn.CONCAT("Examined the following policy during fieldwork:"& CHAR(10),AD8& CHAR(10)& CHAR(10),IF(AND(X8<>"5. Fully Compliant (100%)",AE8<>""),"Reviewed policy exception note:"& CHAR(10) & AE8 & CHAR(10) & CHAR(10),"")),""),"") | BA8: =IFERROR(IF(AH8<>"",_xlfn.CONCAT("Examined the following process during fieldwork:"& CHAR(10),AH8& CHAR(10)& CHAR(10),IF(AND(Y8<>"5. Fully Compliant (100%)",AI8<>""),"Reviewed process exception note:"& CHAR(10) & AI8 & CHAR(10) & CHAR(10),"")),""),"") | BB8: =IF(AK8<>"",(_xlfn.CONCAT("Inquired of the following workforce member: "& CHAR(10),AK8& CHAR(10)& CHAR(10),"Inquiry lead to the following conclusions: "& CHAR(10),AL8& CHAR(10) & CHAR(10))),"") -> Inquired of the following workforce member: Michael Wood - VP of AI Engineering Kyle Smith - IT Operations and AI Expert Inquiry lead to the following conclusions: AI policies and procedures are not formally maintained at this time. Documentation will be developed and integrated to existing Merge policies and procedures | BC8: =IF(AM8<>"",(_xlfn.CONCAT("Observed the following live during fieldwork: "& CHAR(10),AM8& CHAR(10) & CHAR(10))),"") | BD8: =_xlfn.CONCAT("Examined the following evidence during fieldwork:"& CHAR(10),AN8& CHAR(10)& CHAR(10),IF(AO8<>"","Reviewed evidence note:"& CHAR(10)&AO8& CHAR(10) & CHAR(10),"Reviewed evidence addressed the requirement statement."& CHAR(10) & CHAR(10)),IF(AND(AP8<>"5. Fully Compliant (100%)",AP8<>""),"Reviewed evidence exception note: "& CHAR(10) & AP8 & CHAR(10) & CHAR(10),"")) -> Examined the following evidence during fieldwork: Reviewed evidence addressed the requirement statement. Reviewed evidence exception note: Gap: AI policies and procedures considering the details of the requirement statement are not formally maintained at this time. Recommendation: Management should ensure that AI policies and procedures are developed considering the following: - assesses the following risk criteria: tangible and intangible sources of risk - assesses the following risk criteria: causes and events - assesses the following risk criteria: time-related factors - assesses the following risk criteria: changes in the external and internal context - assesses the following risk criteria: how the level of risk is to be determined - assesses the following risk criteria: how combinations and sequences of multiple risks will be taken into account - assesses the following risk criteria: the organization’s capacity - assesses the following risk criteria: threats and opportunities - assesses the following risk criteria: vulnerabilities and capabilities - assesses the following risk criteria: the nature and value of assets and resources - assesses the following risk criteria: consequences and their impact on objectives - assesses the following risk criteria: indicators of emerging risks - assesses the following risk criteria: limitations of knowledge and reliability of information - assesses the following risk criteria: biases, assumptions and beliefs of those involved | BE8: =IF(AT8<>"",(_xlfn.CONCAT("Examined the following measure/metric during fieldwork:"& CHAR(10),AT8& CHAR(10)& CHAR(10),"Reviewed measure/metric note:"& CHAR(10),AU8 & CHAR(10) & CHAR(10))),"") | BF8: =IF(AV8<>"",(_xlfn.CONCAT("Examined the following measure/metric management during fieldwork:"& CHAR(10),AV8& CHAR(10)& CHAR(10),"Reviewed measure/metric management note:"& CHAR(10),AW8 & CHAR(10) & CHAR(10))),"") | BG8: =_xlfn.CONCAT((IF((COUNTIF('Sample Tables'!B:B,"")>0)=TRUE,_xlfn.CONCAT("",""),IF((COUNTIF('Sample Tables'!B:B,"")>0)=FALSE,""))),) | BH8: =IF(V8="No","Not Applicable: "&W8,(_xlfn.CONCAT(AX8,AY8,AZ8,BA8,BB8,BC8,BD8,BE8,BF8,BG8))) -> A-LIGN finished its review of this control on during the scheduled fieldwork window (Fieldwork: xx/xx/xxxx - xx/xx/xxxx). Inquired of the following workforce member: Michael Wood - VP of AI Engineering Kyle Smith - IT Operations and AI Expert Inquiry lead to the following conclusions: AI policies and procedures are not formally maintained at this time. Documentation will be developed and integrated to existing Merge policies and procedures Examined the following evidence during fieldwork: Reviewed evidence addressed the requirement statement. Reviewed evidence exception note: Gap: AI policies and procedures considering the details of the requirement statement are not formally maintained at this time. Recommendation: Management should ensure that AI policies and procedures are developed considering the following: - assesses the following risk criteria: tangible and intangible sources of risk - assesses the following risk criteria: causes and events - assesses the following risk criteria: time-related factors - assesses the following risk criteria: changes in the external and internal context - assesses the following risk criteria: how the level of risk is to be determined - assesses the following risk criteria: how combinations and sequences of multiple risks will be taken into account - assesses the following risk criteria: the organization’s capacity - assesses the following risk criteria: threats and opportunities - assesses the following risk criteria: vulnerabilities and capabilities - assesses the following risk criteria: the nature and value of assets and resources - assesses the following risk criteria: consequences and their impact on objectives - assesses the following risk criteria: indicators of emerging risks - assesses the following risk criteria: limitations of knowledge and reliability of information - assesses the following risk criteria: biases, assumptions and beliefs of those involved
